Workbook

Sheet Q1 Base
B1: Policy information - portfolio of 25-year term assurance policies | O1: Mortality Rate
B3: Policyholder age at start of policy | C3: 32
B4: Total premium | C4: 5000 | D4: per annum, payable annually in advance, ceasing immediately on death | M4: Age | O4: qx
B5: Sum assured | C5: 2500000 | D5: payable at the end of the year of death | M5: 30 | O5: 0.0005834
B6: The policy ceases on the payment of a benefit | M6: 31 | O6: 0.0006232
M7: 32 | O7: 0.0007463
M8: 33 | O8: 0.0007344
B9: Reserving assumptions | M9: 34 | O9: 0.0007952
M10: 35 | O10: 0.0008471
B11: Mortality | C11: See table on right | M11: 36 | O11: 0.0009746
B12: Commission | C12: 0.02 | D12: of all premiums, including the premium in the first year. | M12: 37 | O12: 0.0009703
B13: Expenses | C13: 1000 | D13: per annum, at the start of each year, including the first year. | M13: 38 | O13: 0.0010281
B14: Risk discount rate | C14: 0.0575 | D14: per annum | M14: 39 | O14: 0.0011376
M15: 40 | O15: 0.0012492
B16: You should ignore claim expenses. | M16: 41 | O16: 0.0014165
M17: 42 | O17: 0.0014904
M18: 43 | O18: 0.0016599
M19: 44 | O19: 0.0017666
M20: 45 | O20: 0.0018494
M21: 46 | O21: 0.001982
M22: 47 | O22: 0.0023176
M23: 48 | O23: 0.0023668
M24: 49 | O24: 0.0026407
M25: 50 | O25: 0.0029207
M26: 51 | O26: 0.0029822
M27: 52 | O27: 0.0032392
M28: 53 | O28: 0.0034328
... M35: 60 | O35: 0.0068894

Sheet Q1
E1: ='Q1 Base'!C14 -> 0.0575 | G1: ='Q1 Base'!C4 -> 5000 | H1: ='Q1 Base'!C13 -> 1000 | I1: ='Q1 Base'!C12 -> 0.02 | J1: ='Q1 Base'!C5 -> 2500000
C2: [1] | D2: [1] | E2: [2] | F2: [2] | G2: [2] | H2: [2] | I2: [1] | J2: [2] | K2: [1] | L2: [1] | M2: [1] | N2: [2] | O2: [2] | P2: [2] | Q2: [7]
A3: Policy Year | B3: Age at start | C3: Mortality qx | D3: Survival px | E3: TAx:<n> | F3: aduex:<n> | G3: PV premiums to start year | H3: PV of expenses to start year | I3: PV of commission to start year | J3: PV of Benefits to start year | K3: Prospective Reserve at BOY | L3: Prospective Reserve at EOY | M3: tpx | N3: TAx:<n> | O3: aduex:<n> | P3: Retro: Alternative Calculation | Q3: Retrospective reserve (Recursive calculation)
A4: 1 | B4: 32 | C4: ='Q1 Base'!O7 -> 0.0007463 | D4: =1-C4 -> 0.9992537 | E4: =(C4+E5*D4)/(1+$E$1) -> 0.021060298 | F4: =1+(F5*D4/(1+$E$1)) -> 13.685522 | G4: =$G$1*F4 -> 68427.609 | H4: =$H$1*F4 -> 13685.522 | I4: =$G$1*$I$1*F4 -> 1368.5522 | J4: =$J$1*E4 -> 52650.744 | K4: =J4+H4+I4-G4 -> -722.79085 | L4: =K5 -> 1495.2646 | M4: =D4 -> 0.9992537 | N4: =C4/(1+$E$1) -> 0.00070572104 | O4: 1 | P4: =(($G$1*(1-$I$1)-$H$1)*O4-$J$1*N4)/M4*(1+$E$1)^A4 -> 2260.1868 | Q4: =(($G$1*(1-$I$1)+0-$H$1)*(1+$E$1)-$J$1*C4)/D4 -> 2260.1868
A5: 2 | B5: 33 | C5: ='Q1 Base'!O8 -> 0.0007344 | D5: =1-C5 -> 0.9992656 | E5: =(C5+E6*D5)/(1+$E$1) -> 0.021541041 | F5: =1+(F6*D5/(1+$E$1)) -> 13.424958 | G5: =$G$1*F5 -> 67124.792 | H5: =$H$1*F5 -> 13424.958 | I5: =$G$1*$I$1*F5 -> 1342.4958 | J5: =$J$1*E5 -> 53852.602 | K5: =J5+H5+I5-G5 -> 1495.2646 | L5: =K6 -> 3872.3362 | M5: =M4*D5 -> 0.99851985 | N5: =N4+C5/(1+$E$1)^A5*M4 -> 0.0013619383 | O5: =O4+M4/(1+$E$1)^A4 -> 1.9449208 | P5: =(($G$1*(1-$I$1)-$H$1)*O5-$J$1*N5)/M5*(1+$E$1)^A5 -> 4681.8359 | Q5: =(($G$1*(1-$I$1)+Q4-$H$1)*(1+$E$1)-$J$1*C5)/D5 -> 4681.8359
A6: 3 | B6: 34 | C6: ='Q1 Base'!O9 -> 0.0007952 | D6: =1-C6 -> 0.9992048 | E6: =(C6+E7*D6)/(1+$E$1) -> 0.022061453 | F6: =1+(F7*D6/(1+$E$1)) -> 13.14905 | G6: =$G$1*F6 -> 65745.251 | H6: =$H$1*F6 -> 13149.05 | I6: =$G$1*$I$1*F6 -> 1314.905 | J6: =$J$1*E6 -> 55153.632 | K6: =J6+H6+I6-G6 -> 3872.3362 | L6: =K7 -> 6236.2045 | M6: =M5*D6 -> 0.99772583 | N6: =N5+C6/(1+$E$1)^A6*M5 -> 0.0020333547 | O6: =O5+M5/(1+$E$1)^A5 -> 2.8378066 | P6: =(($G$1*(1-$I$1)-$H$1)*O6-$J$1*N6)/M6*(1+$E$1)^A6 -> 7092.9317 | Q6: =(($G$1*(1-$I$1)+Q5-$H$1)*(1+$E$1)-$J$1*C6)/D6 -> 7092.9317 | R6: 1 | S6: Picking up correct mortality rates
A7: 4 | B7: 35 | C7: ='Q1 Base'!O10 -> 0.0008471 | D7: =1-C7 -> 0.9991529 | E7: =(C7+E8*D7)/(1+$E$1) -> 0.02255272 | F7: =1+(F8*D7/(1+$E$1)) -> 12.857845 | G7: =$G$1*F7 -> 64289.226 | H7: =$H$1*F7 -> 12857.845 | I7: =$G$1*$I$1*F7 -> 1285.7845 | J7: =$J$1*E7 -> 56381.801 | K7: =J7+H7+I7-G7 -> 6236.2045 | L7: =K8 -> 8608.5786 | M7: =M6*D7 -> 0.99688065 | N7: =N6+C7/(1+$E$1)^A7*M6 -> 0.0027091644 | O7: =O6+M6/(1+$E$1)^A6 -> 3.6814717 | P7: =(($G$1*(1-$I$1)-$H$1)*O7-$J$1*N7)/M7*(1+$E$1)^A7 -> 9515.3357 | Q7: =(($G$1*(1-$I$1)+Q6-$H$1)*(1+$E$1)-$J$1*C7)/D7 -> 9515.3357 | R7: 1 | S7: Survival probability
A8: 5 | B8: 36 | C8: ='Q1 Base'!O11 -> 0.0009746 | D8: =1-C8 -> 0.9990254 | E8: =(C8+E9*D8)/(1+$E$1) -> 0.023021904 | F8: =1+(F9*D8/(1+$E$1)) -> 12.550303 | G8: =$G$1*F8 -> 62751.513 | H8: =$H$1*F8 -> 12550.303 | I8: =$G$1*$I$1*F8 -> 1255.0303 | J8: =$J$1*E8 -> 57554.759 | K8: =J8+H8+I8-G8 -> 8608.5786 | L8: =K9 -> 10801.849 | M8: =M7*D8 -> 0.99590909 | N8: =N7+C8/(1+$E$1)^A8*M7 -> 0.0034437928 | O8: =O7+M7/(1+$E$1)^A7 -> 4.478588 | P8: =(($G$1*(1-$I$1)-$H$1)*O8-$J$1*N8)/M8*(1+$E$1)^A8 -> 11761.68 | Q8: =(($G$1*(1-$I$1)+Q7-$H$1)*(1+$E$1)-$J$1*C8)/D8 -> 11761.68 | R8: 2 | S8: PV of premiums
A9: 6 | B9: 37 | C9: ='Q1 Base'!O12 -> 0.0009703 | D9: =1-C9 -> 0.9990297 | E9: =(C9+E10*D9)/(1+$E$1) -> 0.023393863 | F9: =1+(F10*D9/(1+$E$1)) -> 12.226361 | G9: =$G$1*F9 -> 61131.804 | H9: =$H$1*F9 -> 12226.361 | I9: =$G$1*$I$1*F9 -> 1222.6361 | J9: =$J$1*E9 -> 58484.657 | K9: =J9+H9+I9-G9 -> 10801.849 | L9: =K10 -> 13134.2 | M9: =M8*D9 -> 0.99494276 | N9: =N8+C9/(1+$E$1)^A9*M8 -> 0.0041347378 | O9: =O8+M8/(1+$E$1)^A8 -> 5.2316276 | P9: =(($G$1*(1-$I$1)-$H$1)*O9-$J$1*N9)/M9*(1+$E$1)^A9 -> 14150.207 | Q9: =(($G$1*(1-$I$1)+Q8-$H$1)*(1+$E$1)-$J$1*C9)/D9 -> 14150.207 | R9: 2 | S9: PV of expenses
A10: 7 | B10: 38 | C10: ='Q1 Base'!O13 -> 0.0010281 | D10: =1-C10 -> 0.9989719 | E10: =(C10+E11*D10)/(1+$E$1) -> 0.023791795 | F10: =1+(F11*D10/(1+$E$1)) -> 11.883407 | G10: =$G$1*F10 -> 59417.035 | H10: =$H$1*F10 -> 11883.407 | I10: =$G$1*$I$1*F10 -> 1188.3407 | J10: =$J$1*E10 -> 59479.487 | K10: =J10+H10+I10-G10 -> 13134.2 | L10: =K11 -> 15459.31 | M10: =M9*D10 -> 0.99391986 | N10: =N9+C10/(1+$E$1)^A10*M9 -> 0.004826363 | O10: =O9+M9/(1+$E$1)^A9 -> 5.9430308 | P10: =(($G$1*(1-$I$1)-$H$1)*O10-$J$1*N10)/M10*(1+$E$1)^A10 -> 16534.843 | Q10: =(($G$1*(1-$I$1)+Q9-$H$1)*(1+$E$1)-$J$1*C10)/D10 -> 16534.843 | R10: 1 | S10: PV of commission
A11: 8 | B11: 39 | C11: ='Q1 Base'!O14 -> 0.0011376 | D11: =1-C11 -> 0.9988624 | E11: =(C11+E12*D11)/(1+$E$1) -> 0.024156558 | F11: =1+(F12*D11/(1+$E$1)) -> 11.521048 | G11: =$G$1*F11 -> 57605.239 | H11: =$H$1*F11 -> 11521.048 | I11: =$G$1*$I$1*F11 -> 1152.1048 | J11: =$J$1*E11 -> 60391.396 | K11: =J11+H11+I11-G11 -> 15459.31 | L11: =K12 -> 17648.547 | M11: =M10*D11 -> 0.99278918 | N11: =N10+C11/(1+$E$1)^A11*M10 -> 0.0055492958 | O11: =O10+M10/(1+$E$1)^A10 -> 6.6150609 | P11: =(($G$1*(1-$I$1)-$H$1)*O11-$J$1*N11)/M11*(1+$E$1)^A11 -> 18787.219 | Q11: =(($G$1*(1-$I$1)+Q10-$H$1)*(1+$E$1)-$J$1*C11)/D11 -> 18787.219 | R11: 2 | S11: PV of benefits
A12: 9 | B12: 40 | C12: ='Q1 Base'!O15 -> 0.0012492 | D12: =1-C12 -> 0.9987508 | E12: =(C12+E13*D12)/(1+$E$1) -> 0.024435759 | F12: =1+(F13*D12/(1+$E$1)) -> 11.138679 | G12: =$G$1*F12 -> 55693.397 | H12: =$H$1*F12 -> 11138.679 | I12: =$G$1*$I$1*F12 -> 1113.8679 | J12: =$J$1*E12 -> 61089.397 | K12: =J12+H12+I12-G12 -> 17648.547 | L12: =K13 -> 19689.185 | M12: =M11*D12 -> 0.99154898 | N12: =N11+C12/(1+$E$1)^A12*M11 -> 0.0062991307 | O12: =O11+M11/(1+$E$1)^A11 -> 7.2498275 | P12: =(($G$1*(1-$I$1)-$H$1)*O12-$J$1*N12)/M12*(1+$E$1)^A12 -> 20894.836 | Q12: =(($G$1*(1-$I$1)+Q11-$H$1)*(1+$E$1)-$J$1*C12)/D12 -> 20894.836
A13: 10 | B13: 41 | C13: ='Q1 Base'!O16 -> 0.0014165 | D13: =1-C13 -> 0.9985835 | E13: =(C13+E14*D13)/(1+$E$1) -> 0.024622373 | F13: =1+(F14*D13/(1+$E$1)) -> 10.735064 | G13: =$G$1*F13 -> 53675.318 | H13: =$H$1*F13 -> 10735.064 | I13: =$G$1*$I$1*F13 -> 1073.5064 | J13: =$J$1*E13 -> 61555.933 | K13: =J13+H13+I13-G13 -> 19689.185 | L13: =K14 -> 21434.675 | M13: =M12*D13 -> 0.99014446 | N13: =N12+C13/(1+$E$1)^A13*M12 -> 0.0071021518 | O13: =O12+M12/(1+$E$1)^A12 -> 7.8493297 | P13: =(($G$1*(1-$I$1)-$H$1)*O13-$J$1*N13)/M13*(1+$E$1)^A13 -> 22711.46 | Q13: =(($G$1*(1-$I$1)+Q12-$H$1)*(1+$E$1)-$J$1*C13)/D13 -> 22711.46 | R13: 2 | S13: Prosp: TAx:<n> calculation
A14: 11 | B14: 42 | C14: ='Q1 Base'!O17 -> 0.0014904 | D14: =1-C14 -> 0.9985096 | E14: =(C14+E15*D14)/(1+$E$1) -> 0.024656586 | F14: =1+(F15*D14/(1+$E$1)) -> 10.309433 | G14: =$G$1*F14 -> 51547.166 | H14: =$H$1*F14 -> 10309.433 | I14: =$G$1*$I$1*F14 -> 1030.9433 | J14: =$J$1*E14 -> 61641.464 | K14: =J14+H14+I14-G14 -> 21434.675 | L14: =K15 -> 23099.847 | M14: =M13*D14 -> 0.98866874 | N14: =N13+C14/(1+$E$1)^A14*M13 -> 0.0078999945 | O14: =O13+M13/(1+$E$1)^A13 -> 8.4154318 | P14: =(($G$1*(1-$I$1)-$H$1)*O14-$J$1*N14)/M14*(1+$E$1)^A14 -> 24452.062 | Q14: =(($G$1*(1-$I$1)+Q13-$H$1)*(1+$E$1)-$J$1*C14)/D14 -> 24452.062 | R14: 2 | S14: Prosp: aduex:<n> calculation
A15: 12 | B15: 43 | C15: ='Q1 Base'!O18 -> 0.0016599 | D15: =1-C15 -> 0.9983401 | E15: =(C15+E16*D15)/(1+$E$1) -> 0.024620634 | F15: =1+(F16*D15/(1+$E$1)) -> 9.85942 | G15: =$G$1*F15 -> 49297.1 | H15: =$H$1*F15 -> 9859.42 | I15: =$G$1*$I$1*F15 -> 985.942 | J15: =$J$1*E15 -> 61551.585 | K15: =J15+H15+I15-G15 -> 23099.847 | L15: =K16 -> 24443.161 | M15: =M14*D15 -> 0.98702765 | N15: =N14+C15/(1+$E$1)^A15*M14 -> 0.0087390066 | O15: =O14+M14/(1+$E$1)^A14 -> 8.9499552 | P15: =(($G$1*(1-$I$1)-$H$1)*O15-$J$1*N15)/M15*(1+$E$1)^A15 -> 25875.507 | Q15: =(($G$1*(1-$I$1)+Q14-$H$1)*(1+$E$1)-$J$1*C15)/D15 -> 25875.507 | R15: 1 | S15: Prosp: including all elements
A16: 13 | B16: 44 | C16: ='Q1 Base'!O19 -> 0.0017666 | D16: =1-C16 -> 0.9982334 | E16: =(C16+E17*D16)/(1+$E$1) -> 0.02441695 | F16: =1+(F17*D16/(1+$E$1)) -> 9.3844138 | G16: =$G$1*F16 -> 46922.069 | H16: =$H$1*F16 -> 9384.4138 | I16: =$G$1*$I$1*F16 -> 938.44138 | J16: =$J$1*E16 -> 61042.375 | K16: =J16+H16+I16-G16 -> 24443.161 | L16: =K17 -> 25601.621 | M16: =M15*D16 -> 0.98528397 | N16: =N15+C16/(1+$E$1)^A16*M15 -> 0.0095819971 | O16: =O15+M15/(1+$E$1)^A15 -> 9.4545756 | P16: =(($G$1*(1-$I$1)-$H$1)*O16-$J$1*N16)/M16*(1+$E$1)^A16 -> 27119.007 | Q16: =(($G$1*(1-$I$1)+Q15-$H$1)*(1+$E$1)-$J$1*C16)/D16 -> 27119.007 | R16: 1 | S16: Prosp: Quoting end of year figures.
A17: 14 | B17: 45 | C17: ='Q1 Base'!O20 -> 0.0018494 | D17: =1-C17 -> 0.9981506 | E17: =(C17+E18*D17)/(1+$E$1) -> 0.024096894 | F17: =1+(F18*D17/(1+$E$1)) -> 8.8822089 | G17: =$G$1*F17 -> 44411.045 | H17: =$H$1*F17 -> 8882.2089 | I17: =$G$1*$I$1*F17 -> 888.22089 | J17: =$J$1*E17 -> 60242.236 | K17: =J17+H17+I17-G17 -> 25601.621 | L17: =K18 -> 26623.702 | M17: =M16*D17 -> 0.98346179 | N17: =N16+C17/(1+$E$1)^A17*M16 -> 0.010415039 | O17: =O16+M16/(1+$E$1)^A16 -> 9.930915 | P17: =(($G$1*(1-$I$1)-$H$1)*O17-$J$1*N17)/M17*(1+$E$1)^A17 -> 28231.311 | Q17: =(($G$1*(1-$I$1)+Q16-$H$1)*(1+$E$1)-$J$1*C17)/D17 -> 28231.311 | R17: 1 | S17: Prosp: Final year reserve = 0
A18: 15 | B18: 46 | C18: ='Q1 Base'!O21 -> 0.001982 | D18: =1-C18 -> 0.998018 | E18: =(C18+E19*D18)/(1+$E$1) -> 0.023676854 | F18: =1+(F19*D18/(1+$E$1)) -> 8.3508801 | G18: =$G$1*F18 -> 41754.4 | H18: =$H$1*F18 -> 8350.8801 | I18: =$G$1*$I$1*F18 -> 835.08801 | J18: =$J$1*E18 -> 59192.134 | K18: =J18+H18+I18-G18 -> 26623.702 | L18: =K19 -> 27378.078 | M18: =M17*D18 -> 0.98151256 | N18: =N17+C18/(1+$E$1)^A18*M17 -> 0.011257705 | O18: =O17+M17/(1+$E$1)^A17 -> 10.380521 | P18: =(($G$1*(1-$I$1)-$H$1)*O18-$J$1*N18)/M18*(1+$E$1)^A18 -> 29081.501 | Q18: =(($G$1*(1-$I$1)+Q17-$H$1)*(1+$E$1)-$J$1*C18)/D18 -> 29081.501
A19: 16 | B19: 47 | C19: ='Q1 Base'!O22 -> 0.0023176 | D19: =1-C19 -> 0.9976824 | E19: =(C19+E20*D19)/(1+$E$1) -> 0.023102061 | F19: =1+(F20*D19/(1+$E$1)) -> 7.7889935 | G19: =$G$1*F19 -> 38944.967 | H19: =$H$1*F19 -> 7788.9935 | I19: =$G$1*$I$1*F19 -> 778.89935 | J19: =$J$1*E19 -> 57755.152 | K19: =J19+H19+I19-G19 -> 27378.078 | L19: =K20 -> 27345.944 | M19: =M18*D19 -> 0.97923781 | N19: =N18+C19/(1+$E$1)^A19*M18 -> 0.012187631 | O19: =O18+M18/(1+$E$1)^A18 -> 10.804838 | P19: =(($G$1*(1-$I$1)-$H$1)*O19-$J$1*N19)/M19*(1+$E$1)^A19 -> 29151.498 | Q19: =(($G$1*(1-$I$1)+Q18-$H$1)*(1+$E$1)-$J$1*C19)/D19 -> 29151.498 | R19: 1 | S19: Retro: tpx
A20: 17 | B20: 48 | C20: ='Q1 Base'!O23 -> 0.0023668 | D20: =1-C20 -> 0.9976332 | E20: =(C20+E21*D20)/(1+$E$1) -> 0.022164197 | F20: =1+(F21*D20/(1+$E$1)) -> 7.1960381 | G20: =$G$1*F20 -> 35980.191 | H20: =$H$1*F20 -> 7196.0381 | I20: =$G$1*$I$1*F20 -> 719.60381 | J20: =$J$1*E20 -> 55410.493 | K20: =J20+H20+I20-G20 -> 27345.944 | L20: =K21 -> 27189.939 | M20: =M19*D20 -> 0.97692015 | N20: =N19+C20/(1+$E$1)^A20*M19 -> 0.01308358 | O20: =O19+M19/(1+$E$1)^A19 -> 11.205153 | P20: =(($G$1*(1-$I$1)-$H$1)*O20-$J$1*N20)/M20*(1+$E$1)^A20 -> 29103.842 | Q20: =(($G$1*(1-$I$1)+Q19-$H$1)*(1+$E$1)-$J$1*C20)/D20 -> 29103.842 | R20: 1 | S20: Retro: TAx:<n> calculation
A21: 18 | B21: 49 | C21: ='Q1 Base'!O24 -> 0.0026407 | D21: =1-C21 -> 0.9973593 | E21: =(C21+E22*D21)/(1+$E$1) -> 0.02112183 | F21: =1+(F22*D21/(1+$E$1)) -> 6.5678551 | G21: =$G$1*F21 -> 32839.276 | H21: =$H$1*F21 -> 6567.8551 | I21: =$G$1*$I$1*F21 -> 656.78551 | J21: =$J$1*E21 -> 52804.574 | K21: =J21+H21+I21-G21 -> 27189.939 | L21: =K22 -> 26345.431 | M21: =M20*D21 -> 0.9743404 | N21: =N20+C21/(1+$E$1)^A21*M20 -> 0.014026623 | O21: =O20+M20/(1+$E$1)^A20 -> 11.582806 | P21: =(($G$1*(1-$I$1)-$H$1)*O21-$J$1*N21)/M21*(1+$E$1)^A21 -> 28374.743 | Q21: =(($G$1*(1-$I$1)+Q20-$H$1)*(1+$E$1)-$J$1*C21)/D21 -> 28374.743 | R21: 1 | S21: Retro: aduex:<n> calculation
A22: 19 | B22: 50 | C22: ='Q1 Base'!O25 -> 0.0029207 | D22: =1-C22 -> 0.9970793 | E22: =(C22+E23*D22)/(1+$E$1) -> 0.019747783 | F22: =1+(F23*D22/(1+$E$1)) -> 5.9035964 | G22: =$G$1*F22 -> 29517.982 | H22: =$H$1*F22 -> 5903.5964 | I22: =$G$1*$I$1*F22 -> 590.35964 | J22: =$J$1*E22 -> 49369.457 | K22: =J22+H22+I22-G22 -> 26345.431 | L22: =K23 -> 24755.096 | M22: =M21*D22 -> 0.97149464 | N22: =N21+C22/(1+$E$1)^A22*M21 -> 0.015010341 | O22: =O21+M21/(1+$E$1)^A21 -> 11.938981 | P22: =(($G$1*(1-$I$1)-$H$1)*O22-$J$1*N22)/M22*(1+$E$1)^A22 -> 26907.379 | Q22: =(($G$1*(1-$I$1)+Q21-$H$1)*(1+$E$1)-$J$1*C22)/D22 -> 26907.379 | R22: 2 | S22: Retro: including all elements
A23: 20 | B23: 51 | C23: ='Q1 Base'!O26 -> 0.0029822 | D23: =1-C23 -> 0.9970178 | E23: =(C23+E24*D23)/(1+$E$1) -> 0.018015197 | F23: =1+(F24*D23/(1+$E$1)) -> 5.200743 | G23: =$G$1*F23 -> 26003.715 | H23: =$H$1*F23 -> 5200.743 | I23: =$G$1*$I$1*F23 -> 520.0743 | J23: =$J$1*E23 -> 45037.993 | K23: =J23+H23+I23-G23 -> 24755.096 | L23: =K24 -> 22915.603 | M23: =M22*D23 -> 0.96859745 | N23: =N22+C23/(1+$E$1)^A23*M22 -> 0.015957384 | O23: =O22+M22/(1+$E$1)^A22 -> 12.274807 | P23: =(($G$1*(1-$I$1)-$H$1)*O23-$J$1*N23)/M23*(1+$E$1)^A23 -> 25198.45 | Q23: =(($G$1*(1-$I$1)+Q22-$H$1)*(1+$E$1)-$J$1*C23)/D23 -> 25198.45 | R23: 1 | S23: Retro: allowing for survivorship
A24: 21 | B24: 52 | C24: ='Q1 Base'!O27 -> 0.0032392 | D24: =1-C24 -> 0.9967608 | E24: =(C24+E25*D24)/(1+$E$1) -> 0.016116935 | F24: =1+(F25*D24/(1+$E$1)) -> 4.4555732 | G24: =$G$1*F24 -> 22277.866 | H24: =$H$1*F24 -> 4455.5732 | I24: =$G$1*$I$1*F24 -> 445.55732 | J24: =$J$1*E24 -> 40292.338 | K24: =J24+H24+I24-G24 -> 22915.603 | L24: =K25 -> 20325.338 | M24: =M23*D24 -> 0.96545997 | N24: =N23+C24/(1+$E$1)^A24*M23 -> 0.016927208 | O24: =O23+M23/(1+$E$1)^A23 -> 12.591425 | P24: =(($G$1*(1-$I$1)-$H$1)*O24-$J$1*N24)/M24*(1+$E$1)^A24 -> 22747.294 | Q24: =(($G$1*(1-$I$1)+Q23-$H$1)*(1+$E$1)-$J$1*C24)/D24 -> 22747.294 | R24: 1 | S24: Retro: rolling up to year end
A25: 22 | B25: 53 | C25: ='Q1 Base'!O28 -> 0.0034328 | D25: =1-C25 -> 0.9965672 | E25: =(C25+E26*D25)/(1+$E$1) -> 0.01384932 | F25: =1+(F26*D25/(1+$E$1)) -> 3.666144 | G25: =$G$1*F25 -> 18330.72 | H25: =$H$1*F25 -> 3666.144 | I25: =$G$1*$I$1*F25 -> 366.6144 | J25: =$J$1*E25 -> 34623.299 | K25: =J25+H25+I25-G25 -> 20325.338 | L25: =K26 -> 17094.978 | M25: =M24*D25 -> 0.96214574 | N25: =N24+C25/(1+$E$1)^A25*M24 -> 0.017895964 | O25: =O24+M24/(1+$E$1)^A24 -> 12.889857 | P25: =(($G$1*(1-$I$1)-$H$1)*O25-$J$1*N25)/M25*(1+$E$1)^A25 -> 19665.019 | Q25: =(($G$1*(1-$I$1)+Q24-$H$1)*(1+$E$1)-$J$1*C25)/D25 -> 19665.019
A26: 23 | B26: 54 | C26: ='Q1 Base'!O29 -> 0.0037502 | D26: =1-C26 -> 0.9962498 | E26: =(C26+E27*D26)/(1+$E$1) -> 0.01125148 | F26: =1+(F27*D26/(1+$E$1)) -> 2.8291592 | G26: =$G$1*F26 -> 14145.796 | H26: =$H$1*F26 -> 2829.1592 | I26: =$G$1*$I$1*F26 -> 282.91592 | J26: =$J$1*E26 -> 28128.699 | K26: =J26+H26+I26-G26 -> 17094.978 | L26: =K27 -> 12874.973 | M26: =M25*D26 -> 0.9585375 | N26: =N25+C26/(1+$E$1)^A26*M25 -> 0.018893312 | O26: =O25+M25/(1+$E$1)^A25 -> 13.171094 | P26: =(($G$1*(1-$I$1)-$H$1)*O26-$J$1*N26)/M26*(1+$E$1)^A26 -> 15603.022 | Q26: =(($G$1*(1-$I$1)+Q25-$H$1)*(1+$E$1)-$J$1*C26)/D26 -> 15603.022 | R26: =SUM(R6:R24) -> 23
A27: 24 | B27: 55 | C27: ='Q1 Base'!O30 -> 0.0042397 | D27: =1-C27 -> 0.9957603 | E27: =(C27+E28*D27)/(1+$E$1) -> 0.0081789122 | F27: =1+(F28*D27/(1+$E$1)) -> 1.9416173 | G27: =$G$1*F27 -> 9708.0865 | H27: =$H$1*F27 -> 1941.6173 | I27: =$G$1*$I$1*F27 -> 194.16173 | J27: =$J$1*E27 -> 20447.281 | K27: =J27+H27+I27-G27 -> 12874.973 | L27: =K28 -> 7170.6856 | M27: =M26*D27 -> 0.95447359 | N27: =N26+C27/(1+$E$1)^A27*M26 -> 0.019955534 | O27: =O26+M26/(1+$E$1)^A26 -> 13.436042 | P27: =(($G$1*(1-$I$1)-$H$1)*O27-$J$1*N27)/M27*(1+$E$1)^A27 -> 10067.881 | Q27: =(($G$1*(1-$I$1)+Q26-$H$1)*(1+$E$1)-$J$1*C27)/D27 -> 10067.881
A28: 25 | B28: 56 | C28: ='Q1 Base'!O31 -> 0.0046829 | D28: =1-C28 -> 0.9953171 | E28: =(C28+E29*D28)/(1+$E$1) -> 0.0044282742 | F28: =1 -> 1 | G28: =$G$1*F28 -> 5000 | H28: =$H$1*F28 -> 1000 | I28: =$G$1*$I$1*F28 -> 100 | J28: =$J$1*E28 -> 11070.686 | K28: =J28+H28+I28-G28 -> 7170.6856 | L28: =K29 -> 0 | M28: =M27*D28 -> 0.95000388 | N28: =N27+C28/(1+$E$1)^A28*M27 -> 0.021060298 | O28: =O27+M27/(1+$E$1)^A27 -> 13.685522 | P28: =(($G$1*(1-$I$1)-$H$1)*O28-$J$1*N28)/M28*(1+$E$1)^A28 -> 3078.1988 | Q28: =(($G$1*(1-$I$1)+Q27-$H$1)*(1+$E$1)-$J$1*C28)/D28 -> 3078.1988
L29: [1]

Sheet Q1 Answers
A1: (i) | F1: (ii)
A2: Policy Year | B2: Prospective Reserve at EOY | C2: Retrospective Reserve at EOY | G2: See separate sheet
A3: 1 | B3: ='Q1'!L4 -> 1495.2646 | C3: ='Q1'!P4 -> 2260.1868
A4: 2 | B4: ='Q1'!L5 -> 3872.3362 | C4: ='Q1'!P5 -> 4681.8359
A5: 3 | B5: ='Q1'!L6 -> 6236.2045 | C5: ='Q1'!P6 -> 7092.9317
A6: 4 | B6: ='Q1'!L7 -> 8608.5786 | C6: ='Q1'!P7 -> 9515.3357
A7: 5 | B7: ='Q1'!L8 -> 10801.849 | C7: ='Q1'!P8 -> 11761.68
A8: 6 | B8: ='Q1'!L9 -> 13134.2 | C8: ='Q1'!P9 -> 14150.207
A9: 7 | B9: ='Q1'!L10 -> 15459.31 | C9: ='Q1'!P10 -> 16534.843
A10: 8 | B10: ='Q1'!L11 -> 17648.547 | C10: ='Q1'!P11 -> 18787.219
A11: 9 | B11: ='Q1'!L12 -> 19689.185 | C11: ='Q1'!P12 -> 20894.836
A12: 10 | B12: ='Q1'!L13 -> 21434.675 | C12: ='Q1'!P13 -> 22711.46
A13: 11 | B13: ='Q1'!L14 -> 23099.847 | C13: ='Q1'!P14 -> 24452.062
A14: 12 | B14: ='Q1'!L15 -> 24443.161 | C14: ='Q1'!P15 -> 25875.507
... A27: 25 | B27: ='Q1'!L28 -> 0 | C27: ='Q1'!P28 -> 3078.1988

Sheet Q2 Base
B2: Policy Year | G2: Policy Terms
B3: Beginning (t-1) | C3: Ending (t) | D3: mu(01)(x+t-1) critical illness | E3: mu(02)(x+t-1) mortality
B4: 0 | C4: 1 | D4: 0.00040008002 | E4: 0.00050412705 | G4: Age at outset | H4: 30 | I4: exact.
B5: 1 | C5: 2 | D5: 0.00040008002 | E5: 0.00054114639 | G5: Policy Term | H5: 20 | I5: years.
B6: 2 | C6: 3 | D6: 0.00045010128 | E6: 0.00057516538 | G6: Minimum guaranteed death benefit | H6: 15000
B7: 3 | C7: 4 | D7: 0.00045010128 | E7: 0.00061218735 | G7: Annual Premium | H7: 2000 | I7: payable annually in advance.
B8: 4 | C8: 5 | D8: 0.00050012504 | E8: 0.0006532133 | G8: Allocation rate for all policy years | H8: 0.95
B9: 5 | C9: 6 | D9: 0.00055015131 | E9: 0.00069624232 | G9: Bid offer spread | H9: 0.01
B10: 6 | C10: 7 | D10: 0.00060018007 | E10: 0.00074727914 | G10: Annual Management Charge | H10: 0.005 | I10: per annum, payable at the end of each policy year by unit cancellation.
B11: 7 | C11: 8 | D11: 0.00070024511 | E11: 0.00080232177
B12: 8 | C12: 9 | D12: 0.00090040524 | E12: 0.00085436487
B13: 9 | C13: 10 | D13: 0.0010005003 | E13: 0.00090140614
B14: 10 | C14: 11 | D14: 0.0010005003 | E14: 0.00094945059
B15: 11 | C15: 12 | D15: 0.0011006054 | E15: 0.0010075074 | G15: Profit Test Assumptions
B16: 12 | C16: 13 | D16: 0.0012007206 | E16: 0.0010835869
B17: 13 | C17: 14 | D17: 0.0012007206 | E17: 0.0011796956 | G17: Unit growth rate | H17: 0.04 | I17: per annum effective.
B18: 14 | C18: 15 | D18: 0.0013008457 | E18: 0.0013008457 | G18: Return on non-unit balances | H18: 0.01 | I18: per annum effective.
B19: 15 | C19: 16 | D19: 0.0014009809 | E19: 0.0014480479 | G19: Risk Discount Rate | H19: 0.07 | I19: per annum effective.
B20: 16 | C20: 17 | D20: 0.0015011261 | E20: 0.0016153039
B21: 17 | C21: 18 | D21: 0.0016012814 | E21: 0.001806631 | G21: Independent mortality and critical illness diagnosis rates are given by the table.
B22: 18 | C22: 19 | D22: 0.0018016219 | E22: 0.0020310612 | G22: You should assume that deaths and critical illness diagnoses occur uniformly across each policy year.
B23: 19 | C23: 20 | D23: 0.0020020027 | E23: 0.0022916238
B24: 20 | G24: Initial Expenses | H24: 75 | I24: at the start of the first policy year.
G25: Renewal expenses | H25: 25 | I25: per annum, at the start of each subsequent policy year.
G26: Initial Commision | H26: 0.5 | I26: of the premium payable at the start of the first policy year.
G27: Renewal Commission | H27: 0.01 | I27: of the premiums payable at the start of each subsequent policy year.

Sheet Q2 (i)
D1: [1] | E1: [1] | F1: [1] | G1: [2] | H1: [1] | I1: [1]
B2: UNIT FUND | D2: 2000 | E2: 0.95 | F2: 0.01 | G2: 0.04 | H2: 0.005
B3: Policy Year | C3: Fund at start | D3: Premium | E3: Allocated Premium | F3: Bid offer spread | G3: Fund at end year before AMC deduction | H3: AMC | I3: Fund at end
B4: 1 | C4: 0 | D4: =$D$2 -> 2000 | E4: =D4*$E$2 -> 1900 | F4: =-$F$2*E4 -> -19 | G4: =SUM(C4,E4:F4)*(1+$G$2) -> 1956.24 | H4: =-G4*$H$2 -> -9.7812 | I4: =SUM(G4:H4) -> 1946.4588
B5: 2 | C5: =I4 -> 1946.4588 | D5: =$D$2 -> 2000 | E5: =D5*$E$2 -> 1900 | F5: =-$F$2*E5 -> -19 | G5: =SUM(C5,E5:F5)*(1+$G$2) -> 3980.5572 | H5: =-G5*$H$2 -> -19.902786 | I5: =SUM(G5:H5) -> 3960.6544
B6: 3 | C6: =I5 -> 3960.6544 | D6: =$D$2 -> 2000 | E6: =D6*$E$2 -> 1900 | F6: =-$F$2*E6 -> -19 | G6: =SUM(C6,E6:F6)*(1+$G$2) -> 6075.3205 | H6: =-G6*$H$2 -> -30.376603 | I6: =SUM(G6:H6) -> 6044.9439
B7: 4 | C7: =I6 -> 6044.9439 | D7: =$D$2 -> 2000 | E7: =D7*$E$2 -> 1900 | F7: =-$F$2*E7 -> -19 | G7: =SUM(C7,E7:F7)*(1+$G$2) -> 8242.9817 | H7: =-G7*$H$2 -> -41.214908 | I7: =SUM(G7:H7) -> 8201.7668
B8: 5 | C8: =I7 -> 8201.7668 | D8: =$D$2 -> 2000 | E8: =D8*$E$2 -> 1900 | F8: =-$F$2*E8 -> -19 | G8: =SUM(C8,E8:F8)*(1+$G$2) -> 10486.077 | H8: =-G8*$H$2 -> -52.430387 | I8: =SUM(G8:H8) -> 10433.647
B9: 6 | C9: =I8 -> 10433.647 | D9: =$D$2 -> 2000 | E9: =D9*$E$2 -> 1900 | F9: =-$F$2*E9 -> -19 | G9: =SUM(C9,E9:F9)*(1+$G$2) -> 12807.233 | H9: =-G9*$H$2 -> -64.036165 | I9: =SUM(G9:H9) -> 12743.197
B10: 7 | C10: =I9 -> 12743.197 | D10: =$D$2 -> 2000 | E10: =D10*$E$2 -> 1900 | F10: =-$F$2*E10 -> -19 | G10: =SUM(C10,E10:F10)*(1+$G$2) -> 15209.165 | H10: =-G10*$H$2 -> -76.045823 | I10: =SUM(G10:H10) -> 15133.119
B11: 8 | C11: =I10 -> 15133.119 | D11: =$D$2 -> 2000 | E11: =D11*$E$2 -> 1900 | F11: =-$F$2*E11 -> -19 | G11: =SUM(C11,E11:F11)*(1+$G$2) -> 17694.684 | H11: =-G11*$H$2 -> -88.473418 | I11: =SUM(G11:H11) -> 17606.21
B12: 9 | C12: =I11 -> 17606.21 | D12: =$D$2 -> 2000 | E12: =D12*$E$2 -> 1900 | F12: =-$F$2*E12 -> -19 | G12: =SUM(C12,E12:F12)*(1+$G$2) -> 20266.699 | H12: =-G12*$H$2 -> -101.33349 | I12: =SUM(G12:H12) -> 20165.365
B13: 10 | C13: =I12 -> 20165.365 | D13: =$D$2 -> 2000 | E13: =D13*$E$2 -> 1900 | F13: =-$F$2*E13 -> -19 | G13: =SUM(C13,E13:F13)*(1+$G$2) -> 22928.22 | H13: =-G13*$H$2 -> -114.6411 | I13: =SUM(G13:H13) -> 22813.579
B14: 11 | C14: =I13 -> 22813.579 | D14: =$D$2 -> 2000 | E14: =D14*$E$2 -> 1900 | F14: =-$F$2*E14 -> -19 | G14: =SUM(C14,E14:F14)*(1+$G$2) -> 25682.362 | H14: =-G14*$H$2 -> -128.41181 | I14: =SUM(G14:H14) -> 25553.95
B15: 12 | C15: =I14 -> 25553.95 | D15: =$D$2 -> 2000 | E15: =D15*$E$2 -> 1900 | F15: =-$F$2*E15 -> -19 | G15: =SUM(C15,E15:F15)*(1+$G$2) -> 28532.348 | H15: =-G15*$H$2 -> -142.66174 | I15: =SUM(G15:H15) -> 28389.686
B16: 13 | C16: =I15 -> 28389.686 | D16: =$D$2 -> 2000 | E16: =D16*$E$2 -> 1900 | F16: =-$F$2*E16 -> -19 | G16: =SUM(C16,E16:F16)*(1+$G$2) -> 31481.514 | H16: =-G16*$H$2 -> -157.40757 | I16: =SUM(G16:H16) -> 31324.106
... B23: 20 | C23: =I22 -> 51203.899 | D23: =$D$2 -> 2000 | E23: =D23*$E$2 -> 1900 | F23: =-$F$2*E23 -> -19 | G23: =SUM(C23,E23:F23)*(1+$G$2) -> 55208.295 | H23: =-G23*$H$2 -> -276.04147 | I23: =SUM(G23:H23) -> 54932.253

Sheet Q2 (ii)
E1: [2] | F1: [2] | G1: [1] | H1: [2] | I1: [1] | J1: [2] | K1: [1]
A2: Policy Year | R2: [1] | S2: For picking up correct probability
A3: Beginning | B3: Ending | C3: Force of critical illness | D3: Force of mortality | E3: (t-1)p(00)x | F3: (t-1)p(01)x | G3: (t-1)p(02)x | H3: (d/dt)(t-1)p(01)x | I3: (d/dt)(t-1)p(02)x | J3: (1)p(01)(x+t-1) | K3: (1)p(02)(x+t-1) | U3: [1] | V3: [2] | W3: [1] | X3: [1]
A4: 0 | B4: =A4+1 -> 1 | C4: ='Q2 Base'!D4 -> 0.00040008002 | D4: ='Q2 Base'!E4 -> 0.00050412705 | E4: 1 | F4: 0 | G4: 0 | H4: =E4*C4 -> 0.00040008002 | I4: =E4*D4 -> 0.00050412705 | J4: =(F5-F4)/E4 -> 0.00040008002 | K4: =(G5-G4)/E4 -> 0.00050412705
A5: =A4+1 -> 1 | B5: =A5+1 -> 2 | C5: ='Q2 Base'!D5 -> 0.00040008002 | D5: ='Q2 Base'!E5 -> 0.00054114639 | E5: =E4*EXP(-D4-C4) -> 0.9990962 | F5: =F4+1*H4 -> 0.00040008002 | G5: =G4+1*I4 -> 0.00050412705 | H5: =E5*C5 -> 0.00039971843 | I5: =E5*D5 -> 0.00054065731 | J5: =(F6-F5)/E5 -> 0.00040008002 | K5: =(G6-G5)/E5 -> 0.00054114639
A6: =A5+1 -> 2 | B6: =A6+1 -> 3 | C6: ='Q2 Base'!D6 -> 0.00045010128 | D6: ='Q2 Base'!E6 -> 0.00057516538 | E6: =E5*EXP(-D5-C5) -> 0.99815627 | F6: =F5+1*H5 -> 0.00079979845 | G6: =G5+1*I5 -> 0.0010447844 | H6: =E6*C6 -> 0.00044927141 | I6: =E6*D6 -> 0.00057410493 | J6: =(F7-F6)/E6 -> 0.00045010128 | K6: =(G7-G6)/E6 -> 0.00057516538
A7: =A6+1 -> 3 | B7: =A7+1 -> 4 | C7: ='Q2 Base'!D7 -> 0.00045010128 | D7: ='Q2 Base'!E7 -> 0.00061218735 | E7: =E6*EXP(-D6-C6) -> 0.99713342 | F7: =F6+1*H6 -> 0.0012490699 | G7: =G6+1*I6 -> 0.0016188893 | H7: =E7*C7 -> 0.00044881103 | I7: =E7*D7 -> 0.00061043246 | J7: =(F8-F7)/E7 -> 0.00045010128 | K7: =(G8-G7)/E7 -> 0.00061218735
A8: =A7+1 -> 4 | B8: =A8+1 -> 5 | C8: ='Q2 Base'!D8 -> 0.00050012504 | D8: ='Q2 Base'!E8 -> 0.0006532133 | E8: =E7*EXP(-D7-C7) -> 0.99607474 | F8: =F7+1*H7 -> 0.0016978809 | G8: =G7+1*I7 -> 0.0022293217 | H8: =E8*C8 -> 0.00049816192 | I8: =E8*D8 -> 0.00065064926 | J8: =(F9-F8)/E8 -> 0.00050012504 | K8: =(G9-G8)/E8 -> 0.0006532133
A9: =A8+1 -> 5 | B9: =A9+1 -> 6 | C9: ='Q2 Base'!D9 -> 0.00055015131 | D9: ='Q2 Base'!E9 -> 0.00069624232 | E9: =E8*EXP(-D8-C8) -> 0.99492659 | F9: =F8+1*H8 -> 0.0021960428 | G9: =G8+1*I8 -> 0.002879971 | H9: =E9*C9 -> 0.00054736016 | I9: =E9*D9 -> 0.00069271 | J9: =(F10-F9)/E9 -> 0.00055015131 | K9: =(G10-G9)/E9 -> 0.00069624232
A10: =A9+1 -> 6 | B10: =A10+1 -> 7 | C10: ='Q2 Base'!D10 -> 0.00060018007 | D10: ='Q2 Base'!E10 -> 0.00074727914 | E10: =E9*EXP(-D9-C9) -> 0.99368729 | F10: =F9+1*H9 -> 0.002743403 | G10: =G9+1*I9 -> 0.003572681 | H10: =E10*C10 -> 0.00059639131 | I10: =E10*D10 -> 0.00074256179 | J10: =(F11-F10)/E10 -> 0.00060018007 | K10: =(G11-G10)/E10 -> 0.00074727914
A11: =A10+1 -> 7 | B11: =A11+1 -> 8 | C11: ='Q2 Base'!D11 -> 0.00070024511 | D11: ='Q2 Base'!E11 -> 0.00080232177 | E11: =E10*EXP(-D10-C10) -> 0.99234924 | F11: =F10+1*H10 -> 0.0033397943 | G11: =G10+1*I10 -> 0.0043152428 | H11: =E11*C11 -> 0.00069488771 | I11: =E11*D11 -> 0.0007961834 | J11: =(F12-F11)/E11 -> 0.00070024511 | K11: =(G12-G11)/E11 -> 0.00080232177
A12: =A11+1 -> 8 | B12: =A12+1 -> 9 | C12: ='Q2 Base'!D12 -> 0.00090040524 | D12: ='Q2 Base'!E12 -> 0.00085436487 | E12: =E11*EXP(-D11-C11) -> 0.99085929 | F12: =F11+1*H11 -> 0.004034682 | G12: =G11+1*I11 -> 0.0051114262 | H12: =E12*C12 -> 0.0008921749 | I12: =E12*D12 -> 0.00084655536 | J12: =(F13-F12)/E12 -> 0.00090040524 | K12: =(G13-G12)/E12 -> 0.00085436487
A13: =A12+1 -> 9 | B13: =A13+1 -> 10 | C13: ='Q2 Base'!D13 -> 0.0010005003 | D13: ='Q2 Base'!E13 -> 0.00090140614 | E13: =E12*EXP(-D12-C12) -> 0.98912208 | F13: =F12+1*H12 -> 0.0049268569 | G13: =G12+1*I12 -> 0.0059579815 | H13: =E13*C13 -> 0.00098961697 | I13: =E13*D13 -> 0.00089160072 | J13: =(F14-F13)/E13 -> 0.0010005003 | K13: =(G14-G13)/E13 -> 0.00090140614
A14: =A13+1 -> 10 | B14: =A14+1 -> 11 | C14: ='Q2 Base'!D14 -> 0.0010005003 | D14: ='Q2 Base'!E14 -> 0.00094945059 | E14: =E13*EXP(-D13-C13) -> 0.98724265 | F14: =F13+1*H13 -> 0.0059164739 | G14: =G13+1*I13 -> 0.0068495823 | H14: =E14*C14 -> 0.0009877366 | I14: =E14*D14 -> 0.00093733811 | J14: =(F15-F14)/E14 -> 0.0010005003 | K14: =(G15-G14)/E14 -> 0.00094945059
A15: =A14+1 -> 11 | B15: =A15+1 -> 12 | C15: ='Q2 Base'!D15 -> 0.0011006054 | D15: ='Q2 Base'!E15 -> 0.0010075074 | E15: =E14*EXP(-D14-C14) -> 0.98531945 | F15: =F14+1*H14 -> 0.0069042105 | G15: =G14+1*I14 -> 0.0077869204 | H15: =E15*C15 -> 0.001084448 | I15: =E15*D15 -> 0.0009927166 | J15: =(F16-F15)/E15 -> 0.0011006054 | K15: =(G16-G15)/E15 -> 0.0010075074
A16: =A15+1 -> 12 | B16: =A16+1 -> 13 | C16: ='Q2 Base'!D16 -> 0.0012007206 | D16: ='Q2 Base'!E16 -> 0.0010835869 | E16: =E15*EXP(-D15-C15) -> 0.98324447 | F16: =F15+1*H15 -> 0.0079886584 | G16: =G15+1*I15 -> 0.008779637 | H16: =E16*C16 -> 0.0011806019 | I16: =E16*D16 -> 0.0010654308 | J16: =(F17-F16)/E16 -> 0.0012007206 | K16: =(G17-G16)/E16 -> 0.0010835869
... A23: =A22+1 -> 19 | B23: =A23+1 -> 20 | C23: ='Q2 Base'!D23 -> 0.0020020027 | D23: ='Q2 Base'!E23 -> 0.0022916238 | E23: =E22*EXP(-D22-C22) -> 0.96331968 | F23: =F22+1*H22 -> 0.017744876 | G23: =G22+1*I22 -> 0.018978263 | H23: =E23*C23 -> 0.0019285686 | I23: =E23*D23 -> 0.0022075663 | J23: =(F24-F23)/E23 -> 0.0020020027 | K23: =(G24-G23)/E23 -> 0.0022916238
A24: =A23+1 -> 20 | E24: =E23*EXP(-D23-C23) -> 0.95919241 | F24: =F23+1*H23 -> 0.019673444 | G24: =G23+1*I23 -> 0.021185829

Sheet Q2 (iii)
D1: [2] | L1: [1] | M1: [1] | N1: [1] | O1: [1] | P1: [2] | Q1: [2] | S1: [1] | U1: [1] | V1: [1] | W1: [2] | X1: [2] | Y1: [1] | Z1: [1] | AA1: [1]
B2: UNIT FUND | D2: 2000 | E2: 0.98135565 | F2: 0.01 | G2: 0.04 | H2: 0.005 | K2: NON-UNIT FUND | P2: 0.01 | Q2: 15000 | Y2: 0.07
B3: Policy Year | C3: Fund at start | D3: Premium | E3: Allocated Premium | F3: Bid offer spread | G3: Fund at end year before AMC deduction | H3: AMC | I3: Fund at end | K3: Policy Year | L3: Non-allocated premium | M3: Bid Offer Spread | N3: Expenses | O3: Commission | P3: Interest | Q3: Additional Death Benefit | R3: Mortality rate | S3: Cost of extra death cover | T3: Critical illness rate | U3: Cost of Critical Illness cover | V3: AMC | W3: Profit | X3: Probability Policy in force at year start | Y3: Discount factor | Z3: Profit Signature | AA3: Present Value of Profits
B4: 1 | C4: 0 | D4: =$D$2 -> 2000 | E4: =D4*$E$2 -> 1962.7113 | F4: =-$F$2*E4 -> -19.627113 | G4: =SUM(C4,E4:F4)*(1+$G$2) -> 2020.8076 | H4: =-G4*$H$2 -> -10.104038 | I4: =SUM(G4:H4) -> 2010.7035 | K4: 1 | L4: =D4-E4 -> 37.288692 | M4: =-F4 -> 19.627113 | N4: =-'Q2 Base'!H24 -> -75 | O4: =-D4*'Q2 Base'!H26 -> -1000 | P4: =SUM(L4:O4)*$P$2 -> -10.180842 | Q4: =MAX($Q$2-I4,0) -> 12989.296 | R4: ='Q2 (ii)'!K4 -> 0.00050412705 | S4: =-Q4*R4 -> -6.5482557 | T4: ='Q2 (ii)'!J4 -> 0.00040008002 | U4: =H4*T4 -> -0.0040424237 | V4: =-H4 -> 10.104038 | W4: =SUM(L4:P4,S4,U4:V4) -> -1024.7133 | X4: ='Q2 (ii)'!E4 -> 1 | Y4: =(1+$Y$2)^-K4 -> 0.93457944 | Z4: =W4*X4 -> -1024.7133 | AA4: =Y4*Z4 -> -957.67598
B5: 2 | C5: =I4 -> 2010.7035 | D5: =$D$2 -> 2000 | E5: =D5*$E$2 -> 1962.7113 | F5: =-$F$2*E5 -> -19.627113 | G5: =SUM(C5,E5:F5)*(1+$G$2) -> 4111.9392 | H5: =-G5*$H$2 -> -20.559696 | I5: =SUM(G5:H5) -> 4091.3795 | K5: 2 | L5: =D5-E5 -> 37.288692 | M5: =-F5 -> 19.627113 | N5: =-'Q2 Base'!$H$25 -> -25 | O5: =-D5*'Q2 Base'!$H$27 -> -20 | P5: =SUM(L5:O5)*$P$2 -> 0.11915805 | Q5: =MAX($Q$2-I5,0) -> 10908.62 | R5: ='Q2 (ii)'!K5 -> 0.00054114639 | S5: =-Q5*R5 -> -5.9031606 | T5: ='Q2 (ii)'!J5 -> 0.00040008002 | U5: =H5*T5 -> -0.0082255237 | V5: =-H5 -> 20.559696 | W5: =SUM(L5:P5,S5,U5:V5) -> 26.683273 | X5: ='Q2 (ii)'!E5 -> 0.9990962 | Y5: =(1+$Y$2)^-K5 -> 0.87343873 | Z5: =W5*X5 -> 26.659157 | AA5: =Y5*Z5 -> 23.28514
B6: 3 | C6: =I5 -> 4091.3795 | D6: =$D$2 -> 2000 | E6: =D6*$E$2 -> 1962.7113 | F6: =-$F$2*E6 -> -19.627113 | G6: =SUM(C6,E6:F6)*(1+$G$2) -> 6275.8423 | H6: =-G6*$H$2 -> -31.379211 | I6: =SUM(G6:H6) -> 6244.4631 | K6: 3 | L6: =D6-E6 -> 37.288692 | M6: =-F6 -> 19.627113 | N6: =-'Q2 Base'!$H$25 -> -25 | O6: =-D6*'Q2 Base'!$H$27 -> -20 | P6: =SUM(L6:O6)*$P$2 -> 0.11915805 | Q6: =MAX($Q$2-I6,0) -> 8755.5369 | R6: ='Q2 (ii)'!K6 -> 0.00057516538 | S6: =-Q6*R6 -> -5.0358817 | T6: ='Q2 (ii)'!J6 -> 0.00045010128 | U6: =H6*T6 -> -0.014123823 | V6: =-H6 -> 31.379211 | W6: =SUM(L6:P6,S6,U6:V6) -> 38.364169 | X6: ='Q2 (ii)'!E6 -> 0.99815627 | Y6: =(1+$Y$2)^-K6 -> 0.81629788 | Z6: =W6*X6 -> 38.293436 | AA6: =Y6*Z6 -> 31.25885
B7: 4 | C7: =I6 -> 6244.4631 | D7: =$D$2 -> 2000 | E7: =D7*$E$2 -> 1962.7113 | F7: =-$F$2*E7 -> -19.627113 | G7: =SUM(C7,E7:F7)*(1+$G$2) -> 8515.0492 | H7: =-G7*$H$2 -> -42.575246 | I7: =SUM(G7:H7) -> 8472.4739 | K7: 4 | L7: =D7-E7 -> 37.288692 | M7: =-F7 -> 19.627113 | N7: =-'Q2 Base'!$H$25 -> -25 | O7: =-D7*'Q2 Base'!$H$27 -> -20 | P7: =SUM(L7:O7)*$P$2 -> 0.11915805 | Q7: =MAX($Q$2-I7,0) -> 6527.5261 | R7: ='Q2 (ii)'!K7 -> 0.00061218735 | S7: =-Q7*R7 -> -3.9960689 | T7: ='Q2 (ii)'!J7 -> 0.00045010128 | U7: =H7*T7 -> -0.019163173 | V7: =-H7 -> 42.575246 | W7: =SUM(L7:P7,S7,U7:V7) -> 50.594977 | X7: ='Q2 (ii)'!E7 -> 0.99713342 | Y7: =(1+$Y$2)^-K7 -> 0.76289521 | Z7: =W7*X7 -> 50.449942 | AA7: =Y7*Z7 -> 38.488019
B8: 5 | C8: =I7 -> 8472.4739 | D8: =$D$2 -> 2000 | E8: =D8*$E$2 -> 1962.7113 | F8: =-$F$2*E8 -> -19.627113 | G8: =SUM(C8,E8:F8)*(1+$G$2) -> 10832.18 | H8: =-G8*$H$2 -> -54.160902 | I8: =SUM(G8:H8) -> 10778.02 | K8: 5 | L8: =D8-E8 -> 37.288692 | M8: =-F8 -> 19.627113 | N8: =-'Q2 Base'!$H$25 -> -25 | O8: =-D8*'Q2 Base'!$H$27 -> -20 | P8: =SUM(L8:O8)*$P$2 -> 0.11915805 | Q8: =MAX($Q$2-I8,0) -> 4221.9805 | R8: ='Q2 (ii)'!K8 -> 0.0006532133 | S8: =-Q8*R8 -> -2.7578538 | T8: ='Q2 (ii)'!J8 -> 0.00050012504 | U8: =H8*T8 -> -0.027087223 | V8: =-H8 -> 54.160902 | W8: =SUM(L8:P8,S8,U8:V8) -> 63.410924 | X8: ='Q2 (ii)'!E8 -> 0.99607474 | Y8: =(1+$Y$2)^-K8 -> 0.71298618 | Z8: =W8*X8 -> 63.162019 | AA8: =Y8*Z8 -> 45.033647
B9: 6 | C9: =I8 -> 10778.02 | D9: =$D$2 -> 2000 | E9: =D9*$E$2 -> 1962.7113 | F9: =-$F$2*E9 -> -19.627113 | G9: =SUM(C9,E9:F9)*(1+$G$2) -> 13229.948 | H9: =-G9*$H$2 -> -66.149739 | I9: =SUM(G9:H9) -> 13163.798 | K9: 6 | L9: =D9-E9 -> 37.288692 | M9: =-F9 -> 19.627113 | N9: =-'Q2 Base'!$H$25 -> -25 | O9: =-D9*'Q2 Base'!$H$27 -> -20 | P9: =SUM(L9:O9)*$P$2 -> 0.11915805 | Q9: =MAX($Q$2-I9,0) -> 1836.2019 | R9: ='Q2 (ii)'!K9 -> 0.00069624232 | S9: =-Q9*R9 -> -1.2784415 | T9: ='Q2 (ii)'!J9 -> 0.00055015131 | U9: =H9*T9 -> -0.036392365 | V9: =-H9 -> 66.149739 | W9: =SUM(L9:P9,S9,U9:V9) -> 76.869868 | X9: ='Q2 (ii)'!E9 -> 0.99492659 | Y9: =(1+$Y$2)^-K9 -> 0.66634222 | Z9: =W9*X9 -> 76.479876 | AA9: =Y9*Z9 -> 50.961771
B10: 7 | C10: =I9 -> 13163.798 | D10: =$D$2 -> 2000 | E10: =D10*$E$2 -> 1962.7113 | F10: =-$F$2*E10 -> -19.627113 | G10: =SUM(C10,E10:F10)*(1+$G$2) -> 15711.158 | H10: =-G10*$H$2 -> -78.555788 | I10: =SUM(G10:H10) -> 15632.602 | K10: 7 | L10: =D10-E10 -> 37.288692 | M10: =-F10 -> 19.627113 | N10: =-'Q2 Base'!$H$25 -> -25 | O10: =-D10*'Q2 Base'!$H$27 -> -20 | P10: =SUM(L10:O10)*$P$2 -> 0.11915805 | Q10: =MAX($Q$2-I10,0) -> 0 | R10: ='Q2 (ii)'!K10 -> 0.00074727914 | S10: =-Q10*R10 -> 0 | T10: ='Q2 (ii)'!J10 -> 0.00060018007 | U10: =H10*T10 -> -0.047147619 | V10: =-H10 -> 78.555788 | W10: =SUM(L10:P10,S10,U10:V10) -> 90.543603 | X10: ='Q2 (ii)'!E10 -> 0.99368729 | Y10: =(1+$Y$2)^-K10 -> 0.62274974 | Z10: =W10*X10 -> 89.972028 | AA10: =Y10*Z10 -> 56.030057
B11: 8 | C11: =I10 -> 15632.602 | D11: =$D$2 -> 2000 | E11: =D11*$E$2 -> 1962.7113 | F11: =-$F$2*E11 -> -19.627113 | G11: =SUM(C11,E11:F11)*(1+$G$2) -> 18278.713 | H11: =-G11*$H$2 -> -91.393567 | I11: =SUM(G11:H11) -> 18187.32 | K11: 8 | L11: =D11-E11 -> 37.288692 | M11: =-F11 -> 19.627113 | N11: =-'Q2 Base'!$H$25 -> -25 | O11: =-D11*'Q2 Base'!$H$27 -> -20 | P11: =SUM(L11:O11)*$P$2 -> 0.11915805 | Q11: =MAX($Q$2-I11,0) -> 0 | R11: ='Q2 (ii)'!K11 -> 0.00080232177 | S11: =-Q11*R11 -> 0 | T11: ='Q2 (ii)'!J11 -> 0.00070024511 | U11: =H11*T11 -> -0.063997899 | V11: =-H11 -> 91.393567 | W11: =SUM(L11:P11,S11,U11:V11) -> 103.36453 | X11: ='Q2 (ii)'!E11 -> 0.99234924 | Y11: =(1+$Y$2)^-K11 -> 0.5820091 | Z11: =W11*X11 -> 102.57371 | AA11: =Y11*Z11 -> 59.698836
B12: 9 | C12: =I11 -> 18187.32 | D12: =$D$2 -> 2000 | E12: =D12*$E$2 -> 1962.7113 | F12: =-$F$2*E12 -> -19.627113 | G12: =SUM(C12,E12:F12)*(1+$G$2) -> 20935.62 | H12: =-G12*$H$2 -> -104.6781 | I12: =SUM(G12:H12) -> 20830.942 | K12: 9 | L12: =D12-E12 -> 37.288692 | M12: =-F12 -> 19.627113 | N12: =-'Q2 Base'!$H$25 -> -25 | O12: =-D12*'Q2 Base'!$H$27 -> -20 | P12: =SUM(L12:O12)*$P$2 -> 0.11915805 | Q12: =MAX($Q$2-I12,0) -> 0 | R12: ='Q2 (ii)'!K12 -> 0.00085436487 | S12: =-Q12*R12 -> 0 | T12: ='Q2 (ii)'!J12 -> 0.00090040524 | U12: =H12*T12 -> -0.094252711 | V12: =-H12 -> 104.6781 | W12: =SUM(L12:P12,S12,U12:V12) -> 116.61881 | X12: ='Q2 (ii)'!E12 -> 0.99085929 | Y12: =(1+$Y$2)^-K12 -> 0.54393374 | Z12: =W12*X12 -> 115.55283 | AA12: =Y12*Z12 -> 62.853085
B13: 10 | C13: =I12 -> 20830.942 | D13: =$D$2 -> 2000 | E13: =D13*$E$2 -> 1962.7113 | F13: =-$F$2*E13 -> -19.627113 | G13: =SUM(C13,E13:F13)*(1+$G$2) -> 23684.987 | H13: =-G13*$H$2 -> -118.42494 | I13: =SUM(G13:H13) -> 23566.562 | K13: 10 | L13: =D13-E13 -> 37.288692 | M13: =-F13 -> 19.627113 | N13: =-'Q2 Base'!$H$25 -> -25 | O13: =-D13*'Q2 Base'!$H$27 -> -20 | P13: =SUM(L13:O13)*$P$2 -> 0.11915805 | Q13: =MAX($Q$2-I13,0) -> 0 | R13: ='Q2 (ii)'!K13 -> 0.00090140614 | S13: =-Q13*R13 -> 0 | T13: ='Q2 (ii)'!J13 -> 0.0010005003 | U13: =H13*T13 -> -0.11848419 | V13: =-H13 -> 118.42494 | W13: =SUM(L13:P13,S13,U13:V13) -> 130.34142 | X13: ='Q2 (ii)'!E13 -> 0.98912208 | Y13: =(1+$Y$2)^-K13 -> 0.50834929 | Z13: =W13*X13 -> 128.92357 | AA13: =Y13*Z13 -> 65.538207
B14: 11 | C14: =I13 -> 23566.562 | D14: =$D$2 -> 2000 | E14: =D14*$E$2 -> 1962.7113 | F14: =-$F$2*E14 -> -19.627113 | G14: =SUM(C14,E14:F14)*(1+$G$2) -> 26530.033 | H14: =-G14*$H$2 -> -132.65016 | I14: =SUM(G14:H14) -> 26397.382 | K14: 11 | L14: =D14-E14 -> 37.288692 | M14: =-F14 -> 19.627113 | N14: =-'Q2 Base'!$H$25 -> -25 | O14: =-D14*'Q2 Base'!$H$27 -> -20 | P14: =SUM(L14:O14)*$P$2 -> 0.11915805 | Q14: =MAX($Q$2-I14,0) -> 0 | R14: ='Q2 (ii)'!K14 -> 0.00094945059 | S14: =-Q14*R14 -> 0 | T14: ='Q2 (ii)'!J14 -> 0.0010005003 | U14: =H14*T14 -> -0.13271653 | V14: =-H14 -> 132.65016 | W14: =SUM(L14:P14,S14,U14:V14) -> 144.55241 | X14: ='Q2 (ii)'!E14 -> 0.98724265 | Y14: =(1+$Y$2)^-K14 -> 0.4750928 | Z14: =W14*X14 -> 142.7083 | AA14: =Y14*Z14 -> 67.799687
B15: 12 | C15: =I14 -> 26397.382 | D15: =$D$2 -> 2000 | E15: =D15*$E$2 -> 1962.7113 | F15: =-$F$2*E15 -> -19.627113 | G15: =SUM(C15,E15:F15)*(1+$G$2) -> 29474.085 | H15: =-G15*$H$2 -> -147.37043 | I15: =SUM(G15:H15) -> 29326.715 | K15: 12 | L15: =D15-E15 -> 37.288692 | M15: =-F15 -> 19.627113 | N15: =-'Q2 Base'!$H$25 -> -25 | O15: =-D15*'Q2 Base'!$H$27 -> -20 | P15: =SUM(L15:O15)*$P$2 -> 0.11915805 | Q15: =MAX($Q$2-I15,0) -> 0 | R15: ='Q2 (ii)'!K15 -> 0.0010075074 | S15: =-Q15*R15 -> 0 | T15: ='Q2 (ii)'!J15 -> 0.0011006054 | U15: =H15*T15 -> -0.16219669 | V15: =-H15 -> 147.37043 | W15: =SUM(L15:P15,S15,U15:V15) -> 159.24319 | X15: ='Q2 (ii)'!E15 -> 0.98531945 | Y15: =(1+$Y$2)^-K15 -> 0.44401196 | Z15: =W15*X15 -> 156.90541 | AA15: =Y15*Z15 -> 69.667881
B16: 13 | C16: =I15 -> 29326.715 | D16: =$D$2 -> 2000 | E16: =D16*$E$2 -> 1962.7113 | F16: =-$F$2*E16 -> -19.627113 | G16: =SUM(C16,E16:F16)*(1+$G$2) -> 32520.591 | H16: =-G16*$H$2 -> -162.60295 | I16: =SUM(G16:H16) -> 32357.988 | K16: 13 | L16: =D16-E16 -> 37.288692 | M16: =-F16 -> 19.627113 | N16: =-'Q2 Base'!$H$25 -> -25 | O16: =-D16*'Q2 Base'!$H$27 -> -20 | P16: =SUM(L16:O16)*$P$2 -> 0.11915805 | Q16: =MAX($Q$2-I16,0) -> 0 | R16: ='Q2 (ii)'!K16 -> 0.0010835869 | S16: =-Q16*R16 -> 0 | T16: ='Q2 (ii)'!J16 -> 0.0012007206 | U16: =H16*T16 -> -0.19524071 | V16: =-H16 -> 162.60295 | W16: =SUM(L16:P16,S16,U16:V16) -> 174.44268 | X16: ='Q2 (ii)'!E16 -> 0.98324447 | Y16: =(1+$Y$2)^-K16 -> 0.41496445 | Z16: =W16*X16 -> 171.5198 | AA16: =Y16*Z16 -> 71.174618
... B23: 20 | C23: =I22 -> 52893.932 | D23: =$D$2 -> 2000 | E23: =D23*$E$2 -> 1962.7113 | F23: =-$F$2*E23 -> -19.627113 | G23: =SUM(C23,E23:F23)*(1+$G$2) -> 57030.497 | H23: =-G23*$H$2 -> -285.15248 | I23: =SUM(G23:H23) -> 56745.344 | K23: 20 | L23: =D23-E23 -> 37.288692 | M23: =-F23 -> 19.627113 | N23: =-'Q2 Base'!$H$25 -> -25 | O23: =-D23*'Q2 Base'!$H$27 -> -20 | P23: =SUM(L23:O23)*$P$2 -> 0.11915805 | Q23: =MAX($Q$2-I23,0) -> 0 | R23: ='Q2 (ii)'!K23 -> 0.0022916238 | S23: =-Q23*R23 -> 0 | T23: ='Q2 (ii)'!J23 -> 0.0020020027 | U23: =H23*T23 -> -0.57087604 | V23: =-H23 -> 285.15248 | W23: =SUM(L23:P23,S23,U23:V23) -> 296.61657 | X23: ='Q2 (ii)'!E23 -> 0.96331968 | Y23: =(1+$Y$2)^-K23 -> 0.258419 | Z23: =W23*X23 -> 285.73658 | AA23: =Y23*Z23 -> 73.839763
Y25: Total PVP | AA25: =SUM(AA4:AA23) -> 199.98776
Y27: As percentage of P | AA27: =AA25/D2 -> 0.099993878 | AB27: [2]
Y28: Solving for allocation rate | AB28: [2]

Sheet Q2 Answers
B1: (i) | D1: (ii) (a) | G1: (iii)
A2: Policy Year | B2: Unit fund at EOY | D2: (1)p(01)(x+t-1) | E2: (1)p(02)(x+t-1) | G2: Allocation rate
A3: 1 | B3: ='Q2 (i)'!I4 -> 1946.4588 | D3: ='Q2 (ii)'!J4 -> 0.00040008002 | E3: ='Q2 (ii)'!K4 -> 0.00050412705 | G3: ='Q2 (iii)'!E2 -> 0.98135565
A4: 2 | B4: ='Q2 (i)'!I5 -> 3960.6544 | D4: ='Q2 (ii)'!J5 -> 0.00040008002 | E4: ='Q2 (ii)'!K5 -> 0.00054114639
A5: 3 | B5: ='Q2 (i)'!I6 -> 6044.9439 | D5: ='Q2 (ii)'!J6 -> 0.00045010128 | E5: ='Q2 (ii)'!K6 -> 0.00057516538
A6: 4 | B6: ='Q2 (i)'!I7 -> 8201.7668 | D6: ='Q2 (ii)'!J7 -> 0.00045010128 | E6: ='Q2 (ii)'!K7 -> 0.00061218735
A7: 5 | B7: ='Q2 (i)'!I8 -> 10433.647 | D7: ='Q2 (ii)'!J8 -> 0.00050012504 | E7: ='Q2 (ii)'!K8 -> 0.0006532133
A8: 6 | B8: ='Q2 (i)'!I9 -> 12743.197 | D8: ='Q2 (ii)'!J9 -> 0.00055015131 | E8: ='Q2 (ii)'!K9 -> 0.00069624232
A9: 7 | B9: ='Q2 (i)'!I10 -> 15133.119 | D9: ='Q2 (ii)'!J10 -> 0.00060018007 | E9: ='Q2 (ii)'!K10 -> 0.00074727914
A10: 8 | B10: ='Q2 (i)'!I11 -> 17606.21 | D10: ='Q2 (ii)'!J11 -> 0.00070024511 | E10: ='Q2 (ii)'!K11 -> 0.00080232177
A11: 9 | B11: ='Q2 (i)'!I12 -> 20165.365 | D11: ='Q2 (ii)'!J12 -> 0.00090040524 | E11: ='Q2 (ii)'!K12 -> 0.00085436487
A12: 10 | B12: ='Q2 (i)'!I13 -> 22813.579 | D12: ='Q2 (ii)'!J13 -> 0.0010005003 | E12: ='Q2 (ii)'!K13 -> 0.00090140614
A13: 11 | B13: ='Q2 (i)'!I14 -> 25553.95 | D13: ='Q2 (ii)'!J14 -> 0.0010005003 | E13: ='Q2 (ii)'!K14 -> 0.00094945059
A14: 12 | B14: ='Q2 (i)'!I15 -> 28389.686 | D14: ='Q2 (ii)'!J15 -> 0.0011006054 | E14: ='Q2 (ii)'!K15 -> 0.0010075074
A15: 13 | B15: ='Q2 (i)'!I16 -> 31324.106 | D15: ='Q2 (ii)'!J16 -> 0.0012007206 | E15: ='Q2 (ii)'!K16 -> 0.0010835869
... A22: 20 | B22: ='Q2 (i)'!I23 -> 54932.253 | D22: ='Q2 (ii)'!J23 -> 0.0020020027 | E22: ='Q2 (ii)'!K23 -> 0.0022916238
D23: ='Q2 (ii)'!J24 -> 0 | E23: ='Q2 (ii)'!K24 -> 0
