Workbook

Sheet Q1 Base
B1: Policy information - portfolio of 25-year term assurance policies | O1: Mortality Rate
B3: Policyholder age at start of policy | C3: 32
B4: Total premium | C4: 5000 | D4: per annum, payable annually in advance, ceasing immediately on death | M4: Age | O4: qx
B5: Sum assured | C5: 2500000 | D5: payable at the end of the year of death | M5: 30 | O5: 0.0005834
B6: The policy ceases on the payment of a benefit | M6: 31 | O6: 0.0006232
M7: 32 | O7: 0.0007463
M8: 33 | O8: 0.0007344
B9: Reserving assumptions | M9: 34 | O9: 0.0007952
M10: 35 | O10: 0.0008471
B11: Mortality | C11: See table on right | M11: 36 | O11: 0.0009746
B12: Commission | C12: 0.02 | D12: of all premiums, including the premium in the first year. | M12: 37 | O12: 0.0009703
B13: Expenses | C13: 1000 | D13: per annum, at the start of each year, including the first year. | M13: 38 | O13: 0.0010281
B14: Risk discount rate | C14: 0.0575 | D14: per annum | M14: 39 | O14: 0.0011376
M15: 40 | O15: 0.0012492
B16: You should ignore claim expenses. | M16: 41 | O16: 0.0014165
M17: 42 | O17: 0.0014904
M18: 43 | O18: 0.0016599
M19: 44 | O19: 0.0017666
M20: 45 | O20: 0.0018494
M21: 46 | O21: 0.001982
M22: 47 | O22: 0.0023176
M23: 48 | O23: 0.0023668
M24: 49 | O24: 0.0026407
M25: 50 | O25: 0.0029207
M26: 51 | O26: 0.0029822
M27: 52 | O27: 0.0032392
M28: 53 | O28: 0.0034328
... M35: 60 | O35: 0.0068894

Sheet Q1
A3: Policy Year | B3: Age at start | C3: SA | D3: Expense | E3: Comm % | F3: Prem | G3: Comm paid | H3: Net Prem | I3: px | J3: qx | K3: v | L3: vpx | M3: vqx | N3: A_x:n | O3: a_x:n | P3: PV of Net Prem | Q3: PV of Death Benefit | R3: Prospective Pol Val at BOY | S3: Prospective Pol Val at EOY | T3: V(t) | U3: V(t+1)
A4: 1 | B4: 32 | C4: ='Q1 Base'!$C$5 -> 2500000 | D4: ='Q1 Base'!$C$13 -> 1000 | E4: ='Q1 Base'!$C$12 -> 0.02 | F4: ='Q1 Base'!$C$4 -> 5000 | G4: =F4*E4 -> 100 | H4: =F4-G4-D4 -> 3900 | I4: =1-'Q1 Base'!O7 -> 0.9992537 | J4: ='Q1 Base'!O7 -> 0.0007463 | K4: =1/(1+'Q1 Base'!$C$14) -> 0.94562648 | L4: =K4*I4 -> 0.94492076 | M4: =K4*J4 -> 0.00070572104 | N4: =M4+L4*N5 -> 0.021060298 | O4: =1+L4*O5 -> 13.685522 | P4: =H4*O4 -> 53373.535 | Q4: =C4*N4 -> 52650.744 | R4: =Q4-P4 -> -722.79085 | S4: =R5 -> 1495.2646 | T4: =0 -> 0 | U4: =((T4+H4)*(1+'Q1 Base'!$C$14)-C4*J4)/I4 -> 2260.1868
A5: 2 | B5: 33 | C5: ='Q1 Base'!$C$5 -> 2500000 | D5: ='Q1 Base'!$C$13 -> 1000 | E5: ='Q1 Base'!$C$12 -> 0.02 | F5: ='Q1 Base'!$C$4 -> 5000 | G5: =F5*E5 -> 100 | H5: =F5-G5-D5 -> 3900 | I5: =1-'Q1 Base'!O8 -> 0.9992656 | J5: ='Q1 Base'!O8 -> 0.0007344 | K5: =1/(1+'Q1 Base'!$C$14) -> 0.94562648 | L5: =K5*I5 -> 0.94493201 | M5: =K5*J5 -> 0.00069446809 | N5: =M5+L5*N6 -> 0.021541041 | O5: =1+L5*O6 -> 13.424958 | P5: =H5*O5 -> 52357.338 | Q5: =C5*N5 -> 53852.602 | R5: =Q5-P5 -> 1495.2646 | S5: =R6 -> 3872.3362 | T5: =U4 -> 2260.1868 | U5: =((T5+H5)*(1+'Q1 Base'!$C$14)-C5*J5)/I5 -> 4681.8359
A6: 3 | B6: 34 | C6: ='Q1 Base'!$C$5 -> 2500000 | D6: ='Q1 Base'!$C$13 -> 1000 | E6: ='Q1 Base'!$C$12 -> 0.02 | F6: ='Q1 Base'!$C$4 -> 5000 | G6: =F6*E6 -> 100 | H6: =F6-G6-D6 -> 3900 | I6: =1-'Q1 Base'!O9 -> 0.9992048 | J6: ='Q1 Base'!O9 -> 0.0007952 | K6: =1/(1+'Q1 Base'!$C$14) -> 0.94562648 | L6: =K6*I6 -> 0.94487452 | M6: =K6*J6 -> 0.00075196217 | N6: =M6+L6*N7 -> 0.022061453 | O6: =1+L6*O7 -> 13.14905 | P6: =H6*O6 -> 51281.296 | Q6: =C6*N6 -> 55153.632 | R6: =Q6-P6 -> 3872.3362 | S6: =R7 -> 6236.2045 | T6: =U5 -> 4681.8359 | U6: =((T6+H6)*(1+'Q1 Base'!$C$14)-C6*J6)/I6 -> 7092.9317
A7: 4 | B7: 35 | C7: ='Q1 Base'!$C$5 -> 2500000 | D7: ='Q1 Base'!$C$13 -> 1000 | E7: ='Q1 Base'!$C$12 -> 0.02 | F7: ='Q1 Base'!$C$4 -> 5000 | G7: =F7*E7 -> 100 | H7: =F7-G7-D7 -> 3900 | I7: =1-'Q1 Base'!O10 -> 0.9991529 | J7: ='Q1 Base'!O10 -> 0.0008471 | K7: =1/(1+'Q1 Base'!$C$14) -> 0.94562648 | L7: =K7*I7 -> 0.94482544 | M7: =K7*J7 -> 0.00080104019 | N7: =M7+L7*N8 -> 0.02255272 | O7: =1+L7*O8 -> 12.857845 | P7: =H7*O7 -> 50145.596 | Q7: =C7*N7 -> 56381.801 | R7: =Q7-P7 -> 6236.2045 | S7: =R8 -> 8608.5786 | T7: =U6 -> 7092.9317 | U7: =((T7+H7)*(1+'Q1 Base'!$C$14)-C7*J7)/I7 -> 9515.3357
A8: 5 | B8: 36 | C8: ='Q1 Base'!$C$5 -> 2500000 | D8: ='Q1 Base'!$C$13 -> 1000 | E8: ='Q1 Base'!$C$12 -> 0.02 | F8: ='Q1 Base'!$C$4 -> 5000 | G8: =F8*E8 -> 100 | H8: =F8-G8-D8 -> 3900 | I8: =1-'Q1 Base'!O11 -> 0.9990254 | J8: ='Q1 Base'!O11 -> 0.0009746 | K8: =1/(1+'Q1 Base'!$C$14) -> 0.94562648 | L8: =K8*I8 -> 0.94470487 | M8: =K8*J8 -> 0.00092160757 | N8: =M8+L8*N9 -> 0.023021904 | O8: =1+L8*O9 -> 12.550303 | P8: =H8*O8 -> 48946.18 | Q8: =C8*N8 -> 57554.759 | R8: =Q8-P8 -> 8608.5786 | S8: =R9 -> 10801.849 | T8: =U7 -> 9515.3357 | U8: =((T8+H8)*(1+'Q1 Base'!$C$14)-C8*J8)/I8 -> 11761.68
A9: 6 | B9: 37 | C9: ='Q1 Base'!$C$5 -> 2500000 | D9: ='Q1 Base'!$C$13 -> 1000 | E9: ='Q1 Base'!$C$12 -> 0.02 | F9: ='Q1 Base'!$C$4 -> 5000 | G9: =F9*E9 -> 100 | H9: =F9-G9-D9 -> 3900 | I9: =1-'Q1 Base'!O12 -> 0.9990297 | J9: ='Q1 Base'!O12 -> 0.0009703 | K9: =1/(1+'Q1 Base'!$C$14) -> 0.94562648 | L9: =K9*I9 -> 0.94470894 | M9: =K9*J9 -> 0.00091754137 | N9: =M9+L9*N10 -> 0.023393863 | O9: =1+L9*O10 -> 12.226361 | P9: =H9*O9 -> 47682.807 | Q9: =C9*N9 -> 58484.657 | R9: =Q9-P9 -> 10801.849 | S9: =R10 -> 13134.2 | T9: =U8 -> 11761.68 | U9: =((T9+H9)*(1+'Q1 Base'!$C$14)-C9*J9)/I9 -> 14150.207
A10: 7 | B10: 38 | C10: ='Q1 Base'!$C$5 -> 2500000 | D10: ='Q1 Base'!$C$13 -> 1000 | E10: ='Q1 Base'!$C$12 -> 0.02 | F10: ='Q1 Base'!$C$4 -> 5000 | G10: =F10*E10 -> 100 | H10: =F10-G10-D10 -> 3900 | I10: =1-'Q1 Base'!O13 -> 0.9989719 | J10: ='Q1 Base'!O13 -> 0.0010281 | K10: =1/(1+'Q1 Base'!$C$14) -> 0.94562648 | L10: =K10*I10 -> 0.94465428 | M10: =K10*J10 -> 0.00097219858 | N10: =M10+L10*N11 -> 0.023791795 | O10: =1+L10*O11 -> 11.883407 | P10: =H10*O10 -> 46345.287 | Q10: =C10*N10 -> 59479.487 | R10: =Q10-P10 -> 13134.2 | S10: =R11 -> 15459.31 | T10: =U9 -> 14150.207 | U10: =((T10+H10)*(1+'Q1 Base'!$C$14)-C10*J10)/I10 -> 16534.843
A11: 8 | B11: 39 | C11: ='Q1 Base'!$C$5 -> 2500000 | D11: ='Q1 Base'!$C$13 -> 1000 | E11: ='Q1 Base'!$C$12 -> 0.02 | F11: ='Q1 Base'!$C$4 -> 5000 | G11: =F11*E11 -> 100 | H11: =F11-G11-D11 -> 3900 | I11: =1-'Q1 Base'!O14 -> 0.9988624 | J11: ='Q1 Base'!O14 -> 0.0011376 | K11: =1/(1+'Q1 Base'!$C$14) -> 0.94562648 | L11: =K11*I11 -> 0.94455073 | M11: =K11*J11 -> 0.0010757447 | N11: =M11+L11*N12 -> 0.024156558 | O11: =1+L11*O12 -> 11.521048 | P11: =H11*O11 -> 44932.086 | Q11: =C11*N11 -> 60391.396 | R11: =Q11-P11 -> 15459.31 | S11: =R12 -> 17648.547 | T11: =U10 -> 16534.843 | U11: =((T11+H11)*(1+'Q1 Base'!$C$14)-C11*J11)/I11 -> 18787.219
A12: 9 | B12: 40 | C12: ='Q1 Base'!$C$5 -> 2500000 | D12: ='Q1 Base'!$C$13 -> 1000 | E12: ='Q1 Base'!$C$12 -> 0.02 | F12: ='Q1 Base'!$C$4 -> 5000 | G12: =F12*E12 -> 100 | H12: =F12-G12-D12 -> 3900 | I12: =1-'Q1 Base'!O15 -> 0.9987508 | J12: ='Q1 Base'!O15 -> 0.0012492 | K12: =1/(1+'Q1 Base'!$C$14) -> 0.94562648 | L12: =K12*I12 -> 0.9444452 | M12: =K12*J12 -> 0.0011812766 | N12: =M12+L12*N13 -> 0.024435759 | O12: =1+L12*O13 -> 11.138679 | P12: =H12*O12 -> 43440.849 | Q12: =C12*N12 -> 61089.397 | R12: =Q12-P12 -> 17648.547 | S12: =R13 -> 19689.185 | T12: =U11 -> 18787.219 | U12: =((T12+H12)*(1+'Q1 Base'!$C$14)-C12*J12)/I12 -> 20894.836
A13: 10 | B13: 41 | C13: ='Q1 Base'!$C$5 -> 2500000 | D13: ='Q1 Base'!$C$13 -> 1000 | E13: ='Q1 Base'!$C$12 -> 0.02 | F13: ='Q1 Base'!$C$4 -> 5000 | G13: =F13*E13 -> 100 | H13: =F13-G13-D13 -> 3900 | I13: =1-'Q1 Base'!O16 -> 0.9985835 | J13: ='Q1 Base'!O16 -> 0.0014165 | K13: =1/(1+'Q1 Base'!$C$14) -> 0.94562648 | L13: =K13*I13 -> 0.944287 | M13: =K13*J13 -> 0.0013394799 | N13: =M13+L13*N14 -> 0.024622373 | O13: =1+L13*O14 -> 10.735064 | P13: =H13*O13 -> 41866.748 | Q13: =C13*N13 -> 61555.933 | R13: =Q13-P13 -> 19689.185 | S13: =R14 -> 21434.675 | T13: =U12 -> 20894.836 | U13: =((T13+H13)*(1+'Q1 Base'!$C$14)-C13*J13)/I13 -> 22711.46
A14: 11 | B14: 42 | C14: ='Q1 Base'!$C$5 -> 2500000 | D14: ='Q1 Base'!$C$13 -> 1000 | E14: ='Q1 Base'!$C$12 -> 0.02 | F14: ='Q1 Base'!$C$4 -> 5000 | G14: =F14*E14 -> 100 | H14: =F14-G14-D14 -> 3900 | I14: =1-'Q1 Base'!O17 -> 0.9985096 | J14: ='Q1 Base'!O17 -> 0.0014904 | K14: =1/(1+'Q1 Base'!$C$14) -> 0.94562648 | L14: =K14*I14 -> 0.94421712 | M14: =K14*J14 -> 0.0014093617 | N14: =M14+L14*N15 -> 0.024656586 | O14: =1+L14*O15 -> 10.309433 | P14: =H14*O14 -> 40206.789 | Q14: =C14*N14 -> 61641.464 | R14: =Q14-P14 -> 21434.675 | S14: =R15 -> 23099.847 | T14: =U13 -> 22711.46 | U14: =((T14+H14)*(1+'Q1 Base'!$C$14)-C14*J14)/I14 -> 24452.062
A15: 12 | B15: 43 | C15: ='Q1 Base'!$C$5 -> 2500000 | D15: ='Q1 Base'!$C$13 -> 1000 | E15: ='Q1 Base'!$C$12 -> 0.02 | F15: ='Q1 Base'!$C$4 -> 5000 | G15: =F15*E15 -> 100 | H15: =F15-G15-D15 -> 3900 | I15: =1-'Q1 Base'!O18 -> 0.9983401 | J15: ='Q1 Base'!O18 -> 0.0016599 | K15: =1/(1+'Q1 Base'!$C$14) -> 0.94562648 | L15: =K15*I15 -> 0.94405683 | M15: =K15*J15 -> 0.0015696454 | N15: =M15+L15*N16 -> 0.024620634 | O15: =1+L15*O16 -> 9.85942 | P15: =H15*O15 -> 38451.738 | Q15: =C15*N15 -> 61551.585 | R15: =Q15-P15 -> 23099.847 | S15: =R16 -> 24443.161 | T15: =U14 -> 24452.062 | U15: =((T15+H15)*(1+'Q1 Base'!$C$14)-C15*J15)/I15 -> 25875.507
A16: 13 | B16: 44 | C16: ='Q1 Base'!$C$5 -> 2500000 | D16: ='Q1 Base'!$C$13 -> 1000 | E16: ='Q1 Base'!$C$12 -> 0.02 | F16: ='Q1 Base'!$C$4 -> 5000 | G16: =F16*E16 -> 100 | H16: =F16-G16-D16 -> 3900 | I16: =1-'Q1 Base'!O19 -> 0.9982334 | J16: ='Q1 Base'!O19 -> 0.0017666 | K16: =1/(1+'Q1 Base'!$C$14) -> 0.94562648 | L16: =K16*I16 -> 0.94395593 | M16: =K16*J16 -> 0.0016705437 | N16: =M16+L16*N17 -> 0.02441695 | O16: =1+L16*O17 -> 9.3844138 | P16: =H16*O16 -> 36599.214 | Q16: =C16*N16 -> 61042.375 | R16: =Q16-P16 -> 24443.161 | S16: =R17 -> 25601.621 | T16: =U15 -> 25875.507 | U16: =((T16+H16)*(1+'Q1 Base'!$C$14)-C16*J16)/I16 -> 27119.007
... A28: 25 | B28: 56 | C28: ='Q1 Base'!$C$5 -> 2500000 | D28: ='Q1 Base'!$C$13 -> 1000 | E28: ='Q1 Base'!$C$12 -> 0.02 | F28: ='Q1 Base'!$C$4 -> 5000 | G28: =F28*E28 -> 100 | H28: =F28-G28-D28 -> 3900 | I28: =1-'Q1 Base'!O31 -> 0.9953171 | J28: ='Q1 Base'!O31 -> 0.0046829 | K28: =1/(1+'Q1 Base'!$C$14) -> 0.94562648 | L28: =K28*I28 -> 0.9411982 | M28: =K28*J28 -> 0.0044282742 | N28: =M28+L28*N29 -> 0.0044282742 | O28: =1+L28*O29 -> 1 | P28: =H28*O28 -> 3900 | Q28: =C28*N28 -> 11070.686 | R28: =Q28-P28 -> 7170.6856 | S28: =R29 -> 0 | T28: =U27 -> 10067.881 | U28: =((T28+H28)*(1+'Q1 Base'!$C$14)-C28*J28)/I28 -> 3078.1988

Sheet Q1 Answers
A2: Policy Year | B2: Prospective Reserve at EOY | C2: Retrospective Reserve at EOY
A3: 1 | B3: ='Q1'!S4 -> 1495.2646 | C3: ='Q1'!U4 -> 2260.1868
A4: 2 | B4: ='Q1'!S5 -> 3872.3362 | C4: ='Q1'!U5 -> 4681.8359
A5: 3 | B5: ='Q1'!S6 -> 6236.2045 | C5: ='Q1'!U6 -> 7092.9317
A6: 4 | B6: ='Q1'!S7 -> 8608.5786 | C6: ='Q1'!U7 -> 9515.3357
A7: 5 | B7: ='Q1'!S8 -> 10801.849 | C7: ='Q1'!U8 -> 11761.68
A8: 6 | B8: ='Q1'!S9 -> 13134.2 | C8: ='Q1'!U9 -> 14150.207
A9: 7 | B9: ='Q1'!S10 -> 15459.31 | C9: ='Q1'!U10 -> 16534.843
A10: 8 | B10: ='Q1'!S11 -> 17648.547 | C10: ='Q1'!U11 -> 18787.219
A11: 9 | B11: ='Q1'!S12 -> 19689.185 | C11: ='Q1'!U12 -> 20894.836
A12: 10 | B12: ='Q1'!S13 -> 21434.675 | C12: ='Q1'!U13 -> 22711.46
A13: 11 | B13: ='Q1'!S14 -> 23099.847 | C13: ='Q1'!U14 -> 24452.062
A14: 12 | B14: ='Q1'!S15 -> 24443.161 | C14: ='Q1'!U15 -> 25875.507
... A27: 25 | B27: ='Q1'!S28 -> 0 | C27: ='Q1'!U28 -> 3078.1988

Sheet Q2 Base
B2: Policy Year | G2: Policy Terms
B3: Beginning (t-1) | C3: Ending (t) | D3: mu(01)(x+t-1) critical illness | E3: mu(02)(x+t-1) mortality
B4: 0 | C4: 1 | D4: 0.00040008002 | E4: 0.00050412705 | G4: Age at outset | H4: 30 | I4: exact.
B5: 1 | C5: 2 | D5: 0.00040008002 | E5: 0.00054114639 | G5: Policy Term | H5: 20 | I5: years.
B6: 2 | C6: 3 | D6: 0.00045010128 | E6: 0.00057516538 | G6: Minimum guaranteed death benefit | H6: 15000
B7: 3 | C7: 4 | D7: 0.00045010128 | E7: 0.00061218735 | G7: Annual Premium | H7: 2000 | I7: payable annually in advance.
B8: 4 | C8: 5 | D8: 0.00050012504 | E8: 0.0006532133 | G8: Allocation rate for all policy years | H8: 0.95
B9: 5 | C9: 6 | D9: 0.00055015131 | E9: 0.00069624232 | G9: Bid offer spread | H9: 0.01
B10: 6 | C10: 7 | D10: 0.00060018007 | E10: 0.00074727914 | G10: Annual Management Charge | H10: 0.005 | I10: per annum, payable at the end of each policy year by unit cancellation.
B11: 7 | C11: 8 | D11: 0.00070024511 | E11: 0.00080232177
B12: 8 | C12: 9 | D12: 0.00090040524 | E12: 0.00085436487
B13: 9 | C13: 10 | D13: 0.0010005003 | E13: 0.00090140614
B14: 10 | C14: 11 | D14: 0.0010005003 | E14: 0.00094945059
B15: 11 | C15: 12 | D15: 0.0011006054 | E15: 0.0010075074 | G15: Profit Test Assumptions
B16: 12 | C16: 13 | D16: 0.0012007206 | E16: 0.0010835869
B17: 13 | C17: 14 | D17: 0.0012007206 | E17: 0.0011796956 | G17: Unit growth rate | H17: 0.04 | I17: per annum effective.
B18: 14 | C18: 15 | D18: 0.0013008457 | E18: 0.0013008457 | G18: Return on non-unit balances | H18: 0.01 | I18: per annum effective.
B19: 15 | C19: 16 | D19: 0.0014009809 | E19: 0.0014480479 | G19: Risk Discount Rate | H19: 0.07 | I19: per annum effective.
B20: 16 | C20: 17 | D20: 0.0015011261 | E20: 0.0016153039
B21: 17 | C21: 18 | D21: 0.0016012814 | E21: 0.001806631 | G21: Independent mortality and critical illness diagnosis rates are given by the table.
B22: 18 | C22: 19 | D22: 0.0018016219 | E22: 0.0020310612 | G22: You should assume that deaths and critical illness diagnoses occur uniformly across each policy year.
B23: 19 | C23: 20 | D23: 0.0020020027 | E23: 0.0022916238
B24: 20 | G24: Initial Expenses | H24: 75 | I24: at the start of the first policy year.
G25: Renewal expenses | H25: 25 | I25: per annum, at the start of each subsequent policy year.
G26: Initial Commision | H26: 0.5 | I26: of the premium payable at the start of the first policy year.
G27: Renewal Commission | H27: 0.01 | I27: of the premiums payable at the start of each subsequent policy year.

Sheet Q2 (i)
B2: UNIT FUND
B3: Policy Year | C3: Prem | D3: Alloc Rate | E3: B/O Spread | F3: Alloc Prem | G3: Unit fund BOY | H3: Unit Interest | I3: Unit fund val before FMC | J3: FMC | K3: Unit fund val after FMC
B4: 1 | C4: ='Q2 Base'!$H$7 -> 2000 | D4: ='Q2 Base'!$H$8 -> 0.95 | E4: =1-'Q2 Base'!$H$9 -> 0.99 | F4: =C4*D4*E4 -> 1881 | G4: =F4 -> 1881 | H4: =G4*'Q2 Base'!$H$17 -> 75.24 | I4: =G4+H4 -> 1956.24 | J4: =I4*'Q2 Base'!$H$10 -> 9.7812 | K4: =I4-J4 -> 1946.4588
B5: 2 | C5: ='Q2 Base'!$H$7 -> 2000 | D5: ='Q2 Base'!$H$8 -> 0.95 | E5: =1-'Q2 Base'!$H$9 -> 0.99 | F5: =C5*D5*E5 -> 1881 | G5: =K4+F5 -> 3827.4588 | H5: =G5*'Q2 Base'!$H$17 -> 153.09835 | I5: =G5+H5 -> 3980.5572 | J5: =I5*'Q2 Base'!$H$10 -> 19.902786 | K5: =I5-J5 -> 3960.6544
B6: 3 | C6: ='Q2 Base'!$H$7 -> 2000 | D6: ='Q2 Base'!$H$8 -> 0.95 | E6: =1-'Q2 Base'!$H$9 -> 0.99 | F6: =C6*D6*E6 -> 1881 | G6: =K5+F6 -> 5841.6544 | H6: =G6*'Q2 Base'!$H$17 -> 233.66617 | I6: =G6+H6 -> 6075.3205 | J6: =I6*'Q2 Base'!$H$10 -> 30.376603 | K6: =I6-J6 -> 6044.9439
B7: 4 | C7: ='Q2 Base'!$H$7 -> 2000 | D7: ='Q2 Base'!$H$8 -> 0.95 | E7: =1-'Q2 Base'!$H$9 -> 0.99 | F7: =C7*D7*E7 -> 1881 | G7: =K6+F7 -> 7925.9439 | H7: =G7*'Q2 Base'!$H$17 -> 317.03776 | I7: =G7+H7 -> 8242.9817 | J7: =I7*'Q2 Base'!$H$10 -> 41.214908 | K7: =I7-J7 -> 8201.7668
B8: 5 | C8: ='Q2 Base'!$H$7 -> 2000 | D8: ='Q2 Base'!$H$8 -> 0.95 | E8: =1-'Q2 Base'!$H$9 -> 0.99 | F8: =C8*D8*E8 -> 1881 | G8: =K7+F8 -> 10082.767 | H8: =G8*'Q2 Base'!$H$17 -> 403.31067 | I8: =G8+H8 -> 10486.077 | J8: =I8*'Q2 Base'!$H$10 -> 52.430387 | K8: =I8-J8 -> 10433.647
B9: 6 | C9: ='Q2 Base'!$H$7 -> 2000 | D9: ='Q2 Base'!$H$8 -> 0.95 | E9: =1-'Q2 Base'!$H$9 -> 0.99 | F9: =C9*D9*E9 -> 1881 | G9: =K8+F9 -> 12314.647 | H9: =G9*'Q2 Base'!$H$17 -> 492.58588 | I9: =G9+H9 -> 12807.233 | J9: =I9*'Q2 Base'!$H$10 -> 64.036165 | K9: =I9-J9 -> 12743.197
B10: 7 | C10: ='Q2 Base'!$H$7 -> 2000 | D10: ='Q2 Base'!$H$8 -> 0.95 | E10: =1-'Q2 Base'!$H$9 -> 0.99 | F10: =C10*D10*E10 -> 1881 | G10: =K9+F10 -> 14624.197 | H10: =G10*'Q2 Base'!$H$17 -> 584.96787 | I10: =G10+H10 -> 15209.165 | J10: =I10*'Q2 Base'!$H$10 -> 76.045823 | K10: =I10-J10 -> 15133.119
B11: 8 | C11: ='Q2 Base'!$H$7 -> 2000 | D11: ='Q2 Base'!$H$8 -> 0.95 | E11: =1-'Q2 Base'!$H$9 -> 0.99 | F11: =C11*D11*E11 -> 1881 | G11: =K10+F11 -> 17014.119 | H11: =G11*'Q2 Base'!$H$17 -> 680.56475 | I11: =G11+H11 -> 17694.684 | J11: =I11*'Q2 Base'!$H$10 -> 88.473418 | K11: =I11-J11 -> 17606.21
B12: 9 | C12: ='Q2 Base'!$H$7 -> 2000 | D12: ='Q2 Base'!$H$8 -> 0.95 | E12: =1-'Q2 Base'!$H$9 -> 0.99 | F12: =C12*D12*E12 -> 1881 | G12: =K11+F12 -> 19487.21 | H12: =G12*'Q2 Base'!$H$17 -> 779.48841 | I12: =G12+H12 -> 20266.699 | J12: =I12*'Q2 Base'!$H$10 -> 101.33349 | K12: =I12-J12 -> 20165.365
B13: 10 | C13: ='Q2 Base'!$H$7 -> 2000 | D13: ='Q2 Base'!$H$8 -> 0.95 | E13: =1-'Q2 Base'!$H$9 -> 0.99 | F13: =C13*D13*E13 -> 1881 | G13: =K12+F13 -> 22046.365 | H13: =G13*'Q2 Base'!$H$17 -> 881.8546 | I13: =G13+H13 -> 22928.22 | J13: =I13*'Q2 Base'!$H$10 -> 114.6411 | K13: =I13-J13 -> 22813.579
B14: 11 | C14: ='Q2 Base'!$H$7 -> 2000 | D14: ='Q2 Base'!$H$8 -> 0.95 | E14: =1-'Q2 Base'!$H$9 -> 0.99 | F14: =C14*D14*E14 -> 1881 | G14: =K13+F14 -> 24694.579 | H14: =G14*'Q2 Base'!$H$17 -> 987.78314 | I14: =G14+H14 -> 25682.362 | J14: =I14*'Q2 Base'!$H$10 -> 128.41181 | K14: =I14-J14 -> 25553.95
B15: 12 | C15: ='Q2 Base'!$H$7 -> 2000 | D15: ='Q2 Base'!$H$8 -> 0.95 | E15: =1-'Q2 Base'!$H$9 -> 0.99 | F15: =C15*D15*E15 -> 1881 | G15: =K14+F15 -> 27434.95 | H15: =G15*'Q2 Base'!$H$17 -> 1097.398 | I15: =G15+H15 -> 28532.348 | J15: =I15*'Q2 Base'!$H$10 -> 142.66174 | K15: =I15-J15 -> 28389.686
B16: 13 | C16: ='Q2 Base'!$H$7 -> 2000 | D16: ='Q2 Base'!$H$8 -> 0.95 | E16: =1-'Q2 Base'!$H$9 -> 0.99 | F16: =C16*D16*E16 -> 1881 | G16: =K15+F16 -> 30270.686 | H16: =G16*'Q2 Base'!$H$17 -> 1210.8274 | I16: =G16+H16 -> 31481.514 | J16: =I16*'Q2 Base'!$H$10 -> 157.40757 | K16: =I16-J16 -> 31324.106
... B23: 20 | C23: ='Q2 Base'!$H$7 -> 2000 | D23: ='Q2 Base'!$H$8 -> 0.95 | E23: =1-'Q2 Base'!$H$9 -> 0.99 | F23: =C23*D23*E23 -> 1881 | G23: =K22+F23 -> 53084.899 | H23: =G23*'Q2 Base'!$H$17 -> 2123.3959 | I23: =G23+H23 -> 55208.295 | J23: =I23*'Q2 Base'!$H$10 -> 276.04147 | K23: =I23-J23 -> 54932.253

Sheet Q2 (ii)
G1: step_size | H1: 1
A2: Policy Year | S2: [1] | T2: For picking up correct probability
A3: Beginning | B3: Ending | C3: Force of critical illness | D3: Force of mortality | E3: (t-1)(00)px | F3: d/dt (t-1)(01)px | G3: d/dt (t-1)(02)px | H3: (t-1)(01)px | I3: (t-1)(02)px | J3: (01)p_x+(t-1) | K3: (02)p_x+(t-1) | V3: [1] | W3: [2] | X3: [1] | Y3: [1]
A4: 0 | B4: =A4+1 -> 1 | C4: ='Q2 Base'!D4 -> 0.00040008002 | D4: ='Q2 Base'!E4 -> 0.00050412705 | E4: =1 -> 1 | F4: =C4*E4 -> 0.00040008002 | G4: =E4*D4 -> 0.00050412705 | H4: =0 -> 0 | I4: =0 -> 0 | J4: =(H5-H4)/$E4 -> 0.00040008002 | K4: =(I5-I4)/$E4 -> 0.00050412705
A5: =A4+1 -> 1 | B5: =A5+1 -> 2 | C5: ='Q2 Base'!D5 -> 0.00040008002 | D5: ='Q2 Base'!E5 -> 0.00054114639 | E5: =E4*EXP(-C4-D4) -> 0.9990962 | F5: =C5*E5 -> 0.00039971843 | G5: =E5*D5 -> 0.00054065731 | H5: =H4+$H$1*F4 -> 0.00040008002 | I5: =I4+$H$1*G4 -> 0.00050412705 | J5: =(H6-H5)/$E5 -> 0.00040008002 | K5: =(I6-I5)/$E5 -> 0.00054114639
A6: =A5+1 -> 2 | B6: =A6+1 -> 3 | C6: ='Q2 Base'!D6 -> 0.00045010128 | D6: ='Q2 Base'!E6 -> 0.00057516538 | E6: =E5*EXP(-C5-D5) -> 0.99815627 | F6: =C6*E6 -> 0.00044927141 | G6: =E6*D6 -> 0.00057410493 | H6: =H5+$H$1*F5 -> 0.00079979845 | I6: =I5+$H$1*G5 -> 0.0010447844 | J6: =(H7-H6)/$E6 -> 0.00045010128 | K6: =(I7-I6)/$E6 -> 0.00057516538
A7: =A6+1 -> 3 | B7: =A7+1 -> 4 | C7: ='Q2 Base'!D7 -> 0.00045010128 | D7: ='Q2 Base'!E7 -> 0.00061218735 | E7: =E6*EXP(-C6-D6) -> 0.99713342 | F7: =C7*E7 -> 0.00044881103 | G7: =E7*D7 -> 0.00061043246 | H7: =H6+$H$1*F6 -> 0.0012490699 | I7: =I6+$H$1*G6 -> 0.0016188893 | J7: =(H8-H7)/$E7 -> 0.00045010128 | K7: =(I8-I7)/$E7 -> 0.00061218735
A8: =A7+1 -> 4 | B8: =A8+1 -> 5 | C8: ='Q2 Base'!D8 -> 0.00050012504 | D8: ='Q2 Base'!E8 -> 0.0006532133 | E8: =E7*EXP(-C7-D7) -> 0.99607474 | F8: =C8*E8 -> 0.00049816192 | G8: =E8*D8 -> 0.00065064926 | H8: =H7+$H$1*F7 -> 0.0016978809 | I8: =I7+$H$1*G7 -> 0.0022293217 | J8: =(H9-H8)/$E8 -> 0.00050012504 | K8: =(I9-I8)/$E8 -> 0.0006532133
A9: =A8+1 -> 5 | B9: =A9+1 -> 6 | C9: ='Q2 Base'!D9 -> 0.00055015131 | D9: ='Q2 Base'!E9 -> 0.00069624232 | E9: =E8*EXP(-C8-D8) -> 0.99492659 | F9: =C9*E9 -> 0.00054736016 | G9: =E9*D9 -> 0.00069271 | H9: =H8+$H$1*F8 -> 0.0021960428 | I9: =I8+$H$1*G8 -> 0.002879971 | J9: =(H10-H9)/$E9 -> 0.00055015131 | K9: =(I10-I9)/$E9 -> 0.00069624232
A10: =A9+1 -> 6 | B10: =A10+1 -> 7 | C10: ='Q2 Base'!D10 -> 0.00060018007 | D10: ='Q2 Base'!E10 -> 0.00074727914 | E10: =E9*EXP(-C9-D9) -> 0.99368729 | F10: =C10*E10 -> 0.00059639131 | G10: =E10*D10 -> 0.00074256179 | H10: =H9+$H$1*F9 -> 0.002743403 | I10: =I9+$H$1*G9 -> 0.003572681 | J10: =(H11-H10)/$E10 -> 0.00060018007 | K10: =(I11-I10)/$E10 -> 0.00074727914
A11: =A10+1 -> 7 | B11: =A11+1 -> 8 | C11: ='Q2 Base'!D11 -> 0.00070024511 | D11: ='Q2 Base'!E11 -> 0.00080232177 | E11: =E10*EXP(-C10-D10) -> 0.99234924 | F11: =C11*E11 -> 0.00069488771 | G11: =E11*D11 -> 0.0007961834 | H11: =H10+$H$1*F10 -> 0.0033397943 | I11: =I10+$H$1*G10 -> 0.0043152428 | J11: =(H12-H11)/$E11 -> 0.00070024511 | K11: =(I12-I11)/$E11 -> 0.00080232177
A12: =A11+1 -> 8 | B12: =A12+1 -> 9 | C12: ='Q2 Base'!D12 -> 0.00090040524 | D12: ='Q2 Base'!E12 -> 0.00085436487 | E12: =E11*EXP(-C11-D11) -> 0.99085929 | F12: =C12*E12 -> 0.0008921749 | G12: =E12*D12 -> 0.00084655536 | H12: =H11+$H$1*F11 -> 0.004034682 | I12: =I11+$H$1*G11 -> 0.0051114262 | J12: =(H13-H12)/$E12 -> 0.00090040524 | K12: =(I13-I12)/$E12 -> 0.00085436487
A13: =A12+1 -> 9 | B13: =A13+1 -> 10 | C13: ='Q2 Base'!D13 -> 0.0010005003 | D13: ='Q2 Base'!E13 -> 0.00090140614 | E13: =E12*EXP(-C12-D12) -> 0.98912208 | F13: =C13*E13 -> 0.00098961697 | G13: =E13*D13 -> 0.00089160072 | H13: =H12+$H$1*F12 -> 0.0049268569 | I13: =I12+$H$1*G12 -> 0.0059579815 | J13: =(H14-H13)/$E13 -> 0.0010005003 | K13: =(I14-I13)/$E13 -> 0.00090140614
A14: =A13+1 -> 10 | B14: =A14+1 -> 11 | C14: ='Q2 Base'!D14 -> 0.0010005003 | D14: ='Q2 Base'!E14 -> 0.00094945059 | E14: =E13*EXP(-C13-D13) -> 0.98724265 | F14: =C14*E14 -> 0.0009877366 | G14: =E14*D14 -> 0.00093733811 | H14: =H13+$H$1*F13 -> 0.0059164739 | I14: =I13+$H$1*G13 -> 0.0068495823 | J14: =(H15-H14)/$E14 -> 0.0010005003 | K14: =(I15-I14)/$E14 -> 0.00094945059
A15: =A14+1 -> 11 | B15: =A15+1 -> 12 | C15: ='Q2 Base'!D15 -> 0.0011006054 | D15: ='Q2 Base'!E15 -> 0.0010075074 | E15: =E14*EXP(-C14-D14) -> 0.98531945 | F15: =C15*E15 -> 0.001084448 | G15: =E15*D15 -> 0.0009927166 | H15: =H14+$H$1*F14 -> 0.0069042105 | I15: =I14+$H$1*G14 -> 0.0077869204 | J15: =(H16-H15)/$E15 -> 0.0011006054 | K15: =(I16-I15)/$E15 -> 0.0010075074
A16: =A15+1 -> 12 | B16: =A16+1 -> 13 | C16: ='Q2 Base'!D16 -> 0.0012007206 | D16: ='Q2 Base'!E16 -> 0.0010835869 | E16: =E15*EXP(-C15-D15) -> 0.98324447 | F16: =C16*E16 -> 0.0011806019 | G16: =E16*D16 -> 0.0010654308 | H16: =H15+$H$1*F15 -> 0.0079886584 | I16: =I15+$H$1*G15 -> 0.008779637 | J16: =(H17-H16)/$E16 -> 0.0012007206 | K16: =(I17-I16)/$E16 -> 0.0010835869
... A23: =A22+1 -> 19 | B23: =A23+1 -> 20 | C23: ='Q2 Base'!D23 -> 0.0020020027 | D23: ='Q2 Base'!E23 -> 0.0022916238 | E23: =E22*EXP(-C22-D22) -> 0.96331968 | F23: =C23*E23 -> 0.0019285686 | G23: =E23*D23 -> 0.0022075663 | H23: =H22+$H$1*F22 -> 0.017744876 | I23: =I22+$H$1*G22 -> 0.018978263 | J23: =(H24-H23)/$E23 -> 0.0020020027 | K23: =(I24-I23)/$E23 -> 0.0022916238
A24: =A23+1 -> 20 | E24: =E23*EXP(-C23-D23) -> 0.95919241 | F24: =C24*E24 -> 0 | G24: =E24*D24 -> 0 | H24: =H23+$H$1*F23 -> 0.019673444 | I24: =I23+$H$1*G23 -> 0.021185829

Sheet Q2 (iii)
B2: UNIT FUND | D2: 0.98135504 | E2: Modified Alloc Rate | O2: Non-unit fund | Z2: =1/(1+'Q2 Base'!H19) -> 0.93457944
B3: Policy Year | C3: Prem | D3: Alloc Rate | E3: B/O Spread | F3: Alloc Prem | G3: Unit fund BOY | H3: Unit Interest | I3: Unit fund val before FMC | J3: FMC | K3: Unit fund val after FMC | O3: Policy Year | P3: Unalloc Prem | Q3: Expenses | R3: Comm | S3: Int | T3: FMC | U3: Mort Cost | V3: Sick Cost | W3: SFC | X3: t-1px | Y3: Profit vector | Z3: v^n RDR | AA3: EPV
B4: 1 | C4: ='Q2 Base'!$H$7 -> 2000 | D4: =$D$2 -> 0.98135504 | E4: =1-'Q2 Base'!$H$9 -> 0.99 | F4: =C4*D4*E4 -> 1943.083 | G4: =F4 -> 1943.083 | H4: =G4*'Q2 Base'!$H$17 -> 77.723319 | I4: =G4+H4 -> 2020.8063 | J4: =I4*'Q2 Base'!$H$10 -> 10.104031 | K4: =I4-J4 -> 2010.7023 | O4: 1 | P4: =C4-F4 -> 56.917026 | Q4: ='Q2 Base'!H24 -> 75 | R4: ='Q2 Base'!H7*'Q2 Base'!H26 -> 1000 | S4: =(P4-Q4-R4)*'Q2 Base'!$H$18 -> -10.18083 | T4: =J4 -> 10.104031 | U4: =MAX('Q2 (ii)'!K4*('Q2 Base'!$H$6-'Q2 (iii)'!K4),0) -> 6.5482564 | V4: ='Q2 (ii)'!J4*'Q2 (iii)'!J4 -> 0.0040424211 | W4: =P4-Q4-R4+S4+T4-U4-V4 -> -1024.7121 | X4: ='Q2 (ii)'!E4 -> 1 | Y4: =X4*W4 -> -1024.7121 | Z4: =$Z$2^O4 -> 0.93457944 | AA4: =Y4*Z4 -> -957.67483
B5: 2 | C5: ='Q2 Base'!$H$7 -> 2000 | D5: =$D$2 -> 0.98135504 | E5: =1-'Q2 Base'!$H$9 -> 0.99 | F5: =C5*D5*E5 -> 1943.083 | G5: =K4+F5 -> 3953.7852 | H5: =G5*'Q2 Base'!$H$17 -> 158.15141 | I5: =G5+H5 -> 4111.9366 | J5: =I5*'Q2 Base'!$H$10 -> 20.559683 | K5: =I5-J5 -> 4091.377 | O5: 2 | P5: =C5-F5 -> 56.917026 | Q5: ='Q2 Base'!$H$25 -> 25 | R5: ='Q2 Base'!$H$7*'Q2 Base'!$H$27 -> 20 | S5: =(P5-Q5-R5)*'Q2 Base'!$H$18 -> 0.11917026 | T5: =J5 -> 20.559683 | U5: =MAX('Q2 (ii)'!K5*('Q2 Base'!$H$6-'Q2 (iii)'!K5),0) -> 5.903162 | V5: ='Q2 (ii)'!J5*'Q2 (iii)'!J5 -> 0.0082255185 | W5: =P5-Q5-R5+S5+T5-U5-V5 -> 26.684492 | X5: ='Q2 (ii)'!E5 -> 0.9990962 | Y5: =X5*W5 -> 26.660374 | Z5: =$Z$2^O5 -> 0.87343873 | AA5: =Y5*Z5 -> 23.286203
B6: 3 | C6: ='Q2 Base'!$H$7 -> 2000 | D6: =$D$2 -> 0.98135504 | E6: =1-'Q2 Base'!$H$9 -> 0.99 | F6: =C6*D6*E6 -> 1943.083 | G6: =K5+F6 -> 6034.4599 | H6: =G6*'Q2 Base'!$H$17 -> 241.3784 | I6: =G6+H6 -> 6275.8383 | J6: =I6*'Q2 Base'!$H$10 -> 31.379192 | K6: =I6-J6 -> 6244.4591 | O6: 3 | P6: =C6-F6 -> 56.917026 | Q6: ='Q2 Base'!$H$25 -> 25 | R6: ='Q2 Base'!$H$7*'Q2 Base'!$H$27 -> 20 | S6: =(P6-Q6-R6)*'Q2 Base'!$H$18 -> 0.11917026 | T6: =J6 -> 31.379192 | U6: =MAX('Q2 (ii)'!K6*('Q2 Base'!$H$6-'Q2 (iii)'!K6),0) -> 5.0358839 | V6: ='Q2 (ii)'!J6*'Q2 (iii)'!J6 -> 0.014123814 | W6: =P6-Q6-R6+S6+T6-U6-V6 -> 38.36538 | X6: ='Q2 (ii)'!E6 -> 0.99815627 | Y6: =X6*W6 -> 38.294644 | Z6: =$Z$2^O6 -> 0.81629788 | AA6: =Y6*Z6 -> 31.259837
B7: 4 | C7: ='Q2 Base'!$H$7 -> 2000 | D7: =$D$2 -> 0.98135504 | E7: =1-'Q2 Base'!$H$9 -> 0.99 | F7: =C7*D7*E7 -> 1943.083 | G7: =K6+F7 -> 8187.5421 | H7: =G7*'Q2 Base'!$H$17 -> 327.50168 | I7: =G7+H7 -> 8515.0438 | J7: =I7*'Q2 Base'!$H$10 -> 42.575219 | K7: =I7-J7 -> 8472.4686 | O7: 4 | P7: =C7-F7 -> 56.917026 | Q7: ='Q2 Base'!$H$25 -> 25 | R7: ='Q2 Base'!$H$7*'Q2 Base'!$H$27 -> 20 | S7: =(P7-Q7-R7)*'Q2 Base'!$H$18 -> 0.11917026 | T7: =J7 -> 42.575219 | U7: =MAX('Q2 (ii)'!K7*('Q2 Base'!$H$6-'Q2 (iii)'!K7),0) -> 3.9960722 | V7: ='Q2 (ii)'!J7*'Q2 (iii)'!J7 -> 0.019163161 | W7: =P7-Q7-R7+S7+T7-U7-V7 -> 50.59618 | X7: ='Q2 (ii)'!E7 -> 0.99713342 | Y7: =X7*W7 -> 50.451141 | Z7: =$Z$2^O7 -> 0.76289521 | AA7: =Y7*Z7 -> 38.488934
B8: 5 | C8: ='Q2 Base'!$H$7 -> 2000 | D8: =$D$2 -> 0.98135504 | E8: =1-'Q2 Base'!$H$9 -> 0.99 | F8: =C8*D8*E8 -> 1943.083 | G8: =K7+F8 -> 10415.552 | H8: =G8*'Q2 Base'!$H$17 -> 416.62206 | I8: =G8+H8 -> 10832.174 | J8: =I8*'Q2 Base'!$H$10 -> 54.160868 | K8: =I8-J8 -> 10778.013 | O8: 5 | P8: =C8-F8 -> 56.917026 | Q8: ='Q2 Base'!$H$25 -> 25 | R8: ='Q2 Base'!$H$7*'Q2 Base'!$H$27 -> 20 | S8: =(P8-Q8-R8)*'Q2 Base'!$H$18 -> 0.11917026 | T8: =J8 -> 54.160868 | U8: =MAX('Q2 (ii)'!K8*('Q2 Base'!$H$6-'Q2 (iii)'!K8),0) -> 2.7578582 | V8: ='Q2 (ii)'!J8*'Q2 (iii)'!J8 -> 0.027087206 | W8: =P8-Q8-R8+S8+T8-U8-V8 -> 63.412119 | X8: ='Q2 (ii)'!E8 -> 0.99607474 | Y8: =X8*W8 -> 63.163209 | Z8: =$Z$2^O8 -> 0.71298618 | AA8: =Y8*Z8 -> 45.034495
B9: 6 | C9: ='Q2 Base'!$H$7 -> 2000 | D9: =$D$2 -> 0.98135504 | E9: =1-'Q2 Base'!$H$9 -> 0.99 | F9: =C9*D9*E9 -> 1943.083 | G9: =K8+F9 -> 12721.096 | H9: =G9*'Q2 Base'!$H$17 -> 508.84383 | I9: =G9+H9 -> 13229.94 | J9: =I9*'Q2 Base'!$H$10 -> 66.149698 | K9: =I9-J9 -> 13163.79 | O9: 6 | P9: =C9-F9 -> 56.917026 | Q9: ='Q2 Base'!$H$25 -> 25 | R9: ='Q2 Base'!$H$7*'Q2 Base'!$H$27 -> 20 | S9: =(P9-Q9-R9)*'Q2 Base'!$H$18 -> 0.11917026 | T9: =J9 -> 66.149698 | U9: =MAX('Q2 (ii)'!K9*('Q2 Base'!$H$6-'Q2 (iii)'!K9),0) -> 1.2784472 | V9: ='Q2 (ii)'!J9*'Q2 (iii)'!J9 -> 0.036392343 | W9: =P9-Q9-R9+S9+T9-U9-V9 -> 76.871054 | X9: ='Q2 (ii)'!E9 -> 0.99492659 | Y9: =X9*W9 -> 76.481055 | Z9: =$Z$2^O9 -> 0.66634222 | AA9: =Y9*Z9 -> 50.962557
B10: 7 | C10: ='Q2 Base'!$H$7 -> 2000 | D10: =$D$2 -> 0.98135504 | E10: =1-'Q2 Base'!$H$9 -> 0.99 | F10: =C10*D10*E10 -> 1943.083 | G10: =K9+F10 -> 15106.873 | H10: =G10*'Q2 Base'!$H$17 -> 604.27491 | I10: =G10+H10 -> 15711.148 | J10: =I10*'Q2 Base'!$H$10 -> 78.555739 | K10: =I10-J10 -> 15632.592 | O10: 7 | P10: =C10-F10 -> 56.917026 | Q10: ='Q2 Base'!$H$25 -> 25 | R10: ='Q2 Base'!$H$7*'Q2 Base'!$H$27 -> 20 | S10: =(P10-Q10-R10)*'Q2 Base'!$H$18 -> 0.11917026 | T10: =J10 -> 78.555739 | U10: =MAX('Q2 (ii)'!K10*('Q2 Base'!$H$6-'Q2 (iii)'!K10),0) -> 0 | V10: ='Q2 (ii)'!J10*'Q2 (iii)'!J10 -> 0.047147589 | W10: =P10-Q10-R10+S10+T10-U10-V10 -> 90.544787 | X10: ='Q2 (ii)'!E10 -> 0.99368729 | Y10: =X10*W10 -> 89.973204 | Z10: =$Z$2^O10 -> 0.62274974 | AA10: =Y10*Z10 -> 56.030789
B11: 8 | C11: ='Q2 Base'!$H$7 -> 2000 | D11: =$D$2 -> 0.98135504 | E11: =1-'Q2 Base'!$H$9 -> 0.99 | F11: =C11*D11*E11 -> 1943.083 | G11: =K10+F11 -> 17575.675 | H11: =G11*'Q2 Base'!$H$17 -> 703.027 | I11: =G11+H11 -> 18278.702 | J11: =I11*'Q2 Base'!$H$10 -> 91.39351 | K11: =I11-J11 -> 18187.308 | O11: 8 | P11: =C11-F11 -> 56.917026 | Q11: ='Q2 Base'!$H$25 -> 25 | R11: ='Q2 Base'!$H$7*'Q2 Base'!$H$27 -> 20 | S11: =(P11-Q11-R11)*'Q2 Base'!$H$18 -> 0.11917026 | T11: =J11 -> 91.39351 | U11: =MAX('Q2 (ii)'!K11*('Q2 Base'!$H$6-'Q2 (iii)'!K11),0) -> 0 | V11: ='Q2 (ii)'!J11*'Q2 (iii)'!J11 -> 0.063997859 | W11: =P11-Q11-R11+S11+T11-U11-V11 -> 103.36571 | X11: ='Q2 (ii)'!E11 -> 0.99234924 | Y11: =X11*W11 -> 102.57488 | Z11: =$Z$2^O11 -> 0.5820091 | AA11: =Y11*Z11 -> 59.699515
B12: 9 | C12: ='Q2 Base'!$H$7 -> 2000 | D12: =$D$2 -> 0.98135504 | E12: =1-'Q2 Base'!$H$9 -> 0.99 | F12: =C12*D12*E12 -> 1943.083 | G12: =K11+F12 -> 20130.391 | H12: =G12*'Q2 Base'!$H$17 -> 805.21566 | I12: =G12+H12 -> 20935.607 | J12: =I12*'Q2 Base'!$H$10 -> 104.67804 | K12: =I12-J12 -> 20830.929 | O12: 9 | P12: =C12-F12 -> 56.917026 | Q12: ='Q2 Base'!$H$25 -> 25 | R12: ='Q2 Base'!$H$7*'Q2 Base'!$H$27 -> 20 | S12: =(P12-Q12-R12)*'Q2 Base'!$H$18 -> 0.11917026 | T12: =J12 -> 104.67804 | U12: =MAX('Q2 (ii)'!K12*('Q2 Base'!$H$6-'Q2 (iii)'!K12),0) -> 0 | V12: ='Q2 (ii)'!J12*'Q2 (iii)'!J12 -> 0.094252652 | W12: =P12-Q12-R12+S12+T12-U12-V12 -> 116.61998 | X12: ='Q2 (ii)'!E12 -> 0.99085929 | Y12: =X12*W12 -> 115.55399 | Z12: =$Z$2^O12 -> 0.54393374 | AA12: =Y12*Z12 -> 62.853714
B13: 10 | C13: ='Q2 Base'!$H$7 -> 2000 | D13: =$D$2 -> 0.98135504 | E13: =1-'Q2 Base'!$H$9 -> 0.99 | F13: =C13*D13*E13 -> 1943.083 | G13: =K12+F13 -> 22774.012 | H13: =G13*'Q2 Base'!$H$17 -> 910.96048 | I13: =G13+H13 -> 23684.973 | J13: =I13*'Q2 Base'!$H$10 -> 118.42486 | K13: =I13-J13 -> 23566.548 | O13: 10 | P13: =C13-F13 -> 56.917026 | Q13: ='Q2 Base'!$H$25 -> 25 | R13: ='Q2 Base'!$H$7*'Q2 Base'!$H$27 -> 20 | S13: =(P13-Q13-R13)*'Q2 Base'!$H$18 -> 0.11917026 | T13: =J13 -> 118.42486 | U13: =MAX('Q2 (ii)'!K13*('Q2 Base'!$H$6-'Q2 (iii)'!K13),0) -> 0 | V13: ='Q2 (ii)'!J13*'Q2 (iii)'!J13 -> 0.11848411 | W13: =P13-Q13-R13+S13+T13-U13-V13 -> 130.34257 | X13: ='Q2 (ii)'!E13 -> 0.98912208 | Y13: =X13*W13 -> 128.92472 | Z13: =$Z$2^O13 -> 0.50834929 | AA13: =Y13*Z13 -> 65.538789
B14: 11 | C14: ='Q2 Base'!$H$7 -> 2000 | D14: =$D$2 -> 0.98135504 | E14: =1-'Q2 Base'!$H$9 -> 0.99 | F14: =C14*D14*E14 -> 1943.083 | G14: =K13+F14 -> 25509.631 | H14: =G14*'Q2 Base'!$H$17 -> 1020.3852 | I14: =G14+H14 -> 26530.016 | J14: =I14*'Q2 Base'!$H$10 -> 132.65008 | K14: =I14-J14 -> 26397.366 | O14: 11 | P14: =C14-F14 -> 56.917026 | Q14: ='Q2 Base'!$H$25 -> 25 | R14: ='Q2 Base'!$H$7*'Q2 Base'!$H$27 -> 20 | S14: =(P14-Q14-R14)*'Q2 Base'!$H$18 -> 0.11917026 | T14: =J14 -> 132.65008 | U14: =MAX('Q2 (ii)'!K14*('Q2 Base'!$H$6-'Q2 (iii)'!K14),0) -> 0 | V14: ='Q2 (ii)'!J14*'Q2 (iii)'!J14 -> 0.13271645 | W14: =P14-Q14-R14+S14+T14-U14-V14 -> 144.55356 | X14: ='Q2 (ii)'!E14 -> 0.98724265 | Y14: =X14*W14 -> 142.70944 | Z14: =$Z$2^O14 -> 0.4750928 | AA14: =Y14*Z14 -> 67.800226
B15: 12 | C15: ='Q2 Base'!$H$7 -> 2000 | D15: =$D$2 -> 0.98135504 | E15: =1-'Q2 Base'!$H$9 -> 0.99 | F15: =C15*D15*E15 -> 1943.083 | G15: =K14+F15 -> 28340.449 | H15: =G15*'Q2 Base'!$H$17 -> 1133.618 | I15: =G15+H15 -> 29474.067 | J15: =I15*'Q2 Base'!$H$10 -> 147.37033 | K15: =I15-J15 -> 29326.696 | O15: 12 | P15: =C15-F15 -> 56.917026 | Q15: ='Q2 Base'!$H$25 -> 25 | R15: ='Q2 Base'!$H$7*'Q2 Base'!$H$27 -> 20 | S15: =(P15-Q15-R15)*'Q2 Base'!$H$18 -> 0.11917026 | T15: =J15 -> 147.37033 | U15: =MAX('Q2 (ii)'!K15*('Q2 Base'!$H$6-'Q2 (iii)'!K15),0) -> 0 | V15: ='Q2 (ii)'!J15*'Q2 (iii)'!J15 -> 0.16219659 | W15: =P15-Q15-R15+S15+T15-U15-V15 -> 159.24433 | X15: ='Q2 (ii)'!E15 -> 0.98531945 | Y15: =X15*W15 -> 156.90654 | Z15: =$Z$2^O15 -> 0.44401196 | AA15: =Y15*Z15 -> 69.66838
B16: 13 | C16: ='Q2 Base'!$H$7 -> 2000 | D16: =$D$2 -> 0.98135504 | E16: =1-'Q2 Base'!$H$9 -> 0.99 | F16: =C16*D16*E16 -> 1943.083 | G16: =K15+F16 -> 31269.779 | H16: =G16*'Q2 Base'!$H$17 -> 1250.7912 | I16: =G16+H16 -> 32520.571 | J16: =I16*'Q2 Base'!$H$10 -> 162.60285 | K16: =I16-J16 -> 32357.968 | O16: 13 | P16: =C16-F16 -> 56.917026 | Q16: ='Q2 Base'!$H$25 -> 25 | R16: ='Q2 Base'!$H$7*'Q2 Base'!$H$27 -> 20 | S16: =(P16-Q16-R16)*'Q2 Base'!$H$18 -> 0.11917026 | T16: =J16 -> 162.60285 | U16: =MAX('Q2 (ii)'!K16*('Q2 Base'!$H$6-'Q2 (iii)'!K16),0) -> 0 | V16: ='Q2 (ii)'!J16*'Q2 (iii)'!J16 -> 0.19524059 | W16: =P16-Q16-R16+S16+T16-U16-V16 -> 174.44381 | X16: ='Q2 (ii)'!E16 -> 0.98324447 | Y16: =X16*W16 -> 171.52091 | Z16: =$Z$2^O16 -> 0.41496445 | AA16: =Y16*Z16 -> 71.17508
... B23: 20 | C23: ='Q2 Base'!$H$7 -> 2000 | D23: =$D$2 -> 0.98135504 | E23: =1-'Q2 Base'!$H$9 -> 0.99 | F23: =C23*D23*E23 -> 1943.083 | G23: =K22+F23 -> 54836.982 | H23: =G23*'Q2 Base'!$H$17 -> 2193.4793 | I23: =G23+H23 -> 57030.461 | J23: =I23*'Q2 Base'!$H$10 -> 285.15231 | K23: =I23-J23 -> 56745.309 | O23: 20 | P23: =C23-F23 -> 56.917026 | Q23: ='Q2 Base'!$H$25 -> 25 | R23: ='Q2 Base'!$H$7*'Q2 Base'!$H$27 -> 20 | S23: =(P23-Q23-R23)*'Q2 Base'!$H$18 -> 0.11917026 | T23: =J23 -> 285.15231 | U23: =MAX('Q2 (ii)'!K23*('Q2 Base'!$H$6-'Q2 (iii)'!K23),0) -> 0 | V23: ='Q2 (ii)'!J23*'Q2 (iii)'!J23 -> 0.57087568 | W23: =P23-Q23-R23+S23+T23-U23-V23 -> 296.61763 | X23: ='Q2 (ii)'!E23 -> 0.96331968 | Y23: =X23*W23 -> 285.7376 | Z23: =$Z$2^O23 -> 0.258419 | AA23: =Y23*Z23 -> 73.840025
Z24: EPV Profit: | AA24: =SUM(AA4:AA23) -> 200
Z26: Percentage profit | AA26: =AA24/C4 -> 0.1

Sheet Q2 Answers
B1: (i) | D1: (ii) (a) | G1: (ii) (b) | I1: (iii)
A2: Policy Year | B2: Unit fund at EOY | D2: (1)p(01)(x+t-1) | E2: (1)p(02)(x+t-1) | G2: ='Q2 (ii)'!E24 -> 0.95919241 | I2: Allocation rate
A3: 1 | B3: ='Q2 (i)'!K4 -> 1946.4588 | D3: ='Q2 (ii)'!J4 -> 0.00040008002 | E3: ='Q2 (ii)'!K4 -> 0.00050412705 | I3: ='Q2 (iii)'!D2 -> 0.98135504
A4: 2 | B4: ='Q2 (i)'!K5 -> 3960.6544 | D4: ='Q2 (ii)'!J5 -> 0.00040008002 | E4: ='Q2 (ii)'!K5 -> 0.00054114639
A5: 3 | B5: ='Q2 (i)'!K6 -> 6044.9439 | D5: ='Q2 (ii)'!J6 -> 0.00045010128 | E5: ='Q2 (ii)'!K6 -> 0.00057516538
A6: 4 | B6: ='Q2 (i)'!K7 -> 8201.7668 | D6: ='Q2 (ii)'!J7 -> 0.00045010128 | E6: ='Q2 (ii)'!K7 -> 0.00061218735
A7: 5 | B7: ='Q2 (i)'!K8 -> 10433.647 | D7: ='Q2 (ii)'!J8 -> 0.00050012504 | E7: ='Q2 (ii)'!K8 -> 0.0006532133
A8: 6 | B8: ='Q2 (i)'!K9 -> 12743.197 | D8: ='Q2 (ii)'!J9 -> 0.00055015131 | E8: ='Q2 (ii)'!K9 -> 0.00069624232
A9: 7 | B9: ='Q2 (i)'!K10 -> 15133.119 | D9: ='Q2 (ii)'!J10 -> 0.00060018007 | E9: ='Q2 (ii)'!K10 -> 0.00074727914
A10: 8 | B10: ='Q2 (i)'!K11 -> 17606.21 | D10: ='Q2 (ii)'!J11 -> 0.00070024511 | E10: ='Q2 (ii)'!K11 -> 0.00080232177
A11: 9 | B11: ='Q2 (i)'!K12 -> 20165.365 | D11: ='Q2 (ii)'!J12 -> 0.00090040524 | E11: ='Q2 (ii)'!K12 -> 0.00085436487
A12: 10 | B12: ='Q2 (i)'!K13 -> 22813.579 | D12: ='Q2 (ii)'!J13 -> 0.0010005003 | E12: ='Q2 (ii)'!K13 -> 0.00090140614
A13: 11 | B13: ='Q2 (i)'!K14 -> 25553.95 | D13: ='Q2 (ii)'!J14 -> 0.0010005003 | E13: ='Q2 (ii)'!K14 -> 0.00094945059
A14: 12 | B14: ='Q2 (i)'!K15 -> 28389.686 | D14: ='Q2 (ii)'!J15 -> 0.0011006054 | E14: ='Q2 (ii)'!K15 -> 0.0010075074
A15: 13 | B15: ='Q2 (i)'!K16 -> 31324.106 | D15: ='Q2 (ii)'!J16 -> 0.0012007206 | E15: ='Q2 (ii)'!K16 -> 0.0010835869
... A22: 20 | B22: ='Q2 (i)'!K23 -> 54932.253 | D22: ='Q2 (ii)'!J23 -> 0.0020020027 | E22: ='Q2 (ii)'!K23 -> 0.0022916238
