Workbook
Name Expenses: 'Q1 Working'!$E$9
Name FinalDecSA: 'Q1 Working'!$E$12
Name interest: 'Q1 Working'!$A$35
Name PremiumTA: 'Q1 Working'!$E$6
Name ProfitTestTerm: 'Q2 Working 2(IRR)'!$E$13
Name ProfitTestTerm: 'Q2 Working'!$E$13
Name StartDecSA: 'Q1 Working'!$E$11
Name StepSizeQ1: 'Q1 Working'!$B$9
Name SumAssdTA: 'Q1 Working'!$E$7
Name term: 'Q2 Working 2(IRR)'!$E$13
Name term: 'Q2 Working'!$E$13
Name TermOfDecSA: 'Q1 Working'!$E$10

Sheet Q1 Base
B2: Question 1: Assumptions
B3: Please do your calculations in the Q1 Working sheet
B4: Please put your answers in the Q1 Answers sheet, so that they are clearly identifiable
B7: time | C7: age | D7: mu(x+t)
B8: 0 | C8: 40 | D8: 0.00075148936
B9: 0.1 | C9: 40.1 | D9: 0.0007582612
B10: 0.2 | C10: 40.2 | D10: 0.00076503304
B11: 0.3 | C11: 40.3 | D11: 0.00077180488
B12: 0.4 | C12: 40.4 | D12: 0.00077857672
B13: 0.5 | C13: 40.5 | D13: 0.00078534856
B14: 0.6 | C14: 40.6 | D14: 0.0007921204
B15: 0.7 | C15: 40.7 | D15: 0.00079889224
B16: 0.8 | C16: 40.8 | D16: 0.00080566408
B17: 0.9 | C17: 40.9 | D17: 0.00081243592
B18: 1 | C18: 41 | D18: 0.00081920776
B19: 1.1 | C19: 41.1 | D19: 0.00082675518
... B208: 20 | C208: 60 | D208: 0.0034692053

Sheet Q1 Working
A2: Question 1: Working
A4: Parameters
D6: PremiumTA | E6: 180
A7: delta | B7: 0.07 | D7: SumAssdTA | E7: 100000
A8: x | B8: 40
A9: stepsize h | B9: 0.1 | D9: Expenses | E9: 0
D10: TermOfIncTA | E10: 20
D11: StartDecSA | E11: 200000
D12: FinalDecSA | E12: 0
A15: Results Part (a) | G15: Results Part (b) | M15: Results Part (c) | S15: Results Part (d) | AB15: Results Part (e)
G17: V(0) | H17: =I227 -> -251.29305 | I17: 1 | M17: V(0) | N17: =O227 -> 9.752199e-13 | O17: 2 | S17: V(0) | T17: =U227 -> -281.46002 | U17: 1 | AB17: EPV TA at time zero
A18: (20)p(x) | B18: =D227 -> 0.96358793 | M18: Net premium | N18: 156.45117 | O18: 1 | AA18: (i) | AB18: =SUM(AH27:AH227)*StepSizeQ1 -> 0.016616671 | AC18: 1
M19: (Net premium was found using Goal Seek)
AB20: EPV annuity at time zero
AA21: (ii) | AB21: =SUM(AI27:AI227)*StepSizeQ1 -> 10.654719 | AC21: 1
AA23: (iii) | AB23: V(0) | AC23: {=AB18*SumAssdTA-PremiumTA*AB21} -> -256.18225 | AD23: =AC23/H17-1 -> 0.019456173 | AE23: 1
G24: Use | H24: V'(t) = V(t)delta + P -mu*(100000-V(t))-Expenses | M24: Use | N24: V'(t) = V(t)delta + P -mu*(100000-V(t)) | S24: Use | T24: V'(t) = V(t)delta + P -mu*(SA-V(t)) + expenses
C25: 1 | D25: 2 | E25: 2 | I25: 2 | K25: 4 | W25: 2 | X25: 2 | AF25: 1 | AG25: 1 | AH25: 2 | AI25: 2
B26: age | C26: mu(x+t) | D26: (t)p(x) | E26: (d/dt)(tpx) | G26: time | H26: age | I26: V(t) | J26: mu(x+t) | K26: V'(t) | M26: time | N26: age | O26: V(t) | P26: mu(x+t) | Q26: V'(t) | S26: time | T26: age | U26: V(t) | V26: mu(x+t) | W26: Sum assured | X26: V'(t) | Y26: check | Z26: check | AB26: time | AC26: age | AD26: mu(x+t) | AE26: (t)p(x) | AF26: Weight | AG26: v^t | AH26: Weighted integrand term assurance | AI26: Weighted integrand annuity
A27: 0 | B27: =$B$8+A27 -> 40 | C27: =_xlfn.XLOOKUP($B27,'Q1 Base'!$C$8:$C$208,'Q1 Base'!$D$8:$D$208,,0,) -> 0.00075148936 | D27: 1 | E27: =-D27*C27 -> -0.00075148936 | G27: 20 | H27: =$B$8+G27 -> 60 | I27: 0 | J27: =_xlfn.XLOOKUP($H27,'Q1 Base'!$C$8:$C$208,'Q1 Base'!$D$8:$D$208,,0,) -> 0.0034692053 | K27: {=I27*$B$7+$E$6-J27*(SumAssdTA-I27)} -> -166.92053 | M27: 20 | N27: =$B$8+M27 -> 60 | O27: 0 | P27: =_xlfn.XLOOKUP($N27,'Q1 Base'!$C$8:$C$208,'Q1 Base'!$D$8:$D$208,,0,) -> 0.0034692053 | Q27: =O27*$B$7+$N$18-P27*(SumAssdTA-O27) -> -190.46936 | S27: 20 | T27: =$B$8+S27 -> 60 | U27: 0 | V27: =_xlfn.XLOOKUP($T27,'Q1 Base'!$C$8:$C$208,'Q1 Base'!$D$8:$D$208,,0,) -> 0.0034692053 | W27: =StartDecSA+(FinalDecSA-StartDecSA)*(S27/TermOfDecSA) -> 0 | X27: =U27*$B$7+$E$6-V27*(W27-U27)-Expenses -> 180 | Z27: =U27-I27 -> 0 | AB27: 0 | AC27: =$B$8+AB27 -> 40 | AD27: =C27 -> 0.00075148936 | AE27: =D27 -> 1 | AF27: =IF(OR(AB27=0,AB27=TermOfDecSA),0.5,1) -> 0.5 | AG27: =EXP(-AB27*$B$7) -> 1 | AH27: =AD27*AE27*AF27*AG27 -> 0.00037574468 | AI27: =AE27*AF27*AG27 -> 0.5
A28: =ROUND(A27+StepSizeQ1,2) -> 0.1 | B28: =$B$8+A28 -> 40.1 | C28: =_xlfn.XLOOKUP($B28,'Q1 Base'!$C$8:$C$208,'Q1 Base'!$D$8:$D$208,,0,) -> 0.0007582612 | D28: =D27+StepSizeQ1*E27 -> 0.99992485 | E28: =-D28*C28 -> -0.00075820421 | G28: =ROUND(G27-StepSizeQ1,2) -> 19.9 | H28: =$B$8+G28 -> 59.9 | I28: =I27-StepSizeQ1*K27 -> 16.692053 | J28: =_xlfn.XLOOKUP($H28,'Q1 Base'!$C$8:$C$208,'Q1 Base'!$D$8:$D$208,,0,) -> 0.0034462167 | K28: {=I28*$B$7+$E$6-J28*(SumAssdTA-I28)} -> -163.3957 | M28: =ROUND(M27-StepSizeQ1,2) -> 19.9 | N28: =$B$8+M28 -> 59.9 | O28: =O27-StepSizeQ1*Q27 -> 19.046936 | P28: =_xlfn.XLOOKUP($N28,'Q1 Base'!$C$8:$C$208,'Q1 Base'!$D$8:$D$208,,0,) -> 0.0034462167 | Q28: =O28*$B$7+$N$18-P28*(SumAssdTA-O28) -> -186.77157 | S28: =ROUND(S27-StepSizeQ1,2) -> 19.9 | T28: =$B$8+S28 -> 59.9 | U28: =U27-StepSizeQ1*X27 -> -18 | V28: =_xlfn.XLOOKUP($T28,'Q1 Base'!$C$8:$C$208,'Q1 Base'!$D$8:$D$208,,0,) -> 0.0034462167 | W28: =StartDecSA+(FinalDecSA-StartDecSA)*(S28/TermOfDecSA) -> 1000 | X28: =U28*$B$7+$E$6-V28*(W28-U28)-Expenses -> 175.23175 | Y28: =U28/I28-1 -> -2.0783575 | Z28: =U28-I28 -> -34.692053 | AB28: =ROUND(AB27+StepSizeQ1,2) -> 0.1 | AC28: =$B$8+AB28 -> 40.1 | AD28: =C28 -> 0.0007582612 | AE28: =D28 -> 0.99992485 | AF28: =IF(OR(AB28=0,AB28=TermOfDecSA),0.5,1) -> 1 | AG28: =EXP(-AB28*$B$7) -> 0.99302444 | AH28: =AD28*AE28*AF28*AG28 -> 0.00075291532 | AI28: =AE28*AF28*AG28 -> 0.99294982
A29: =ROUND(A28+StepSizeQ1,2) -> 0.2 | B29: =$B$8+A29 -> 40.2 | C29: =_xlfn.XLOOKUP($B29,'Q1 Base'!$C$8:$C$208,'Q1 Base'!$D$8:$D$208,,0,) -> 0.00076503304 | D29: =D28+StepSizeQ1*E28 -> 0.99984903 | E29: =-D29*C29 -> -0.00076491754 | G29: =ROUND(G28-StepSizeQ1,2) -> 19.8 | H29: =$B$8+G29 -> 59.8 | I29: =I28-StepSizeQ1*K28 -> 33.031623 | J29: =_xlfn.XLOOKUP($H29,'Q1 Base'!$C$8:$C$208,'Q1 Base'!$D$8:$D$208,,0,) -> 0.0034232281 | K29: {=I29*$B$7+$E$6-J29*(SumAssdTA-I29)} -> -159.89753 | M29: =ROUND(M28-StepSizeQ1,2) -> 19.8 | N29: =$B$8+M29 -> 59.8 | O29: =O28-StepSizeQ1*Q28 -> 37.724093 | P29: =_xlfn.XLOOKUP($N29,'Q1 Base'!$C$8:$C$208,'Q1 Base'!$D$8:$D$208,,0,) -> 0.0034232281 | Q29: =O29*$B$7+$N$18-P29*(SumAssdTA-O29) -> -183.10182 | S29: =ROUND(S28-StepSizeQ1,2) -> 19.8 | T29: =$B$8+S29 -> 59.8 | U29: =U28-StepSizeQ1*X28 -> -35.523175 | V29: =_xlfn.XLOOKUP($T29,'Q1 Base'!$C$8:$C$208,'Q1 Base'!$D$8:$D$208,,0,) -> 0.0034232281 | W29: =StartDecSA+(FinalDecSA-StartDecSA)*(S29/TermOfDecSA) -> 2000 | X29: =U29*$B$7+$E$6-V29*(W29-U29)-Expenses -> 170.54532 | Y29: =U29/I29-1 -> -2.0754293 | Z29: =U29-I29 -> -68.554798 | AB29: =ROUND(AB28+StepSizeQ1,2) -> 0.2 | AC29: =$B$8+AB29 -> 40.2 | AD29: =C29 -> 0.00076503304 | AE29: =D29 -> 0.99984903 | AF29: =IF(OR(AB29=0,AB29=TermOfDecSA),0.5,1) -> 1 | AG29: =EXP(-AB29*$B$7) -> 0.98609754 | AH29: =AD29*AE29*AF29*AG29 -> 0.00075428331 | AI29: =AE29*AF29*AG29 -> 0.98594867
A30: =ROUND(A29+StepSizeQ1,2) -> 0.3 | B30: =$B$8+A30 -> 40.3 | C30: =_xlfn.XLOOKUP($B30,'Q1 Base'!$C$8:$C$208,'Q1 Base'!$D$8:$D$208,,0,) -> 0.00077180488 | D30: =D29+StepSizeQ1*E29 -> 0.99977254 | E30: =-D30*C30 -> -0.00077162932 | G30: =ROUND(G29-StepSizeQ1,2) -> 19.7 | H30: =$B$8+G30 -> 59.7 | I30: =I29-StepSizeQ1*K29 -> 49.021376 | J30: =_xlfn.XLOOKUP($H30,'Q1 Base'!$C$8:$C$208,'Q1 Base'!$D$8:$D$208,,0,) -> 0.0034002396 | K30: {=I30*$B$7+$E$6-J30*(SumAssdTA-I30)} -> -156.42578 | M30: =ROUND(M29-StepSizeQ1,2) -> 19.7 | N30: =$B$8+M30 -> 59.7 | O30: =O29-StepSizeQ1*Q29 -> 56.034275 | P30: =_xlfn.XLOOKUP($N30,'Q1 Base'!$C$8:$C$208,'Q1 Base'!$D$8:$D$208,,0,) -> 0.0034002396 | Q30: =O30*$B$7+$N$18-P30*(SumAssdTA-O30) -> -179.45986 | S30: =ROUND(S29-StepSizeQ1,2) -> 19.7 | T30: =$B$8+S30 -> 59.7 | U30: =U29-StepSizeQ1*X29 -> -52.577707 | V30: =_xlfn.XLOOKUP($T30,'Q1 Base'!$C$8:$C$208,'Q1 Base'!$D$8:$D$208,,0,) -> 0.0034002396 | W30: =StartDecSA+(FinalDecSA-StartDecSA)*(S30/TermOfDecSA) -> 3000 | X30: =U30*$B$7+$E$6-V30*(W30-U30)-Expenses -> 165.94006 | Y30: =U30/I30-1 -> -2.0725465 | Z30: =U30-I30 -> -101.59908 | AB30: =ROUND(AB29+StepSizeQ1,2) -> 0.3 | AC30: =$B$8+AB30 -> 40.3 | AD30: =C30 -> 0.00077180488 | AE30: =D30 -> 0.99977254 | AF30: =IF(OR(AB30=0,AB30=TermOfDecSA),0.5,1) -> 1 | AG30: =EXP(-AB30*$B$7) -> 0.97921896 | AH30: =AD30*AE30*AF30*AG30 -> 0.00075559407 | AI30: =AE30*AF30*AG30 -> 0.97899623
A31: =ROUND(A30+StepSizeQ1,2) -> 0.4 | B31: =$B$8+A31 -> 40.4 | C31: =_xlfn.XLOOKUP($B31,'Q1 Base'!$C$8:$C$208,'Q1 Base'!$D$8:$D$208,,0,) -> 0.00077857672 | D31: =D30+StepSizeQ1*E30 -> 0.99969538 | E31: =-D31*C31 -> -0.00077833954 | G31: =ROUND(G30-StepSizeQ1,2) -> 19.6 | H31: =$B$8+G31 -> 59.6 | I31: =I30-StepSizeQ1*K30 -> 64.663954 | J31: =_xlfn.XLOOKUP($H31,'Q1 Base'!$C$8:$C$208,'Q1 Base'!$D$8:$D$208,,0,) -> 0.003377251 | K31: {=I31*$B$7+$E$6-J31*(SumAssdTA-I31)} -> -152.98024 | M31: =ROUND(M30-StepSizeQ1,2) -> 19.6 | N31: =$B$8+M31 -> 59.6 | O31: =O30-StepSizeQ1*Q30 -> 73.98026 | P31: =_xlfn.XLOOKUP($N31,'Q1 Base'!$C$8:$C$208,'Q1 Base'!$D$8:$D$208,,0,) -> 0.003377251 | Q31: =O31*$B$7+$N$18-P31*(SumAssdTA-O31) -> -175.84546 | S31: =ROUND(S30-StepSizeQ1,2) -> 19.6 | T31: =$B$8+S31 -> 59.6 | U31: =U30-StepSizeQ1*X30 -> -69.171713 | V31: =_xlfn.XLOOKUP($T31,'Q1 Base'!$C$8:$C$208,'Q1 Base'!$D$8:$D$208,,0,) -> 0.003377251 | W31: =StartDecSA+(FinalDecSA-StartDecSA)*(S31/TermOfDecSA) -> 4000 | X31: =U31*$B$7+$E$6-V31*(W31-U31)-Expenses -> 161.41537 | Y31: =U31/I31-1 -> -2.0697106 | Z31: =U31-I31 -> -133.83567 | AB31: =ROUND(AB30+StepSizeQ1,2) -> 0.4 | AC31: =$B$8+AB31 -> 40.4 | AD31: =C31 -> 0.00077857672 | AE31: =D31 -> 0.99969538 | AF31: =IF(OR(AB31=0,AB31=TermOfDecSA),0.5,1) -> 1 | AG31: =EXP(-AB31*$B$7) -> 0.97238837 | AH31: =AD31*AE31*AF31*AG31 -> 0.00075684832 | AI31: =AE31*AF31*AG31 -> 0.97209215
A32: =ROUND(A31+StepSizeQ1,2) -> 0.5 | B32: =$B$8+A32 -> 40.5 | C32: =_xlfn.XLOOKUP($B32,'Q1 Base'!$C$8:$C$208,'Q1 Base'!$D$8:$D$208,,0,) -> 0.00078534856 | D32: =D31+StepSizeQ1*E31 -> 0.99961754 | E32: =-D32*C32 -> -0.00078504819 | G32: =ROUND(G31-StepSizeQ1,2) -> 19.5 | H32: =$B$8+G32 -> 59.5 | I32: =I31-StepSizeQ1*K31 -> 79.961977 | J32: =_xlfn.XLOOKUP($H32,'Q1 Base'!$C$8:$C$208,'Q1 Base'!$D$8:$D$208,,0,) -> 0.0033542624 | K32: {=I32*$B$7+$E$6-J32*(SumAssdTA-I32)} -> -149.56069 | M32: =ROUND(M31-StepSizeQ1,2) -> 19.5 | N32: =$B$8+M32 -> 59.5 | O32: =O31-StepSizeQ1*Q31 -> 91.564806 | P32: =_xlfn.XLOOKUP($N32,'Q1 Base'!$C$8:$C$208,'Q1 Base'!$D$8:$D$208,,0,) -> 0.0033542624 | Q32: =O32*$B$7+$N$18-P32*(SumAssdTA-O32) -> -172.2584 | S32: =ROUND(S31-StepSizeQ1,2) -> 19.5 | T32: =$B$8+S32 -> 59.5 | U32: =U31-StepSizeQ1*X31 -> -85.31325 | V32: =_xlfn.XLOOKUP($T32,'Q1 Base'!$C$8:$C$208,'Q1 Base'!$D$8:$D$208,,0,) -> 0.0033542624 | W32: =StartDecSA+(FinalDecSA-StartDecSA)*(S32/TermOfDecSA) -> 5000 | X32: =U32*$B$7+$E$6-V32*(W32-U32)-Expenses -> 156.9706 | Y32: =U32/I32-1 -> -2.0669227 | Z32: =U32-I32 -> -165.27523 | AB32: =ROUND(AB31+StepSizeQ1,2) -> 0.5 | AC32: =$B$8+AB32 -> 40.5 | AD32: =C32 -> 0.00078534856 | AE32: =D32 -> 0.99961754 | AF32: =IF(OR(AB32=0,AB32=TermOfDecSA),0.5,1) -> 1 | AG32: =EXP(-AB32*$B$7) -> 0.96560542 | AH32: =AD32*AE32*AF32*AG32 -> 0.00075804679 | AI32: =AE32*AF32*AG32 -> 0.96523611
A33: =ROUND(A32+StepSizeQ1,2) -> 0.6 | B33: =$B$8+A33 -> 40.6 | C33: =_xlfn.XLOOKUP($B33,'Q1 Base'!$C$8:$C$208,'Q1 Base'!$D$8:$D$208,,0,) -> 0.0007921204 | D33: =D32+StepSizeQ1*E32 -> 0.99953904 | E33: =-D33*C33 -> -0.00079175526 | G33: =ROUND(G32-StepSizeQ1,2) -> 19.4 | H33: =$B$8+G33 -> 59.4 | I33: =I32-StepSizeQ1*K32 -> 94.918047 | J33: =_xlfn.XLOOKUP($H33,'Q1 Base'!$C$8:$C$208,'Q1 Base'!$D$8:$D$208,,0,) -> 0.0033312739 | K33: {=I33*$B$7+$E$6-J33*(SumAssdTA-I33)} -> -146.16693 | M33: =ROUND(M32-StepSizeQ1,2) -> 19.4 | N33: =$B$8+M33 -> 59.4 | O33: =O32-StepSizeQ1*Q32 -> 108.79065 | P33: =_xlfn.XLOOKUP($N33,'Q1 Base'!$C$8:$C$208,'Q1 Base'!$D$8:$D$208,,0,) -> 0.0033312739 | Q33: =O33*$B$7+$N$18-P33*(SumAssdTA-O33) -> -168.69846 | S33: =ROUND(S32-StepSizeQ1,2) -> 19.4 | T33: =$B$8+S33 -> 59.4 | U33: =U32-StepSizeQ1*X32 -> -101.01031 | V33: =_xlfn.XLOOKUP($T33,'Q1 Base'!$C$8:$C$208,'Q1 Base'!$D$8:$D$208,,0,) -> 0.0033312739 | W33: =StartDecSA+(FinalDecSA-StartDecSA)*(S33/TermOfDecSA) -> 6000 | X33: =U33*$B$7+$E$6-V33*(W33-U33)-Expenses -> 152.60514 | Y33: =U33/I33-1 -> -2.0641845 | Z33: =U33-I33 -> -195.92836 | AB33: =ROUND(AB32+StepSizeQ1,2) -> 0.6 | AC33: =$B$8+AB33 -> 40.6 | AD33: =C33 -> 0.0007921204 | AE33: =D33 -> 0.99953904 | AF33: =IF(OR(AB33=0,AB33=TermOfDecSA),0.5,1) -> 1 | AG33: =EXP(-AB33*$B$7) -> 0.95886978 | AH33: =AD33*AE33*AF33*AG33 -> 0.00075919019 | AI33: =AE33*AF33*AG33 -> 0.95842778
A34: =ROUND(A33+StepSizeQ1,2) -> 0.7 | B34: =$B$8+A34 -> 40.7 | C34: =_xlfn.XLOOKUP($B34,'Q1 Base'!$C$8:$C$208,'Q1 Base'!$D$8:$D$208,,0,) -> 0.00079889224 | D34: =D33+StepSizeQ1*E33 -> 0.99945986 | E34: =-D34*C34 -> -0.00079846073 | G34: =ROUND(G33-StepSizeQ1,2) -> 19.3 | H34: =$B$8+G34 -> 59.3 | I34: =I33-StepSizeQ1*K33 -> 109.53474 | J34: =_xlfn.XLOOKUP($H34,'Q1 Base'!$C$8:$C$208,'Q1 Base'!$D$8:$D$208,,0,) -> 0.0033082853 | K34: {=I34*$B$7+$E$6-J34*(SumAssdTA-I34)} -> -142.79873 | M34: =ROUND(M33-StepSizeQ1,2) -> 19.3 | N34: =$B$8+M34 -> 59.3 | O34: =O33-StepSizeQ1*Q33 -> 125.66049 | P34: =_xlfn.XLOOKUP($N34,'Q1 Base'!$C$8:$C$208,'Q1 Base'!$D$8:$D$208,,0,) -> 0.0033082853 | Q34: =O34*$B$7+$N$18-P34*(SumAssdTA-O34) -> -165.1654 | S34: =ROUND(S33-StepSizeQ1,2) -> 19.3 | T34: =$B$8+S34 -> 59.3 | U34: =U33-StepSizeQ1*X33 -> -116.27082 | V34: =_xlfn.XLOOKUP($T34,'Q1 Base'!$C$8:$C$208,'Q1 Base'!$D$8:$D$208,,0,) -> 0.0033082853 | W34: =StartDecSA+(FinalDecSA-StartDecSA)*(S34/TermOfDecSA) -> 7000 | X34: =U34*$B$7+$E$6-V34*(W34-U34)-Expenses -> 148.31839 | Y34: =U34/I34-1 -> -2.0614972 | Z34: =U34-I34 -> -225.80556 | AB34: =ROUND(AB33+StepSizeQ1,2) -> 0.7 | AC34: =$B$8+AB34 -> 40.7 | AD34: =C34 -> 0.00079889224 | AE34: =D34 -> 0.99945986 | AF34: =IF(OR(AB34=0,AB34=TermOfDecSA),0.5,1) -> 1 | AG34: =EXP(-AB34*$B$7) -> 0.95218113 | AH34: =AD34*AE34*AF34*AG34 -> 0.00076027924 | AI34: =AE34*AF34*AG34 -> 0.95166682
A35: =ROUND(A34+StepSizeQ1,2) -> 0.8 | B35: =$B$8+A35 -> 40.8 | C35: =_xlfn.XLOOKUP($B35,'Q1 Base'!$C$8:$C$208,'Q1 Base'!$D$8:$D$208,,0,) -> 0.00080566408 | D35: =D34+StepSizeQ1*E34 -> 0.99938002 | E35: =-D35*C35 -> -0.00080516458 | G35: =ROUND(G34-StepSizeQ1,2) -> 19.2 | H35: =$B$8+G35 -> 59.2 | I35: =I34-StepSizeQ1*K34 -> 123.81461 | J35: =_xlfn.XLOOKUP($H35,'Q1 Base'!$C$8:$C$208,'Q1 Base'!$D$8:$D$208,,0,) -> 0.0032852967 | K35: {=I35*$B$7+$E$6-J35*(SumAssdTA-I35)} -> -139.45588 | M35: =ROUND(M34-StepSizeQ1,2) -> 19.2 | N35: =$B$8+M35 -> 59.2 | O35: =O34-StepSizeQ1*Q34 -> 142.17703 | P35: =_xlfn.XLOOKUP($N35,'Q1 Base'!$C$8:$C$208,'Q1 Base'!$D$8:$D$208,,0,) -> 0.0032852967 | Q35: =O35*$B$7+$N$18-P35*(SumAssdTA-O35) -> -161.65901 | S35: =ROUND(S34-StepSizeQ1,2) -> 19.2 | T35: =$B$8+S35 -> 59.2 | U35: =U34-StepSizeQ1*X34 -> -131.10266 | V35: =_xlfn.XLOOKUP($T35,'Q1 Base'!$C$8:$C$208,'Q1 Base'!$D$8:$D$208,,0,) -> 0.0032852967 | W35: =StartDecSA+(FinalDecSA-StartDecSA)*(S35/TermOfDecSA) -> 8000 | X35: =U35*$B$7+$E$6-V35*(W35-U35)-Expenses -> 144.10973 | Y35: =U35/I35-1 -> -2.0588626 | Z35: =U35-I35 -> -254.91727 | AB35: =ROUND(AB34+StepSizeQ1,2) -> 0.8 | AC35: =$B$8+AB35 -> 40.8 | AD35: =C35 -> 0.00080566408 | AE35: =D35 -> 0.99938002 | AF35: =IF(OR(AB35=0,AB35=TermOfDecSA),0.5,1) -> 1 | AG35: =EXP(-AB35*$B$7) -> 0.94553914 | AH35: =AD35*AE35*AF35*AG35 -> 0.00076131462 | AI35: =AE35*AF35*AG35 -> 0.94495292
A36: =ROUND(A35+StepSizeQ1,2) -> 0.9 | B36: =$B$8+A36 -> 40.9 | C36: =_xlfn.XLOOKUP($B36,'Q1 Base'!$C$8:$C$208,'Q1 Base'!$D$8:$D$208,,0,) -> 0.00081243592 | D36: =D35+StepSizeQ1*E35 -> 0.9992995 | E36: =-D36*C36 -> -0.00081186681 | G36: =ROUND(G35-StepSizeQ1,2) -> 19.1 | H36: =$B$8+G36 -> 59.1 | I36: =I35-StepSizeQ1*K35 -> 137.7602 | J36: =_xlfn.XLOOKUP($H36,'Q1 Base'!$C$8:$C$208,'Q1 Base'!$D$8:$D$208,,0,) -> 0.0032623082 | K36: {=I36*$B$7+$E$6-J36*(SumAssdTA-I36)} -> -136.13819 | M36: =ROUND(M35-StepSizeQ1,2) -> 19.1 | N36: =$B$8+M36 -> 59.1 | O36: =O35-StepSizeQ1*Q35 -> 158.34293 | P36: =_xlfn.XLOOKUP($N36,'Q1 Base'!$C$8:$C$208,'Q1 Base'!$D$8:$D$208,,0,) -> 0.0032623082 | Q36: =O36*$B$7+$N$18-P36*(SumAssdTA-O36) -> -158.17907 | S36: =ROUND(S35-StepSizeQ1,2) -> 19.1 | T36: =$B$8+S36 -> 59.1 | U36: =U35-StepSizeQ1*X35 -> -145.51364 | V36: =_xlfn.XLOOKUP($T36,'Q1 Base'!$C$8:$C$208,'Q1 Base'!$D$8:$D$208,,0,) -> 0.0032623082 | W36: =StartDecSA+(FinalDecSA-StartDecSA)*(S36/TermOfDecSA) -> 9000 | X36: =U36*$B$7+$E$6-V36*(W36-U36)-Expenses -> 139.97856 | Y36: =U36/I36-1 -> -2.0562821 | Z36: =U36-I36 -> -283.27384 | AB36: =ROUND(AB35+StepSizeQ1,2) -> 0.9 | AC36: =$B$8+AB36 -> 40.9 | AD36: =C36 -> 0.00081243592 | AE36: =D36 -> 0.9992995 | AF36: =IF(OR(AB36=0,AB36=TermOfDecSA),0.5,1) -> 1 | AG36: =EXP(-AB36*$B$7) -> 0.93894347 | AH36: =AD36*AE36*AF36*AG36 -> 0.00076229704 | AI36: =AE36*AF36*AG36 -> 0.93828574
A37: =ROUND(A36+StepSizeQ1,2) -> 1 | B37: =$B$8+A37 -> 41 | C37: =_xlfn.XLOOKUP($B37,'Q1 Base'!$C$8:$C$208,'Q1 Base'!$D$8:$D$208,,0,) -> 0.00081920776 | D37: =D36+StepSizeQ1*E36 -> 0.99921831 | E37: =-D37*C37 -> -0.00081856739 | G37: =ROUND(G36-StepSizeQ1,2) -> 19 | H37: =$B$8+G37 -> 59 | I37: =I36-StepSizeQ1*K36 -> 151.37402 | J37: =_xlfn.XLOOKUP($H37,'Q1 Base'!$C$8:$C$208,'Q1 Base'!$D$8:$D$208,,0,) -> 0.0032393196 | K37: {=I37*$B$7+$E$6-J37*(SumAssdTA-I37)} -> -132.84543 | M37: =ROUND(M36-StepSizeQ1,2) -> 19 | N37: =$B$8+M37 -> 59 | O37: =O36-StepSizeQ1*Q36 -> 174.16084 | P37: =_xlfn.XLOOKUP($N37,'Q1 Base'!$C$8:$C$208,'Q1 Base'!$D$8:$D$208,,0,) -> 0.0032393196 | Q37: =O37*$B$7+$N$18-P37*(SumAssdTA-O37) -> -154.72536 | S37: =ROUND(S36-StepSizeQ1,2) -> 19 | T37: =$B$8+S37 -> 59 | U37: =U36-StepSizeQ1*X36 -> -159.51149 | V37: =_xlfn.XLOOKUP($T37,'Q1 Base'!$C$8:$C$208,'Q1 Base'!$D$8:$D$208,,0,) -> 0.0032393196 | W37: =StartDecSA+(FinalDecSA-StartDecSA)*(S37/TermOfDecSA) -> 10000 | X37: =U37*$B$7+$E$6-V37*(W37-U37)-Expenses -> 135.92429 | Y37: =U37/I37-1 -> -2.0537574 | Z37: =U37-I37 -> -310.88551 | AB37: =ROUND(AB36+StepSizeQ1,2) -> 1 | AC37: =$B$8+AB37 -> 41 | AD37: =C37 -> 0.00081920776 | AE37: =D37 -> 0.99921831 | AF37: =IF(OR(AB37=0,AB37=TermOfDecSA),0.5,1) -> 1 | AG37: =EXP(-AB37*$B$7) -> 0.93239382 | AH37: =AD37*AE37*AF37*AG37 -> 0.00076322718 | AI37: =AE37*AF37*AG37 -> 0.93166498
A38: =ROUND(A37+StepSizeQ1,2) -> 1.1 | B38: =$B$8+A38 -> 41.1 | C38: =_xlfn.XLOOKUP($B38,'Q1 Base'!$C$8:$C$208,'Q1 Base'!$D$8:$D$208,,0,) -> 0.00082675518 | D38: =D37+StepSizeQ1*E37 -> 0.99913646 | E38: =-D38*C38 -> -0.00082604124 | G38: =ROUND(G37-StepSizeQ1,2) -> 18.9 | H38: =$B$8+G38 -> 58.9 | I38: =I37-StepSizeQ1*K37 -> 164.65856 | J38: =_xlfn.XLOOKUP($H38,'Q1 Base'!$C$8:$C$208,'Q1 Base'!$D$8:$D$208,,0,) -> 0.0032183192 | K38: {=I38*$B$7+$E$6-J38*(SumAssdTA-I38)} -> -129.77589 | M38: =ROUND(M37-StepSizeQ1,2) -> 18.9 | N38: =$B$8+M38 -> 58.9 | O38: =O37-StepSizeQ1*Q37 -> 189.63338 | P38: =_xlfn.XLOOKUP($N38,'Q1 Base'!$C$8:$C$208,'Q1 Base'!$D$8:$D$208,,0,) -> 0.0032183192 | Q38: =O38*$B$7+$N$18-P38*(SumAssdTA-O38) -> -151.49611 | S38: =ROUND(S37-StepSizeQ1,2) -> 18.9 | T38: =$B$8+S38 -> 58.9 | U38: =U37-StepSizeQ1*X37 -> -173.10392 | V38: =_xlfn.XLOOKUP($T38,'Q1 Base'!$C$8:$C$208,'Q1 Base'!$D$8:$D$208,,0,) -> 0.0032183192 | W38: =StartDecSA+(FinalDecSA-StartDecSA)*(S38/TermOfDecSA) -> 11000 | X38: =U38*$B$7+$E$6-V38*(W38-U38)-Expenses -> 131.92411 | Y38: =U38/I38-1 -> -2.0512901 | Z38: =U38-I38 -> -337.76248 | AB38: =ROUND(AB37+StepSizeQ1,2) -> 1.1 | AC38: =$B$8+AB38 -> 41.1 | AD38: =C38 -> 0.00082675518 | AE38: =D38 -> 0.99913646 | AF38: =IF(OR(AB38=0,AB38=TermOfDecSA),0.5,1) -> 1 | AG38: =EXP(-AB38*$B$7) -> 0.92588985 | AH38: =AD38*AE38*AF38*AG38 -> 0.0007648232 | AI38: =AE38*AF38*AG38 -> 0.92509031
A39: =ROUND(A38+StepSizeQ1,2) -> 1.2 | B39: =$B$8+A39 -> 41.2 | C39: =_xlfn.XLOOKUP($B39,'Q1 Base'!$C$8:$C$208,'Q1 Base'!$D$8:$D$208,,0,) -> 0.0008343026 | D39: =D38+StepSizeQ1*E38 -> 0.99905385 | E39: =-D39*C39 -> -0.00083351323 | G39: =ROUND(G38-StepSizeQ1,2) -> 18.8 | H39: =$B$8+G39 -> 58.8 | I39: =I38-StepSizeQ1*K38 -> 177.63615 | J39: =_xlfn.XLOOKUP($H39,'Q1 Base'!$C$8:$C$208,'Q1 Base'!$D$8:$D$208,,0,) -> 0.0031973188 | K39: {=I39*$B$7+$E$6-J39*(SumAssdTA-I39)} -> -126.72939 | M39: =ROUND(M38-StepSizeQ1,2) -> 18.8 | N39: =$B$8+M39 -> 58.8 | O39: =O38-StepSizeQ1*Q38 -> 204.78299 | P39: =_xlfn.XLOOKUP($N39,'Q1 Base'!$C$8:$C$208,'Q1 Base'!$D$8:$D$208,,0,) -> 0.0031973188 | Q39: =O39*$B$7+$N$18-P39*(SumAssdTA-O39) -> -148.29114 | S39: =ROUND(S38-StepSizeQ1,2) -> 18.8 | T39: =$B$8+S39 -> 58.8 | U39: =U38-StepSizeQ1*X38 -> -186.29633 | V39: =_xlfn.XLOOKUP($T39,'Q1 Base'!$C$8:$C$208,'Q1 Base'!$D$8:$D$208,,0,) -> 0.0031973188 | W39: =StartDecSA+(FinalDecSA-StartDecSA)*(S39/TermOfDecSA) -> 12000 | X39: =U39*$B$7+$E$6-V39*(W39-U39)-Expenses -> 127.99578 | Y39: =U39/I39-1 -> -2.0487524 | Z39: =U39-I39 -> -363.93248 | AB39: =ROUND(AB38+StepSizeQ1,2) -> 1.2 | AC39: =$B$8+AB39 -> 41.2 | AD39: =C39 -> 0.0008343026 | AE39: =D39 -> 0.99905385 | AF39: =IF(OR(AB39=0,AB39=TermOfDecSA),0.5,1) -> 1 | AG39: =EXP(-AB39*$B$7) -> 0.91943126 | AH39: =AD39*AE39*AF39*AG39 -> 0.00076635811 | AI39: =AE39*AF39*AG39 -> 0.91856134
... A227: =ROUND(A226+StepSizeQ1,2) -> 20 | B227: =$B$8+A227 -> 60 | C227: =_xlfn.XLOOKUP($B227,'Q1 Base'!$C$8:$C$208,'Q1 Base'!$D$8:$D$208,,0,) -> 0.0034692053 | D227: =D226+StepSizeQ1*E226 -> 0.96358793 | E227: =-D227*C227 -> -0.0033428844 | G227: =ROUND(G226-StepSizeQ1,2) -> 0 | H227: =$B$8+G227 -> 40 | I227: =I226-StepSizeQ1*K226 -> -251.29305 | J227: =_xlfn.XLOOKUP($H227,'Q1 Base'!$C$8:$C$208,'Q1 Base'!$D$8:$D$208,,0,) -> 0.00075148936 | K227: {=I227*$B$7+$E$6-J227*(SumAssdTA-I227)} -> 87.071707 | M227: =ROUND(M226-StepSizeQ1,2) -> 0 | N227: =$B$8+M227 -> 40 | O227: =O226-StepSizeQ1*Q226 -> 9.752199e-13 | P227: =_xlfn.XLOOKUP($N227,'Q1 Base'!$C$8:$C$208,'Q1 Base'!$D$8:$D$208,,0,) -> 0.00075148936 | Q227: =O227*$B$7+$N$18-P227*(SumAssdTA-O227) -> 81.302237 | S227: =ROUND(S226-StepSizeQ1,2) -> 0 | T227: =$B$8+S227 -> 40 | U227: =U226-StepSizeQ1*X226 -> -281.46002 | V227: =_xlfn.XLOOKUP($T227,'Q1 Base'!$C$8:$C$208,'Q1 Base'!$D$8:$D$208,,0,) -> 0.00075148936 | W227: =StartDecSA+(FinalDecSA-StartDecSA)*(S227/TermOfDecSA) -> 200000 | X227: =U227*$B$7+$E$6-V227*(W227-U227)-Expenses -> 9.7884127 | Y227: =U227/I227-1 -> 0.12004698 | Z227: =U227-I227 -> -30.166973 | AB227: =ROUND(AB226+StepSizeQ1,2) -> 20 | AC227: =$B$8+AB227 -> 60 | AD227: =C227 -> 0.0034692053 | AE227: =D227 -> 0.96358793 | AF227: =IF(OR(AB227=0,AB227=TermOfDecSA),0.5,1) -> 0.5 | AG227: =EXP(-AB227*$B$7) -> 0.24659696 | AH227: =AD227*AE227*AF227*AG227 -> 0.00041217257 | AI227: =AE227*AF227*AG227 -> 0.11880893

Sheet Q1 Answers
B2: Question 1: Answers
B5: Summary results
B7: Question | C7: Result | D7: Value | E7: Marks
B8: (a) Probablities | C8: (20)p(x) | D8: ='Q1 Working'!B18 -> 0.96358793 | E8: 5
B9: (b) Gross premium, flat SA | C9: V(0) | D9: ='Q1 Working'!H17 -> -251.29305 | E9: 7
B10: (c) Net premium | C10: Net premium | D10: ='Q1 Working'!N18 -> 156.45117 | E10: 3
B11: (d) Gross premium, decreasing SA | C11: V(0) | D11: ='Q1 Working'!T17 -> -281.46002 | E11: 5
B12: (e) Trapezium rule method
B13: (i) EPV term assurance £1 | C13: EPV TA | D13: ='Q1 Working'!AB18 -> 0.016616671
B14: (ii) EPV annuity £1 | C14: EPV annuity | D14: ='Q1 Working'!AB21 -> 10.654719
B15: (iii) policy value | C15: V(0) | D15: ='Q1 Working'!AC23 -> -256.18225
E16: 9
E17: =SUM(E8:E16) -> 29

Sheet Q2 Base
B2: Question 2: Assumptions
B3: Please do your calculations in the Q2 Working sheet
B4: Please put your answers in the Q2 Answers sheet, so that they are clearly identifiable
G5: Time at year | H5: Time at year
G6: start (t-1) | H6: end (t) | I6: Start of yr | J6: End of yr
C7: x+t | D7: q(x+t) | I7: Reserve | J7: Reserve
C8: 70 | D8: 0.0078176305 | G8: 0 | H8: =G8+1 -> 1 | I8: 0 | J8: 144000
C9: 71 | D9: 0.0087215052 | G9: =G8+1 -> 1 | H9: =G9+1 -> 2 | I9: 144000 | J9: 141000
C10: 72 | D10: 0.0097672252 | G10: =G9+1 -> 2 | H10: =G10+1 -> 3 | I10: 141000 | J10: 137000
C11: 73 | D11: 0.010982639 | G11: =G10+1 -> 3 | H11: =G11+1 -> 4 | I11: 137000 | J11: 134000
C12: 74 | D12: 0.012401652 | G12: =G11+1 -> 4 | H12: =G12+1 -> 5 | I12: 134000 | J12: 130000
C13: 75 | D13: 0.014062731 | G13: =G12+1 -> 5 | H13: =G13+1 -> 6 | I13: 130000 | J13: 126000
C14: 76 | D14: 0.016005163 | G14: =G13+1 -> 6 | H14: =G14+1 -> 7 | I14: 126000 | J14: 123000
C15: 77 | D15: 0.018277699 | G15: =G14+1 -> 7 | H15: =G15+1 -> 8 | I15: 123000 | J15: 119000
C16: 78 | D16: 0.020931815 | G16: =G15+1 -> 8 | H16: =G16+1 -> 9 | I16: 119000 | J16: 115000
C17: 79 | D17: 0.024032269 | G17: =G16+1 -> 9 | H17: =G17+1 -> 10 | I17: 115000 | J17: 112000
C18: 80 | D18: 0.027651675 | G18: =G17+1 -> 10 | H18: =G18+1 -> 11 | I18: 112000 | J18: 108000
C19: 81 | D19: 0.031876458 | G19: =G18+1 -> 11 | H19: =G19+1 -> 12 | I19: 108000 | J19: 104000
C20: 82 | D20: 0.03680866 | G20: =G19+1 -> 12 | H20: =G20+1 -> 13 | I20: 104000 | J20: 101000
... C37: 99 | D37: 0.3509234 | G37: =G36+1 -> 29 | H37: =G37+1 -> 30 | I37: 23800 | J37: 0

Sheet Q2 Working
B2: Question 5: Working
B5: Parameters | H5: Results
B6: Single premium | E6: 140000
B7: Initial exp (fixed amount) | E7: 10000
B8: Renewal exp (fixed amount) | E8: 100 | H8: Total EPV of profit
B9: Sum assured | E9: 50000 | H9: (a) …with no reserves | J9: =SUM(Q26:Q55) -> 31358.95 | K9: 2 | L9: =K9+SUM(G23:O23,P21:Q21) -> 22
B10: Annuity benefit | E10: 10000 | H10: (b) …with reserves | J10: =SUM(V26:V55) -> 3898.8711 | K10: 2 | L10: =K10+SUM(R21:V21) -> 12
B11: Interest earned on reserves and cashflows | E11: 0.06
B12: RDR | E12: 0.09 | H12: (c) Profit margin with reserves | J12: =J10/E6 -> 0.027849079 | K12: 1 | L12: =K12 -> 1
B13: Term | E13: 30 | H13: (d) DPP with reserves | J13: =_xlfn.MINIFS(D26:D55,W26:W55,">"&0) -> 11 | K13: 2 | L13: =K13+W21 -> 4
P21: 2 | Q21: 2 | R21: 2 | S21: 2 | T21: 2 | U21: 2 | V21: 2 | W21: 2
P22: Calculate EPV profit without allowance for reserves | R22: Calculations which allow for reserves
A23: Age at year | B23: Age at year | C23: Time at year | D23: Time at year | G23: 1 | H23: 2 | I23: 2 | J23: 1 | K23: 2 | L23: 2 | M23: 2 | N23: 2 | O23: 2
A24: start (t-1) | B24: end (t) | C24: start (t-1) | D24: end (t) | E24: Start of yr | F24: End of yr | G24: Premium | H24: Expenses | I24: Interest | J24: q(x+t-1) | K24: Death | L24: p(x+t-1) | M24: Survival | N24: Expected | O24: (t-1)_px | P24: Discount | Q24: EPV of | R24: Inc in | S24: Interest on | T24: Profit | U24: Profit | V24: EPV of | W24: Sum of EPV(Profit)
E25: Reserve | F25: Reserve | K25: Benefit | M25: Benefit | N25: Cashflow | P25: v^t @RDR | Q25: Cashflow | R25: Reserve | S25: Reserve | T25: Vector | U25: Signature | V25: Profit | W25: to find DPP
A26: 70 | B26: =A26+1 -> 71 | C26: 0 | D26: =C26+1 -> 1 | E26: ='Q2 Base'!I8 -> 0 | F26: ='Q2 Base'!J8 -> 144000 | G26: =IF(C26=0,$E$6,0) -> 140000 | H26: =IF(C26=0,$E$7,$E$8) -> 10000 | I26: =(G26-H26)*E$11 -> 7800 | J26: ='Q2 Base'!D8 -> 0.0078176305 | K26: =E$9*J26 -> 390.88153 | L26: =1-J26 -> 0.99218237 | M26: =L26*$E$7 -> 9921.8237 | N26: =G26-H26+I26-K26-M26 -> 127487.29 | O26: 1 | P26: =(1+$E$12)^-D26 -> 0.91743119 | Q26: =N26*O26*P26 -> 116960.82 | R26: =F26*L26-E26 -> 142874.26 | S26: =E$11*E26 -> 0 | T26: =N26-R26+S26 -> -15386.966 | U26: =T26*O26 -> -15386.966 | V26: =U26*P26 -> -14116.483 | W26: =SUM(V$26:V26) -> -14116.483
A27: =A26+1 -> 71 | B27: =A27+1 -> 72 | C27: =C26+1 -> 1 | D27: =C27+1 -> 2 | E27: ='Q2 Base'!I9 -> 144000 | F27: ='Q2 Base'!J9 -> 141000 | G27: =IF(C27=0,$E$6,0) -> 0 | H27: =IF(C27=0,$E$7,$E$8) -> 100 | I27: =(G27-H27)*E$11 -> -6 | J27: ='Q2 Base'!D9 -> 0.0087215052 | K27: =E$9*J27 -> 436.07526 | L27: =1-J27 -> 0.99127849 | M27: =L27*$E$7 -> 9912.7849 | N27: =G27-H27+I27-K27-M27 -> -10454.86 | O27: =L26*O26 -> 0.99218237 | P27: =(1+$E$12)^-D27 -> 0.84167999 | Q27: =N27*O27*P27 -> -8730.8543 | R27: =F27*L27-E27 -> -4229.7322 | S27: =E$11*E27 -> 8640 | T27: =N27-R27+S27 -> 2414.872 | U27: =T27*O27 -> 2395.9934 | V27: =U27*P27 -> 2016.6597 | W27: =SUM(V$26:V27) -> -12099.823
A28: =A27+1 -> 72 | B28: =A28+1 -> 73 | C28: =C27+1 -> 2 | D28: =C28+1 -> 3 | E28: ='Q2 Base'!I10 -> 141000 | F28: ='Q2 Base'!J10 -> 137000 | G28: =IF(C28=0,$E$6,0) -> 0 | H28: =IF(C28=0,$E$7,$E$8) -> 100 | I28: =(G28-H28)*E$11 -> -6 | J28: ='Q2 Base'!D10 -> 0.0097672252 | K28: =E$9*J28 -> 488.36126 | L28: =1-J28 -> 0.99023277 | M28: =L28*$E$7 -> 9902.3277 | N28: =G28-H28+I28-K28-M28 -> -10496.689 | O28: =L27*O27 -> 0.98352905 | P28: =(1+$E$12)^-D28 -> 0.77218348 | Q28: =N28*O28*P28 -> -7971.8667 | R28: =F28*L28-E28 -> -5338.1098 | S28: =E$11*E28 -> 8460 | T28: =N28-R28+S28 -> 3301.4208 | U28: =T28*O28 -> 3247.0433 | V28: =U28*P28 -> 2507.3132 | W28: =SUM(V$26:V28) -> -9592.51
A29: =A28+1 -> 73 | B29: =A29+1 -> 74 | C29: =C28+1 -> 3 | D29: =C29+1 -> 4 | E29: ='Q2 Base'!I11 -> 137000 | F29: ='Q2 Base'!J11 -> 134000 | G29: =IF(C29=0,$E$6,0) -> 0 | H29: =IF(C29=0,$E$7,$E$8) -> 100 | I29: =(G29-H29)*E$11 -> -6 | J29: ='Q2 Base'!D11 -> 0.010982639 | K29: =E$9*J29 -> 549.13193 | L29: =1-J29 -> 0.98901736 | M29: =L29*$E$7 -> 9890.1736 | N29: =G29-H29+I29-K29-M29 -> -10545.306 | O29: =L28*O28 -> 0.9739227 | P29: =(1+$E$12)^-D29 -> 0.70842521 | Q29: =N29*O29*P29 -> -7275.7482 | R29: =F29*L29-E29 -> -4471.6736 | S29: =E$11*E29 -> 8220 | T29: =N29-R29+S29 -> 2146.368 | U29: =T29*O29 -> 2090.3965 | V29: =U29*P29 -> 1480.8896 | W29: =SUM(V$26:V29) -> -8111.6204
A30: =A29+1 -> 74 | B30: =A30+1 -> 75 | C30: =C29+1 -> 4 | D30: =C30+1 -> 5 | E30: ='Q2 Base'!I12 -> 134000 | F30: ='Q2 Base'!J12 -> 130000 | G30: =IF(C30=0,$E$6,0) -> 0 | H30: =IF(C30=0,$E$7,$E$8) -> 100 | I30: =(G30-H30)*E$11 -> -6 | J30: ='Q2 Base'!D12 -> 0.012401652 | K30: =E$9*J30 -> 620.08262 | L30: =1-J30 -> 0.98759835 | M30: =L30*$E$7 -> 9875.9835 | N30: =G30-H30+I30-K30-M30 -> -10602.066 | O30: =L29*O29 -> 0.96322646 | P30: =(1+$E$12)^-D30 -> 0.64993139 | Q30: =N30*O30*P30 -> -6637.2232 | R30: =F30*L30-E30 -> -5612.2148 | S30: =E$11*E30 -> 8040 | T30: =N30-R30+S30 -> 3050.1487 | U30: =T30*O30 -> 2937.9839 | V30: =U30*P30 -> 1909.488 | W30: =SUM(V$26:V30) -> -6202.1324
A31: =A30+1 -> 75 | B31: =A31+1 -> 76 | C31: =C30+1 -> 5 | D31: =C31+1 -> 6 | E31: ='Q2 Base'!I13 -> 130000 | F31: ='Q2 Base'!J13 -> 126000 | G31: =IF(C31=0,$E$6,0) -> 0 | H31: =IF(C31=0,$E$7,$E$8) -> 100 | I31: =(G31-H31)*E$11 -> -6 | J31: ='Q2 Base'!D13 -> 0.014062731 | K31: =E$9*J31 -> 703.13657 | L31: =1-J31 -> 0.98593727 | M31: =L31*$E$7 -> 9859.3727 | N31: =G31-H31+I31-K31-M31 -> -10668.509 | O31: =L30*O30 -> 0.95128086 | P31: =(1+$E$12)^-D31 -> 0.59626733 | Q31: =N31*O31*P31 -> -6051.3672 | R31: =F31*L31-E31 -> -5771.9042 | S31: =E$11*E31 -> 7800 | T31: =N31-R31+S31 -> 2903.3949 | U31: =T31*O31 -> 2761.944 | V31: =U31*P31 -> 1646.857 | W31: =SUM(V$26:V31) -> -4555.2755
A32: =A31+1 -> 76 | B32: =A32+1 -> 77 | C32: =C31+1 -> 6 | D32: =C32+1 -> 7 | E32: ='Q2 Base'!I14 -> 126000 | F32: ='Q2 Base'!J14 -> 123000 | G32: =IF(C32=0,$E$6,0) -> 0 | H32: =IF(C32=0,$E$7,$E$8) -> 100 | I32: =(G32-H32)*E$11 -> -6 | J32: ='Q2 Base'!D14 -> 0.016005163 | K32: =E$9*J32 -> 800.25817 | L32: =1-J32 -> 0.98399484 | M32: =L32*$E$7 -> 9839.9484 | N32: =G32-H32+I32-K32-M32 -> -10746.207 | O32: =L31*O31 -> 0.93790325 | P32: =(1+$E$12)^-D32 -> 0.54703424 | Q32: =N32*O32*P32 -> -5513.5046 | R32: =F32*L32-E32 -> -4968.6351 | S32: =E$11*E32 -> 7560 | T32: =N32-R32+S32 -> 1782.4286 | U32: =T32*O32 -> 1671.7455 | V32: =U32*P32 -> 914.50205 | W32: =SUM(V$26:V32) -> -3640.7734
A33: =A32+1 -> 77 | B33: =A33+1 -> 78 | C33: =C32+1 -> 7 | D33: =C33+1 -> 8 | E33: ='Q2 Base'!I15 -> 123000 | F33: ='Q2 Base'!J15 -> 119000 | G33: =IF(C33=0,$E$6,0) -> 0 | H33: =IF(C33=0,$E$7,$E$8) -> 100 | I33: =(G33-H33)*E$11 -> -6 | J33: ='Q2 Base'!D15 -> 0.018277699 | K33: =E$9*J33 -> 913.88495 | L33: =1-J33 -> 0.9817223 | M33: =L33*$E$7 -> 9817.223 | N33: =G33-H33+I33-K33-M33 -> -10837.108 | O33: =L32*O32 -> 0.92289195 | P33: =(1+$E$12)^-D33 -> 0.50186628 | Q33: =N33*O33*P33 -> -5019.4054 | R33: =F33*L33-E33 -> -6175.0462 | S33: =E$11*E33 -> 7380 | T33: =N33-R33+S33 -> 2717.9382 | U33: =T33*O33 -> 2508.3633 | V33: =U33*P33 -> 1258.863 | W33: =SUM(V$26:V33) -> -2381.9105
A34: =A33+1 -> 78 | B34: =A34+1 -> 79 | C34: =C33+1 -> 8 | D34: =C34+1 -> 9 | E34: ='Q2 Base'!I16 -> 119000 | F34: ='Q2 Base'!J16 -> 115000 | G34: =IF(C34=0,$E$6,0) -> 0 | H34: =IF(C34=0,$E$7,$E$8) -> 100 | I34: =(G34-H34)*E$11 -> -6 | J34: ='Q2 Base'!D16 -> 0.020931815 | K34: =E$9*J34 -> 1046.5908 | L34: =1-J34 -> 0.97906818 | M34: =L34*$E$7 -> 9790.6818 | N34: =G34-H34+I34-K34-M34 -> -10943.273 | O34: =L33*O33 -> 0.90602361 | P34: =(1+$E$12)^-D34 -> 0.46042778 | Q34: =N34*O34*P34 -> -4565.0785 | R34: =F34*L34-E34 -> -6407.1588 | S34: =E$11*E34 -> 7140 | T34: =N34-R34+S34 -> 2603.8862 | U34: =T34*O34 -> 2359.1823 | V34: =U34*P34 -> 1086.2331 | W34: =SUM(V$26:V34) -> -1295.6774
A35: =A34+1 -> 79 | B35: =A35+1 -> 80 | C35: =C34+1 -> 9 | D35: =C35+1 -> 10 | E35: ='Q2 Base'!I17 -> 115000 | F35: ='Q2 Base'!J17 -> 112000 | G35: =IF(C35=0,$E$6,0) -> 0 | H35: =IF(C35=0,$E$7,$E$8) -> 100 | I35: =(G35-H35)*E$11 -> -6 | J35: ='Q2 Base'!D17 -> 0.024032269 | K35: =E$9*J35 -> 1201.6135 | L35: =1-J35 -> 0.97596773 | M35: =L35*$E$7 -> 9759.6773 | N35: =G35-H35+I35-K35-M35 -> -11067.291 | O35: =L34*O34 -> 0.88705889 | P35: =(1+$E$12)^-D35 -> 0.42241081 | Q35: =N35*O35*P35 -> -4146.95 | R35: =F35*L35-E35 -> -5691.6141 | S35: =E$11*E35 -> 6900 | T35: =N35-R35+S35 -> 1524.3234 | U35: =T35*O35 -> 1352.1646 | V35: =U35*P35 -> 571.16894 | W35: =SUM(V$26:V35) -> -724.50844
A36: =A35+1 -> 80 | B36: =A36+1 -> 81 | C36: =C35+1 -> 10 | D36: =C36+1 -> 11 | E36: ='Q2 Base'!I18 -> 112000 | F36: ='Q2 Base'!J18 -> 108000 | G36: =IF(C36=0,$E$6,0) -> 0 | H36: =IF(C36=0,$E$7,$E$8) -> 100 | I36: =(G36-H36)*E$11 -> -6 | J36: ='Q2 Base'!D18 -> 0.027651675 | K36: =E$9*J36 -> 1382.5837 | L36: =1-J36 -> 0.97234833 | M36: =L36*$E$7 -> 9723.4833 | N36: =G36-H36+I36-K36-M36 -> -11212.067 | O36: =L35*O35 -> 0.86574086 | P36: =(1+$E$12)^-D36 -> 0.38753285 | Q36: =N36*O36*P36 -> -3761.6823 | R36: =F36*L36-E36 -> -6986.3808 | S36: =E$11*E36 -> 6720 | T36: =N36-R36+S36 -> 2494.3139 | U36: =T36*O36 -> 2159.4294 | V36: =U36*P36 -> 836.84984 | W36: =SUM(V$26:V36) -> 112.3414
A37: =A36+1 -> 81 | B37: =A37+1 -> 82 | C37: =C36+1 -> 11 | D37: =C37+1 -> 12 | E37: ='Q2 Base'!I19 -> 108000 | F37: ='Q2 Base'!J19 -> 104000 | G37: =IF(C37=0,$E$6,0) -> 0 | H37: =IF(C37=0,$E$7,$E$8) -> 100 | I37: =(G37-H37)*E$11 -> -6 | J37: ='Q2 Base'!D19 -> 0.031876458 | K37: =E$9*J37 -> 1593.8229 | L37: =1-J37 -> 0.96812354 | M37: =L37*$E$7 -> 9681.2354 | N37: =G37-H37+I37-K37-M37 -> -11381.058 | O37: =L36*O36 -> 0.84180167 | P37: =(1+$E$12)^-D37 -> 0.35553473 | Q37: =N37*O37*P37 -> -3406.2338 | R37: =F37*L37-E37 -> -7315.1516 | S37: =E$11*E37 -> 6480 | T37: =N37-R37+S37 -> 2414.0933 | U37: =T37*O37 -> 2032.1878 | V37: =U37*P37 -> 722.51332 | W37: =SUM(V$26:V37) -> 834.85472
A38: =A37+1 -> 82 | B38: =A38+1 -> 83 | C38: =C37+1 -> 12 | D38: =C38+1 -> 13 | E38: ='Q2 Base'!I20 -> 104000 | F38: ='Q2 Base'!J20 -> 101000 | G38: =IF(C38=0,$E$6,0) -> 0 | H38: =IF(C38=0,$E$7,$E$8) -> 100 | I38: =(G38-H38)*E$11 -> -6 | J38: ='Q2 Base'!D20 -> 0.03680866 | K38: =E$9*J38 -> 1840.433 | L38: =1-J38 -> 0.96319134 | M38: =L38*$E$7 -> 9631.9134 | N38: =G38-H38+I38-K38-M38 -> -11578.346 | O38: =L37*O37 -> 0.81496802 | P38: =(1+$E$12)^-D38 -> 0.32617865 | Q38: =N38*O38*P38 -> -3077.8158 | R38: =F38*L38-E38 -> -6717.6746 | S38: =E$11*E38 -> 6240 | T38: =N38-R38+S38 -> 1379.3282 | U38: =T38*O38 -> 1124.1084 | V38: =U38*P38 -> 366.66015 | W38: =SUM(V$26:V38) -> 1201.5149
... A54: =A53+1 -> 98 | B54: =A54+1 -> 99 | C54: =C53+1 -> 28 | D54: =C54+1 -> 29 | E54: ='Q2 Base'!I36 -> 38100 | F54: ='Q2 Base'!J36 -> 23800 | G54: =IF(C54=0,$E$6,0) -> 0 | H54: =IF(C54=0,$E$7,$E$8) -> 100 | I54: =(G54-H54)*E$11 -> -6 | J54: ='Q2 Base'!D36 -> 0.32064926 | K54: =E$9*J54 -> 16032.463 | L54: =1-J54 -> 0.67935074 | M54: =L54*$E$7 -> 6793.5074 | N54: =G54-H54+I54-K54-M54 -> -22931.97 | O54: =L53*O53 -> 0.07939935 | P54: =(1+$E$12)^-D54 -> 0.082154538 | Q54: =N54*O54*P54 -> -149.58563 | R54: =F54*L54-E54 -> -21931.452 | S54: =E$11*E54 -> 2286 | T54: =N54-R54+S54 -> 1285.482 | U54: =T54*O54 -> 102.06644 | V54: =U54*P54 -> 8.3852211 | W54: =SUM(V$26:V54) -> 3894.4597
A55: =A54+1 -> 99 | B55: =A55+1 -> 100 | C55: =C54+1 -> 29 | D55: =C55+1 -> 30 | E55: ='Q2 Base'!I37 -> 23800 | F55: ='Q2 Base'!J37 -> 0 | G55: =IF(C55=0,$E$6,0) -> 0 | H55: =IF(C55=0,$E$7,$E$8) -> 100 | I55: =(G55-H55)*E$11 -> -6 | J55: ='Q2 Base'!D37 -> 0.3509234 | K55: =E$9*J55 -> 17546.17 | L55: =1-J55 -> 0.6490766 | M55: =L55*$E$7 -> 6490.766 | N55: =G55-H55+I55-K55-M55 -> -24142.936 | O55: =L54*O54 -> 0.053940007 | P55: =(1+$E$12)^-D55 -> 0.075371136 | Q55: =N55*O55*P55 -> -98.153581 | R55: =F55*L55-E55 -> -23800 | S55: =E$11*E55 -> 1428 | T55: =N55-R55+S55 -> 1085.0638 | U55: =T55*O55 -> 58.528352 | V55: =U55*P55 -> 4.4113484 | W55: =SUM($V$26:V55) -> 3898.8711

Sheet Q2 Working 2(IRR)
B2: Question 5: Working
B5: Parameters | H5: Results
B6: Single premium | E6: 140000
B7: Initial exp (fixed amount) | E7: 10000
B8: Renewal exp (fixed amount) | E8: 100 | H8: Total EPV of profit
B9: Sum assured | E9: 50000
B10: Annuity benefit | E10: 10000 | H10: …with reserves | J10: =SUM(V26:V55) -> 0.00093314101
B11: Interest earned on reserves and cashflows | E11: 0.06
B12: IRR | E12: =J13 -> 0.13368106
B13: Term | E13: 30 | H13: (e) IRR | J13: 0.13368106 | K13: 4
P22: Calculate EPV profit without allowance for reserves | R22: Calculations which allow for reserves
A23: Age at year | B23: Age at year | C23: Time at year | D23: Time at year
A24: start (t-1) | B24: end (t) | C24: start (t-1) | D24: end (t) | E24: Start of yr | F24: End of yr | G24: Premium | H24: Expenses | I24: Interest | J24: q(x+t-1) | K24: Death | L24: p(x+t-1) | M24: Survival | N24: Expected | O24: (t-1)_px | P24: Discount | Q24: EPV of | R24: Inc in | S24: Interest on | T24: Profit | U24: Profit | V24: EPV of | W24: Sum of EPV(Profit)
E25: Reserve | F25: Reserve | K25: Benefit | M25: Benefit | N25: Cashflow | P25: v^t @RDR | Q25: Cashflow | R25: Reserve | S25: Reserve | T25: Vector | U25: Signature | V25: Profit | W25: to find DPP
A26: 70 | B26: =A26+1 -> 71 | C26: 0 | D26: =C26+1 -> 1 | E26: ='Q2 Base'!I8 -> 0 | F26: ='Q2 Base'!J8 -> 144000 | G26: =IF(C26=0,$E$6,0) -> 140000 | H26: =IF(C26=0,$E$7,$E$8) -> 10000 | I26: =(G26-H26)*E$11 -> 7800 | J26: ='Q2 Base'!D8 -> 0.0078176305 | K26: =E$9*J26 -> 390.88153 | L26: =1-J26 -> 0.99218237 | M26: =L26*$E$7 -> 9921.8237 | N26: =G26-H26+I26-K26-M26 -> 127487.29 | O26: 1 | P26: =(1+$E$12)^-D26 -> 0.8820823 | Q26: =N26*O26*P26 -> 112454.29 | R26: =F26*L26-E26 -> 142874.26 | S26: =E$11*E26 -> 0 | T26: =N26-R26+S26 -> -15386.966 | U26: =T26*O26 -> -15386.966 | V26: =U26*P26 -> -13572.571 | W26: =SUM(V$26:V26) -> -13572.571
A27: =A26+1 -> 71 | B27: =A27+1 -> 72 | C27: =C26+1 -> 1 | D27: =C27+1 -> 2 | E27: ='Q2 Base'!I9 -> 144000 | F27: ='Q2 Base'!J9 -> 141000 | G27: =IF(C27=0,$E$6,0) -> 0 | H27: =IF(C27=0,$E$7,$E$8) -> 100 | I27: =(G27-H27)*E$11 -> -6 | J27: ='Q2 Base'!D9 -> 0.0087215052 | K27: =E$9*J27 -> 436.07526 | L27: =1-J27 -> 0.99127849 | M27: =L27*$E$7 -> 9912.7849 | N27: =G27-H27+I27-K27-M27 -> -10454.86 | O27: =L26*O26 -> 0.99218237 | P27: =(1+$E$12)^-D27 -> 0.77806918 | Q27: =N27*O27*P27 -> -8071.0112 | R27: =F27*L27-E27 -> -4229.7322 | S27: =E$11*E27 -> 8640 | T27: =N27-R27+S27 -> 2414.872 | U27: =T27*O27 -> 2395.9934 | V27: =U27*P27 -> 1864.2487 | W27: =SUM(V$26:V27) -> -11708.322
A28: =A27+1 -> 72 | B28: =A28+1 -> 73 | C28: =C27+1 -> 2 | D28: =C28+1 -> 3 | E28: ='Q2 Base'!I10 -> 141000 | F28: ='Q2 Base'!J10 -> 137000 | G28: =IF(C28=0,$E$6,0) -> 0 | H28: =IF(C28=0,$E$7,$E$8) -> 100 | I28: =(G28-H28)*E$11 -> -6 | J28: ='Q2 Base'!D10 -> 0.0097672252 | K28: =E$9*J28 -> 488.36126 | L28: =1-J28 -> 0.99023277 | M28: =L28*$E$7 -> 9902.3277 | N28: =G28-H28+I28-K28-M28 -> -10496.689 | O28: =L27*O27 -> 0.98352905 | P28: =(1+$E$12)^-D28 -> 0.68632105 | Q28: =N28*O28*P28 -> -7085.4403 | R28: =F28*L28-E28 -> -5338.1098 | S28: =E$11*E28 -> 8460 | T28: =N28-R28+S28 -> 3301.4208 | U28: =T28*O28 -> 3247.0433 | V28: =U28*P28 -> 2228.5142 | W28: =SUM(V$26:V28) -> -9479.8079
A29: =A28+1 -> 73 | B29: =A29+1 -> 74 | C29: =C28+1 -> 3 | D29: =C29+1 -> 4 | E29: ='Q2 Base'!I11 -> 137000 | F29: ='Q2 Base'!J11 -> 134000 | G29: =IF(C29=0,$E$6,0) -> 0 | H29: =IF(C29=0,$E$7,$E$8) -> 100 | I29: =(G29-H29)*E$11 -> -6 | J29: ='Q2 Base'!D11 -> 0.010982639 | K29: =E$9*J29 -> 549.13193 | L29: =1-J29 -> 0.98901736 | M29: =L29*$E$7 -> 9890.1736 | N29: =G29-H29+I29-K29-M29 -> -10545.306 | O29: =L28*O28 -> 0.9739227 | P29: =(1+$E$12)^-D29 -> 0.60539165 | Q29: =N29*O29*P29 -> -6217.5614 | R29: =F29*L29-E29 -> -4471.6736 | S29: =E$11*E29 -> 8220 | T29: =N29-R29+S29 -> 2146.368 | U29: =T29*O29 -> 2090.3965 | V29: =U29*P29 -> 1265.5086 | W29: =SUM(V$26:V29) -> -8214.2993
A30: =A29+1 -> 74 | B30: =A30+1 -> 75 | C30: =C29+1 -> 4 | D30: =C30+1 -> 5 | E30: ='Q2 Base'!I12 -> 134000 | F30: ='Q2 Base'!J12 -> 130000 | G30: =IF(C30=0,$E$6,0) -> 0 | H30: =IF(C30=0,$E$7,$E$8) -> 100 | I30: =(G30-H30)*E$11 -> -6 | J30: ='Q2 Base'!D12 -> 0.012401652 | K30: =E$9*J30 -> 620.08262 | L30: =1-J30 -> 0.98759835 | M30: =L30*$E$7 -> 9875.9835 | N30: =G30-H30+I30-K30-M30 -> -10602.066 | O30: =L29*O29 -> 0.96322646 | P30: =(1+$E$12)^-D30 -> 0.53400526 | Q30: =N30*O30*P30 -> -5453.3635 | R30: =F30*L30-E30 -> -5612.2148 | S30: =E$11*E30 -> 8040 | T30: =N30-R30+S30 -> 3050.1487 | U30: =T30*O30 -> 2937.9839 | V30: =U30*P30 -> 1568.8989 | W30: =SUM(V$26:V30) -> -6645.4004
A31: =A30+1 -> 75 | B31: =A31+1 -> 76 | C31: =C30+1 -> 5 | D31: =C31+1 -> 6 | E31: ='Q2 Base'!I13 -> 130000 | F31: ='Q2 Base'!J13 -> 126000 | G31: =IF(C31=0,$E$6,0) -> 0 | H31: =IF(C31=0,$E$7,$E$8) -> 100 | I31: =(G31-H31)*E$11 -> -6 | J31: ='Q2 Base'!D13 -> 0.014062731 | K31: =E$9*J31 -> 703.13657 | L31: =1-J31 -> 0.98593727 | M31: =L31*$E$7 -> 9859.3727 | N31: =G31-H31+I31-K31-M31 -> -10668.509 | O31: =L30*O30 -> 0.95128086 | P31: =(1+$E$12)^-D31 -> 0.47103659 | Q31: =N31*O31*P31 -> -4780.4319 | R31: =F31*L31-E31 -> -5771.9042 | S31: =E$11*E31 -> 7800 | T31: =N31-R31+S31 -> 2903.3949 | U31: =T31*O31 -> 2761.944 | V31: =U31*P31 -> 1300.9767 | W31: =SUM(V$26:V31) -> -5344.4237
A32: =A31+1 -> 76 | B32: =A32+1 -> 77 | C32: =C31+1 -> 6 | D32: =C32+1 -> 7 | E32: ='Q2 Base'!I14 -> 126000 | F32: ='Q2 Base'!J14 -> 123000 | G32: =IF(C32=0,$E$6,0) -> 0 | H32: =IF(C32=0,$E$7,$E$8) -> 100 | I32: =(G32-H32)*E$11 -> -6 | J32: ='Q2 Base'!D14 -> 0.016005163 | K32: =E$9*J32 -> 800.25817 | L32: =1-J32 -> 0.98399484 | M32: =L32*$E$7 -> 9839.9484 | N32: =G32-H32+I32-K32-M32 -> -10746.207 | O32: =L31*O31 -> 0.93790325 | P32: =(1+$E$12)^-D32 -> 0.41549304 | Q32: =N32*O32*P32 -> -4187.7136 | R32: =F32*L32-E32 -> -4968.6351 | S32: =E$11*E32 -> 7560 | T32: =N32-R32+S32 -> 1782.4286 | U32: =T32*O32 -> 1671.7455 | V32: =U32*P32 -> 694.59863 | W32: =SUM(V$26:V32) -> -4649.8251
A33: =A32+1 -> 77 | B33: =A33+1 -> 78 | C33: =C32+1 -> 7 | D33: =C33+1 -> 8 | E33: ='Q2 Base'!I15 -> 123000 | F33: ='Q2 Base'!J15 -> 119000 | G33: =IF(C33=0,$E$6,0) -> 0 | H33: =IF(C33=0,$E$7,$E$8) -> 100 | I33: =(G33-H33)*E$11 -> -6 | J33: ='Q2 Base'!D15 -> 0.018277699 | K33: =E$9*J33 -> 913.88495 | L33: =1-J33 -> 0.9817223 | M33: =L33*$E$7 -> 9817.223 | N33: =G33-H33+I33-K33-M33 -> -10837.108 | O33: =L32*O32 -> 0.92289195 | P33: =(1+$E$12)^-D33 -> 0.36649905 | Q33: =N33*O33*P33 -> -3665.5328 | R33: =F33*L33-E33 -> -6175.0462 | S33: =E$11*E33 -> 7380 | T33: =N33-R33+S33 -> 2717.9382 | U33: =T33*O33 -> 2508.3633 | V33: =U33*P33 -> 919.31278 | W33: =SUM(V$26:V33) -> -3730.5123
A34: =A33+1 -> 78 | B34: =A34+1 -> 79 | C34: =C33+1 -> 8 | D34: =C34+1 -> 9 | E34: ='Q2 Base'!I16 -> 119000 | F34: ='Q2 Base'!J16 -> 115000 | G34: =IF(C34=0,$E$6,0) -> 0 | H34: =IF(C34=0,$E$7,$E$8) -> 100 | I34: =(G34-H34)*E$11 -> -6 | J34: ='Q2 Base'!D16 -> 0.020931815 | K34: =E$9*J34 -> 1046.5908 | L34: =1-J34 -> 0.97906818 | M34: =L34*$E$7 -> 9790.6818 | N34: =G34-H34+I34-K34-M34 -> -10943.273 | O34: =L33*O33 -> 0.90602361 | P34: =(1+$E$12)^-D34 -> 0.32328233 | Q34: =N34*O34*P34 -> -3205.3001 | R34: =F34*L34-E34 -> -6407.1588 | S34: =E$11*E34 -> 7140 | T34: =N34-R34+S34 -> 2603.8862 | U34: =T34*O34 -> 2359.1823 | V34: =U34*P34 -> 762.68196 | W34: =SUM(V$26:V34) -> -2967.8304
A35: =A34+1 -> 79 | B35: =A35+1 -> 80 | C35: =C34+1 -> 9 | D35: =C35+1 -> 10 | E35: ='Q2 Base'!I17 -> 115000 | F35: ='Q2 Base'!J17 -> 112000 | G35: =IF(C35=0,$E$6,0) -> 0 | H35: =IF(C35=0,$E$7,$E$8) -> 100 | I35: =(G35-H35)*E$11 -> -6 | J35: ='Q2 Base'!D17 -> 0.024032269 | K35: =E$9*J35 -> 1201.6135 | L35: =1-J35 -> 0.97596773 | M35: =L35*$E$7 -> 9759.6773 | N35: =G35-H35+I35-K35-M35 -> -11067.291 | O35: =L34*O34 -> 0.88705889 | P35: =(1+$E$12)^-D35 -> 0.28516162 | Q35: =N35*O35*P35 -> -2799.5282 | R35: =F35*L35-E35 -> -5691.6141 | S35: =E$11*E35 -> 6900 | T35: =N35-R35+S35 -> 1524.3234 | U35: =T35*O35 -> 1352.1646 | V35: =U35*P35 -> 385.58545 | W35: =SUM(V$26:V35) -> -2582.2449
A36: =A35+1 -> 80 | B36: =A36+1 -> 81 | C36: =C35+1 -> 10 | D36: =C36+1 -> 11 | E36: ='Q2 Base'!I18 -> 112000 | F36: ='Q2 Base'!J18 -> 108000 | G36: =IF(C36=0,$E$6,0) -> 0 | H36: =IF(C36=0,$E$7,$E$8) -> 100 | I36: =(G36-H36)*E$11 -> -6 | J36: ='Q2 Base'!D18 -> 0.027651675 | K36: =E$9*J36 -> 1382.5837 | L36: =1-J36 -> 0.97234833 | M36: =L36*$E$7 -> 9723.4833 | N36: =G36-H36+I36-K36-M36 -> -11212.067 | O36: =L35*O35 -> 0.86574086 | P36: =(1+$E$12)^-D36 -> 0.25153602 | Q36: =N36*O36*P36 -> -2441.5958 | R36: =F36*L36-E36 -> -6986.3808 | S36: =E$11*E36 -> 6720 | T36: =N36-R36+S36 -> 2494.3139 | U36: =T36*O36 -> 2159.4294 | V36: =U36*P36 -> 543.17427 | W36: =SUM(V$26:V36) -> -2039.0706
A37: =A36+1 -> 81 | B37: =A37+1 -> 82 | C37: =C36+1 -> 11 | D37: =C37+1 -> 12 | E37: ='Q2 Base'!I19 -> 108000 | F37: ='Q2 Base'!J19 -> 104000 | G37: =IF(C37=0,$E$6,0) -> 0 | H37: =IF(C37=0,$E$7,$E$8) -> 100 | I37: =(G37-H37)*E$11 -> -6 | J37: ='Q2 Base'!D19 -> 0.031876458 | K37: =E$9*J37 -> 1593.8229 | L37: =1-J37 -> 0.96812354 | M37: =L37*$E$7 -> 9681.2354 | N37: =G37-H37+I37-K37-M37 -> -11381.058 | O37: =L36*O36 -> 0.84180167 | P37: =(1+$E$12)^-D37 -> 0.22187547 | Q37: =N37*O37*P37 -> -2125.6987 | R37: =F37*L37-E37 -> -7315.1516 | S37: =E$11*E37 -> 6480 | T37: =N37-R37+S37 -> 2414.0933 | U37: =T37*O37 -> 2032.1878 | V37: =U37*P37 -> 450.89261 | W37: =SUM(V$26:V37) -> -1588.178
A38: =A37+1 -> 82 | B38: =A38+1 -> 83 | C38: =C37+1 -> 12 | D38: =C38+1 -> 13 | E38: ='Q2 Base'!I20 -> 104000 | F38: ='Q2 Base'!J20 -> 101000 | G38: =IF(C38=0,$E$6,0) -> 0 | H38: =IF(C38=0,$E$7,$E$8) -> 100 | I38: =(G38-H38)*E$11 -> -6 | J38: ='Q2 Base'!D20 -> 0.03680866 | K38: =E$9*J38 -> 1840.433 | L38: =1-J38 -> 0.96319134 | M38: =L38*$E$7 -> 9631.9134 | N38: =G38-H38+I38-K38-M38 -> -11578.346 | O38: =L37*O37 -> 0.81496802 | P38: =(1+$E$12)^-D38 -> 0.19571242 | Q38: =N38*O38*P38 -> -1846.7389 | R38: =F38*L38-E38 -> -6717.6746 | S38: =E$11*E38 -> 6240 | T38: =N38-R38+S38 -> 1379.3282 | U38: =T38*O38 -> 1124.1084 | V38: =U38*P38 -> 220.00198 | W38: =SUM(V$26:V38) -> -1368.1761
... A54: =A53+1 -> 98 | B54: =A54+1 -> 99 | C54: =C53+1 -> 28 | D54: =C54+1 -> 29 | E54: ='Q2 Base'!I36 -> 38100 | F54: ='Q2 Base'!J36 -> 23800 | G54: =IF(C54=0,$E$6,0) -> 0 | H54: =IF(C54=0,$E$7,$E$8) -> 100 | I54: =(G54-H54)*E$11 -> -6 | J54: ='Q2 Base'!D36 -> 0.32064926 | K54: =E$9*J54 -> 16032.463 | L54: =1-J54 -> 0.67935074 | M54: =L54*$E$7 -> 6793.5074 | N54: =G54-H54+I54-K54-M54 -> -22931.97 | O54: =L53*O53 -> 0.07939935 | P54: =(1+$E$12)^-D54 -> 0.026288397 | Q54: =N54*O54*P54 -> -47.86548 | R54: =F54*L54-E54 -> -21931.452 | S54: =E$11*E54 -> 2286 | T54: =N54-R54+S54 -> 1285.482 | U54: =T54*O54 -> 102.06644 | V54: =U54*P54 -> 2.683163 | W54: =SUM(V$26:V54) -> -1.3562533
A55: =A54+1 -> 99 | B55: =A55+1 -> 100 | C55: =C54+1 -> 29 | D55: =C55+1 -> 30 | E55: ='Q2 Base'!I37 -> 23800 | F55: ='Q2 Base'!J37 -> 0 | G55: =IF(C55=0,$E$6,0) -> 0 | H55: =IF(C55=0,$E$7,$E$8) -> 100 | I55: =(G55-H55)*E$11 -> -6 | J55: ='Q2 Base'!D37 -> 0.3509234 | K55: =E$9*J55 -> 17546.17 | L55: =1-J55 -> 0.6490766 | M55: =L55*$E$7 -> 6490.766 | N55: =G55-H55+I55-K55-M55 -> -24142.936 | O55: =L54*O54 -> 0.053940007 | P55: =(1+$E$12)^-D55 -> 0.02318853 | Q55: =N55*O55*P55 -> -30.19773 | R55: =F55*L55-E55 -> -23800 | S55: =E$11*E55 -> 1428 | T55: =N55-R55+S55 -> 1085.0638 | U55: =T55*O55 -> 58.528352 | V55: =U55*P55 -> 1.3571864 | W55: =SUM($V$26:V55) -> 0.00093314101

Sheet Q2 Answers
A2: Question 2: Answers
B6: Results
B9: Total EPV of profit
B10: (a) …with no reserves | D10: ='Q2 Working'!J9 -> 31358.95 | E10: ='Q2 Working'!L9 -> 22
B11: (b) …with reserves | D11: ='Q2 Working'!J10 -> 3898.8711 | E11: ='Q2 Working'!L10 -> 12
B13: (c) Profit margin with reserves | D13: ='Q2 Working'!J12 -> 0.027849079 | E13: ='Q2 Working'!L12 -> 1
B14: (d) DPP with reserves | D14: ='Q2 Working'!J13 -> 11 | E14: ='Q2 Working'!L13 -> 4
B16: (e) IRR | D16: ='Q2 Working 2(IRR)'!J13 -> 0.13368106 | E16: ='Q2 Working 2(IRR)'!K13 -> 4
E18: =SUM(E10:E16) -> 43

Sheet Part B mark scheme
C3: Mark scheme for written comments about Q1
C5: B) "Tell Alex your results for Q1 (b),(c) , (d) and (e) and explain, with reasons, how they compare to each other and whether they seem reasonable."
C7: Marks | D7: (Where students have got incorrect answers, credit will be given for reasonable explanations provided answers are stated.)
C8: 2 | D8: Statement of results, ie. All four results are stated or it is explained where they are incomplete.
C9: 2 | D9: The net premium is lower than the gross premium (for a flat SA), which makes sense since the gross premium will be set to allow us to make a profit (and cover expenses.)
C10: 2 | D10: Our trapezium rule calculation gives approximately the same answer as Thiele's equation (2% different).
C11: 2 | D11: …This is reassuring because it provides a check that the calculation is approximately correct.
C12: 2 | D12: V(0) is negative for the gross premium policy values calculations, which we expect since we're assuming no expenses and it is higher than the net premium, ie more income reduces the policy value.
C13: 2 | D13: …This means the policy has to continue for a couple of years before we achieve the profit we are expecting.
C14: 2 | D14: …There is a lapse risk during that period
C15: 2 | D15: The decreasing sum assured is the same value on average as the flat sum assured
C16: 2 | D16: …But V(0) is lower (more negative) than for the flat SA so the benefits must have a lower value (the income is unchanged)
C17: 2 | D17: …This makes sense because the sum assured is low at the higher ages where deaths are more likely
C18: 2 | D18: ..But it will have been at partly offset by having less discounting on average on the lump sum payments (because they are bigger earlier)
D19: Credit will be given for sensible comments about limitations, errors, etc. 2 marks per idea.
C21: Marks available for written content:
C22: 22+
C23: (Capped at 12)
C25: Mark scheme for style of writing:
C28: 0 | D28: No attempt made to write as a sensible email. It is written like an exam answer.
C29: 1 | D29: Written in a broadly appropriate format, but does not meet the criteria for 2 marks.
C30: 2 | D30: Written in a broadly appropriate format and at tone, writing or structure is suitable but only one.
C31: 3 | D31: Written in an appropriate format and at least two out of tone, writing or structure are suitable.
C32: 4 | D32: Written in an appropriate format and tone, writing or structure are all broadly suitable.
C33: 5 | D33: Meets the criteria above and is excellent in some respects
C34: 6 | D34: Meets the criteria above and is excellent in most respects
C36: A suitable format is email with salutation, paragraphs, a sign-off, etc
C37: A suitable tone is friendly but professional
C38: Suitable structure includes use of paragraphs, perhaps bullets and subheadings, and signposting. Eg, tell Alex what the email is for.
C39: Suitable writing includes correct spelling and punctuation, each sentence has a purpose and its meaning is clear

Sheet colour key
A1: Colour key
A3: Parameters
A4: Data/values
A5: Calculations
A6: Discontinuous formulas
A7: Value looked up from data
A8: Results
